Workbook

Sheet Índice
B1: 📚 INDICE DE RECOMENDACIONES - 2º CUATRI 2026 - LA CÁMPORA 📚
A2: Accedé a los links o ingresá directamente en las distintas hojas para ver toda la información ¡Éxitos!
A3: 1 | B3: Teoría del Estado
A4: 2 | B4: Teoría General del Derecho
A5: 3 | B5: Elementos del Derecho Civil
A6: 4 | B6: Derechos Humanos y Garantías
A7: 5 | B7: Elementos de Análisis Económico y Financiero
A8: 6 | B8: Elementos del Derecho Constitucional
A9: 7 | B9: Obligaciones Civiles y Comerciales
A10: 8 | B10: Contratos Civiles y Comerciales
A11: 9 | B11: Elementos del Derecho Penal y Procesal Penal
A12: 10 | B12: Elementos del Derecho Comercial
A13: 11 | B13: Elementos de Derechos Reales
A14: 12 | B14: Elementos de Derecho Procesal Civil
... A22: 20 | B22: Comisiones Recomendadas por la Red de Profesoras de la Facultad de Derecho
A23: Los comentarios e información de estas hojas fueron relevadas en las aulas y grupos de Whatsapp de estudiantes, esperamos que te sirvan para anotarte. Si cursaste en alguna comisión de la que no tengamos data o haya información incorrecta, no dudes en contarnos por MD en el Instagram @lacamporaderechouba.

Sheet TGD
A1: 📚 TEORÍA GENERAL DEL DERECHO - 2º CUATRI 2026 - LA CÁMPORA 📚
A2: N° | B2: COMISIÓN | C2: DÍAS | D2: MODALIDAD | E2: HORARIO | F2: NIVEL | G2: EXAMEN | H2: TOMA LISTA | I2: TOMA TPS | J2: COMENTARIO | K2: POSTURA POLITICA
A3: 6010 | B3: ALONSO-BOICO | C3: MA-VI | D3: PRESENCIAL | E3: 07:00-08:30 | F3: MEDIO | G3: ESCRITO | H3: NO | I3: NO | J3: Toman lo dado en clase, los parciales son de 3 preguntas a desarrollar. | K3: TECNICA
A4: 6073 | B4: ALONSO.-RANIERI D. | C4: LU-JU | D4: PRESENCIAL | E4: 07:00-08:30 | F4: MEDIO | G4: ESCRITO | H4: SI | I4: SI | J4: Es exigente pero no tanto, los profes son copados y las clases se prestan al debate, toman un tp que ayuda a levantar nota. Es importante estar al día con el material, los parciales se basan más en la teoria que en lo dado en clase. IMPORTANTE: En el primer cuatrimestre esta comisión no fue abierta por no llegar al mínimo de inscriptos que exige la Facultad. | K4: TECNICA
A5: 6050 | B5: ROSENKRANTZ-DIMITRIU | C5: LU-JU | D5: PRESENCIAL | E5: 07:00-08:30 | F5: MEDIO | G5: MIXTO | H5: SI | I5: NO | J5: Los profesores tiene buen trato con los estudiantes, no tienen ánimos de bochar y responden dudas sin problemas. Toman dos parciales, uno escrito a desarrollar y otro oral. IMPORTANTE: En el primer cuatrimestre esta comisión no fue abierta por no llegar al mínimo de inscriptos que exige la Facultad.
A6: 6000 | B6: ALEGRE-SEMINARIO LAURA | C6: MIE | D6: PRESENCIAL | E6: 07:00-10:00 | F6: ALTO | G6: ESCRITO | H6: SI | I6: NO | J6: Hay opiniones encontradas acerca del trato de los docentes con los estudiantes, poca llegada para responder y hacer llevadera la cursada que puede complicar la materia. // OTRA OPINIÓN: Buena comisión, se entiende todo y no tienen ánimos de bochar. Se aprende mucho y son exigentes
A7: 6011 | B7: ALONSO-BOICO | C7: MA-VI | D7: PRESENCIAL | E7: 08:30-10:00 | F7: MEDIO | G7: ESCRITO | H7: NO | I7: NO | J7: Toman lo dado en clase, los parciales son de 3 preguntas a desarrollar. Son Pro alumno | K7: TECNICA
A8: 6060 | B8: ALONSO-DUQUELSKY | C8: LU-JU | D8: PRESENCIAL | E8: 08:30-10:00 | F8: MEDIO | H8: NO | I8: SI | J8: Evalúan con 4tps (obligatorios) bastante sencillos y un tp final, cuenta la nota del último para el cierre de la materia. El profe es pro alumno, comprensivo y generoso con las notas. Las clases son muy divertidas y se analiza el derecho desde una perspectiva critica. | K8: APERTURA
A9: 6079 | B9: ALONSO.-RANIERI D. | C9: LU-JU | D9: PRESENCIAL | E9: 08:30-10:00 | F9: MEDIO | G9: ESCRITO | H9: SI | I9: SI | J9: * Es exigente pero no tanto, los profes son copados y las clases se prestan al debate, toman un tp que ayuda a levantar nota. Es importante estar al día con el material, los parciales se basan más en la teoria que en lo dado en clase. IMPORTANTE: En el primer cuatrimestre esta comisión no fue abierta por no llegar al mínimo de inscriptos que exige la Facultad.El 1er cuatri de 2026 fue abierta. | K9: CONSERVADORA
A10: 6031 | B10: MARTYNIUK-BARRERA L. | C10: LU-JU | D10: PRESENCIAL | E10: 08:30-10:00 | F10: MEDIO | G10: ESCRITO | H10: SI | J10: Buena cátedra, no tienen ánimos de bochar a nadie. Si bien no ponen notas altas los parciales no son dificiles (3 preguntas a desarrollar), la mayoría promociona. La profe tiene buena onda y la cursada es con perspectiva feminista, muy interesante.
A11: 6061 | B11: MARTYNIUK-HEFFES AGOS O.D. | C11: MA-VI | D11: PRESENCIAL | E11: 08:30-10:00 | F11: MEDIO | G11: MIXTO | H11: NO | I11: SI | J11: El profesor hace la clase llevadera. El primer parcial fue domiciliario y el segundo un trabajo en grupo a exponer.
A12: 6051 | B12: ROSENKRANTZ-ZULETA MARTÍN | C12: LU-JU | D12: PRESENCIAL | E12: 08:30-10:00 | F12: MEDIO | G12: ESCRITO | H12: SI | I12: NO | J12: Los profesores tiene buen trato con los estudiantes, no tienen ánimos de bochar y responden dudas sin problemas. Toman dos parciales, uno escrito a desarrollar y otro oral
A13: 6080 | B13: ZULETA-SCATAGLINI | C13: LU-JU | D13: PRESENCIAL | E13: 08:30-10:00 | F13: MEDIO | G13: ESCRITO | H13: SI | J13: Cada 15 días había un encuentro sincrónico con la profesora por Meet. Parciales a desarrollar, con casos actuales. Busca que los alumnos formulen respuestas completas en base a lo que opinan. | K13: APERTURA
A14: 6005 | B14: ALEGRE-RAMALLO | C14: LU-JU | D14: PRESENCIAL | E14: 10:00-11:30 | F14: MEDIO | G14: MIXTO | H14: SI | I14: NO | J14: Los profes explican muy bien y son pro alumno, super promocionable. Los parciales son choice con algunas preguntas a desarrollar. Toman lo dado en clase, y el cuatri pasado no tomaron tps pero si una exposición oral grupal, nada muy complicado.
A15: 6002 | B15: ALEGRE-SANTANATOGLIA | C15: LU-JU | D15: PRESENCIAL | E15: 10:00-11:30 | F15: MEDIO | G15: ESCRITO | H15: NO | I15: NO | J15: Buena cátedra, la profe explica bien y hay buena disposición del equipo docente. Toman dos parciales ambos a desarrollar.
A16: 6062 | B16: ALONSO-DUQUELSKY | C16: LU-JU | D16: PRESENCIAL | E16: 10:00-11:30 | F16: MEDIO | H16: NO | I16: SI | J16: Evaluan con 4tps (obligatorios) bastante sencillos y un tp final, cuenta la nota del ùltimo para el cierra de la materia. El profe es pro alumno, comprensivo y generoso con las notas. Las clases son muy divertidas y se analiza el derecho desde una perspectiva crìtica. | K16: APERTURA
A17: 6087 | B17: GAIDO - BIANCHI A. | C17: LU-JU | D17: PRESENCIAL | E17: 10:00-11:30 | F17: MEDIO | G17: MULTIPLECHOICE | H17: SI | I17: SI | J17: Toman lista, los parciales son dos multiplechoice y toman durante el cuatrimestre un TP para mantener la regularidad. IMPORTANTE: En el primer cuatrimestre esta comisión no fue abierta por no llegar al mínimo de inscriptos que exige la Facultad.
A18: 6033 | B18: MARTYNIUK-BARRERA L. | C18: LU-JU | D18: PRESENCIAL | E18: 10:00-11:30 | F18: ALTO | G18: ESCRITO | H18: SI | J18: La profe a veces no se da a entender bien, pero tienen buena predisposición para responder dudas. Toman dos parciales generalmente de 4 preguntas a desarrollar, llevando las lecturas al día y prestando atención en clase se aprueba. Cursada con perspectiva feminista.
A19: 6030 | B19: MARTYNIUK-IBARRA R. | C19: MA-VI | D19: PRESENCIAL | E19: 10:00-11:30 | F19: MEDIO | G19: ESCRITO | H19: NO | I19: NO | J19: Son principalmente dos profes. Respetan mucho el cronograma y cargan todo el material de la cursada en un drive. Toman dos parciales escritos sobre los textos vistos en clase (de dos preguntas, para desarrollar en una carilla cada una). Es una cátedra exigente pero ordenada, si se está al día con el material se aprueba con buena nota. Se promociona con 4 y se tienen que contestar mínimamente bien ambas preguntas. | K19: APERTURA
A20: 6055 | B20: ROSENKRANTZ-CALVO SOLER | C20: LU-JU | D20: PRESENCIAL | E20: 10:00-11:30 | F20: BAJO | G20: MULTIPLECHOICE | H20: SI | I20: SI | J20: Cátedra pro alumno, muy promocionable. Toman dos parciales múltiple choice y dos tps (no obligatorios) que sirven para levantar nota. | K20: TECNICA
A21: 6052 | B21: ROSENKRANTZ-CALVO SOLER | C21: MIE | D21: PRESENCIAL | E21: 10:00-13:00 | F21: BAJO | G21: MIXTO | H21: SI | I21: SI | J21: Hay TPs con notas. Los exámenes son escritos y multiplechoice. Los profes son copados y dan buenas clases
A22: 6088 | B22: GAIDO - BIANCHI A. | C22: LU-JU | D22: PRESENCIAL | E22: 11:30-13:00 | F22: MEDIO | G22: MULTIPLECHOICE | H22: SI | I22: SI | J22: Toman lista, los parciales son dos multiplechoice y toman durante el cuatrimestre un TP para mantener la regularidad
A23: 6063 | B23: MARTYNIUK-DEMCZUK | C23: LU-JU | D23: PRESENCIAL | E23: 11:30-13:00 | F23: MEDIO | G23: ESCRITO | H23: NO | I23: NO | J23: Cátedra pro alumno. La clase la da el profesor Nicolás Vainer, es un genio, explica muy bien y las veces que sea necesario, suben el material de lectura al campus, no hay tps y los parciales son escritos (antes de cada parcial hacen clase de repaso).
A24: 6032 | B24: MARTYNIUK-IBARRA R. | C24: MA-VI | D24: PRESENCIAL | E24: 11:30-13:00 | F24: MEDIO | G24: ESCRITO | H24: NO | I24: NO | J24: Son principalmente dos profes. Respetan mucho el cronograma y cargan todo el material de la cursada en un drive. Toman dos parciales escritos sobre los textos vistos en clase (de dos preguntas, para desarrollar en una carilla cada una). Es una cátedra exigente pero ordenada, si se está al día con el material se aprueba con buena nota. Se promociona con 4 y se tienen que contestar mínimamente bien ambas preguntas. | K24: APERTURA
A25: 6064 | B25: MARTYNIUK-DEMCZUK | C25: LU-JU | D25: PRESENCIAL | E25: 13:00:14:30 | F25: MEDIO | G25: ESCRITO | H25: NO | I25: NO | J25: Cátedra pro alumno. La clase la da el profesor Nicolás Vainer, es un genio, explica muy bien y las veces que sea necesario, suben el material de lectura al campus, no hay tps y los parciales son escritos (antes de cada parcial hacen clase de repaso).
A26: 6021 | B26: ALONSO-CAÑAL | C26: MA-VI | D26: VIRTUAL | E26: 14:00-15:30 | F26: MEDIO | G26: MIXTO | H26: SI | I26: SI | J26: Buen equipo docente, sin ánimos de bochar gente. La cursada mezcla filosofía y derecho, es importante participar en clases. El primer parcial suele ser choice y el segundo un coloquio.
A27: 6020 | B27: ALONSO-AGREDA M. | C27: LU-JU | D27: PRESENCIAL | E27: 14:00-15:30 | F27: MEDIO | G27: ESCRITO | H27: NO | I27: NO | J27: Càtedra pro alumno. Toman lo dado en clase (complementado con el material que es poco). La primera parte es filosofìa màs general con lìnea epistemològica. La segunda parte es filosofìa del derecho. Full positivista, evalùan "teorìa pura del derecho" de Kelsen. | K27: APERTURA
A28: 6007 | B28: ALEGRE ABAL FEDERICO | C28: LU-JU | D28: PRESENCIAL | E28: 15:30-17:00 | F28: ALTO | G28: ESCRITO | H28: NO | I28: NO | J28: Cátedra exigente, no toman lista pero hay que prestar mucha atención en clase porque toman muy puntillosamente lo que dan. Hay que trabajar muy bien los textos. Toman parciales a desarrollar con libro abierto
A29: 6004 | B29: ALEGRE-CHORNY E. | C29: LU-JU | D29: VIRTUAL | E29: 15:30-17:00 | F29: MEDIO | G29: MIXTO | H29: SI | J29: Recomendable. Cátedra con perspectiva de género, la cursada es llevadera y organizada, siguen mucho el cronograma. Hay bastante para leer y algunas clases se complementan con videos de YouTube de los profes. Evalúan tomando dos parciales choice con alguna pregunta a desarrollar y también toman una presentación oral. | K29: APERTURA
A30: 6024 | B30: ALONSO-CALO MAIZA | C30: MA-VI | D30: PRESENCIAL | E30: 15:30-17:00 | F30: MEDIO | G30: ESCRITO | H30: SI | J30: Cuesta agarrarle el ritmo a la cursada pero es promocionable. Toman dos parciales, el primero es escrito y el segundo oral un poco màs complicado.
A31: 6023 | B31: ALONSO-CAÑAL | C31: MA-VI | D31: PRESENCIAL | E31: 15:30-17:00 | F31: MEDIO | G31: MIXTO | H31: SI | I31: SI | J31: Muy buena càtedra, con un enfoque critico interesante. La cursada es bastante dinàmica y los profes son pro alumno. Toman un tp para mantener la regularidad y evalùan con un examen al final de la materia.
A32: 6041 | B32: RABBI B.-IRIBARNE S. | C32: LU-JU | D32: PRESENCIAL | E32: 15:30-17:00 | F32: MEDIO | G32: ESCRITO | H32: NO | I32: NO | J32: Buena cátedra, las clases son muy organizadas y el profe explica bien, para cada tema de la cursada hay un fallo que lo trata. Evalúan con dos parciales escritos no muy extensos.
A33: 6081 | B33: ZULETA-MARTINEZ G. | C33: LU-JU | D33: VIRTUAL | E33: 15:30-17:00 | F33: MEDIO | G33: ESCRITO | H33: SI | I33: NO | J33: Las clases se las dividen entre dos profesoras. Hay dos parciales escritos y toman lo dado en clase. | K33: APERTURA
A34: 6008 | B34: ALEGRE ABAL FEDERICO | C34: MIE | D34: VIRTUAL | E34: 15:30-18:30 | F34: MEDIO | G34: MIXTO | J34: Los parciales son mitad escrito a desarrollar, mitad choice, mete choices prácticos en la clase para control de lectura. Recomendable, muy buen docente
A35: 6022 | B35: ALONSO-DOLABJIAN D. | C35: MIE | D35: PRESENCIAL | E35: 15:30-18:30 | F35: MEDIO | G35: ESCRITO | H35: NO | I35: NO | J35: Cátedra pro alumno. Toman lo dado en clase (complementado con el material que es poco). La primera parte es filosofía más general con línea epistemológica. La segunda parte es filosofía del derecho. Full positivista, evalúan "teoría pura del derecho" de Kelsen. | K35: APERTURA
A36: 6056 | B36: BOHMER-BOHMER | C36: LU-JU | D36: PRESENCIAL | E36: 17:00-18:30 | F36: ALTO | G36: MIXTO | H36: SI | I36: NO | J36: Catedra exigente, intercala clases teorícas con prácticas, 1 examen escrito y 1 oral. Salis aprendiendo y se puede promocionar pero no te regalan nota
A37: 6053 | B37: BOHMER-MANTIÑAN | C37: LU-JU | D37: PRESENCIAL | E37: 17:00-18:30 | J37: Comisión nueva
A38: 6042 | B38: RABBI B.-IRIBARNE S. | C38: LU-JU | D38: PRESENCIAL | E38: 17:00-18:30 | F38: MEDIO | G38: ESCRITO | H38: NO | I38: NO | J38: Son 3 profes, explican bien y toman lo dado en clase. Hay que estar al día con los fallos y el manual, los parciales son de 3/4 preguntas no tan complejas a desarrollar. | K38: TECNICA
A39: 6082 | B39: ZULETA-REPETTO | C39: LU-JU | D39: PRESENCIAL | E39: 17:00-18:30 | F39: MEDIO | G39: ESCRITO | I39: SI | J39: La comisión es desordenada y hay opiniones encontradas sobre las explicaciones de los docentes. Toman más de un TP por cuatrimestre.
A40: 6083 | B40: ZULETA-SGRAZUTTI | C40: MA-VI | D40: PRESENCIAL | E40: 17:00-18:30 | F40: MEDIO | G40: ESCRITO | H40: NO | I40: SI | J40: Parciales domiciliarios a desarrollar. pro alumno, control de regularidad con TP. | K40: TECNICA
A41: 6003 | B41: ALEGRE-CHORNY E. | C41: LU-JU | D41: VIRTUAL | E41: 18:30-20:00 | F41: MEDIO | G41: MIXTO | H41: SI | J41: Càtedra recomendada. Suben textos al campus, algunos son complejos pero en clase explican todo. Los profes valoran mucho la participaciòn y que lleves los textos leìdos. Los parciales tienen una parte multiple choice y otra a desarrollar, es promocionable.
A42: 6012 | B42: MARTYNIUK-ABRAMOVICH | C42: LU-JU | D42: PRESENCIAL | E42: 18:30-20:00 | F42: MEDIO | G42: ESCRITO | H42: NO | I42: SI | J42: Toman un TP por clase, el profe puede ser demandante pero no tienen ánimos de bochar. No se toma lista. Cursada bien estructurada
A43: 6034 | B43: MARTYNIUK-DANAS | C43: MA-VI | D43: VIRTUAL | E43: 18:30-20:00 | F43: MEDIO | H43: SI | J43: Son dos profes. Respetan mucho el cronograma y cargan todo el material de la cursada en un drive. Toman dos parciales escritos de dos preguntas para desarrollar en una carilla cada uno. Es una càtedra exigente pero ordenada, si se està al dìa con el material se aprueba con buena nota. Se promociona con 4.
A44: 6077 | B44: RABBI B.-MAINO | C44: MA-VI | D44: PRESENCIAL | E44: 18:30-20:00 | F44: MEDIO | G44: ESCRITO | H44: SI | I44: NO | J44: Toman dos parciales a desarrollar. Respetan mucho el cronograma, y explican los temas más de una vez. Es una cátedra con enfoque ius naturalista. No hay mucho para leer pero es importante estar al día con el material. | K44: TECNICA
A45: 6043 | B45: RABBI B.-MULLER | C45: MA-VI | D45: PRESENCIAL | E45: 18:30-20:00 | F45: MEDIO | G45: ESCRITO | H45: NO | I45: NO | J45: Buenos profes, sin ánimos de bochar a nadie. Los parciales son escritos pero los recuperatorios son orales, es promocionable, se toma lo dado en clase. El manual es el de Rabbi Baldi, y los profes en general explican bien cada tema, recomiendo tomar apuntes.
A46: 6040 | B46: RABBI B.-PREGNO | C46: LU-JU | D46: VIRTUAL | E46: 18:30-20:00 | G46: MULTIPLECHOICE | H46: SI | I46: NO | J46: Cada tanto toman asistencia. Parciales domiciliarios, 5 preguntas multiple-choice y 5 preguntas V o F. Se promociona con 6 entre ambos parciales. El final es oral y presencial, se promociona con 4.
A47: 6084 | B47: ZULETA-SGRAZUTTI | C47: MA-VI | D47: VIRTUAL | E47: 18:30-20:00 | F47: MEDIO | G47: ESCRITO | H47: NO | I47: SI | J47: Parciales domiciliarios a desarrollar. pro alumno, control de regularidad con TP. | K47: TECNICA
A48: 6086 | B48: GAIDO-TOLNAY | C48: MIE | D48: PRESENCIAL | E48: 18:30-21:30 | G48: MULTIPLECHOICE
A49: 6013 | B49: MARTYNIUK-SANTAGATA | C49: MIE | D49: PRESENCIAL | E49: 18:30-21:30 | F49: MEDIO | G49: ESCRITO | H49: SI | J49: Cátedra para aprender, la cursada es media pesada pero las profes saben mucho. Evalúan con dos parciales a desarrollar | K49: TECNICA
A50: 6015 | B50: MARTYNIUK-SANTAGATA | C50: MIE | D50: PRESENCIAL | E50: 18:30-21:30 | F50: MEDIO | G50: ESCRITO | H50: SI | J50: Cátedra para aprender, la cursada es media pesada pero las profes saben mucho. Evalúan con dos parciales a desarrollar
A51: 6047 | B51: RABBI B.-LIBANO JUAN | C51: MIE | D51: PRESENCIAL | E51: 18:30-21:30 | F51: MEDIO | G51: MIXTO | H51: SI | I51: SI | J51: Toman lista a veces. Hay un TP que no va con nota pero algunas de las preguntas que están en este pueden aparecer en el primer parcial, que es escrito; el segundo parcial es oral. No tienen ánimos de bochar, las clases son buenas aunque pueden irse por las ramas y tornarse confusas
A52: 6006 | B52: ALEGRE-SEMINARIO LAURA | C52: LU-JU | D52: VIRTUAL | E52: 20:00-21:30 | F52: MEDIO | G52: ORAL | H52: NO | I52: NO | J52: Catedra pro-alumno. Profesores dedicados y con mucho dominio del contenido. Si bien no toman lista, registran la participación. Los parciales se rinden presencialmente.
A53: 6009 | B53: ALEGRE-SEMINARIO LAURA | C53: LU-JU | D53: VIRTUAL | E53: 20:00-21:30 | F53: MEDIO | G53: ORAL | H53: NO | I53: NO | J53: Catedra pro-alumno. Profesores dedicados y con mucho dominio del contenido. Si bien no toman lista, registran la participación. Los parciales se rinden presencialmente.
A54: 6085 | B54: GAIDO-TOLNAY | C54: LU-JU | D54: VIRTUAL | E54: 20:00-21:30 | F54: MEDIO | G54: MULTIPLECHOICE | H54: SI | I54: NO | J54: Toman dos parciales multiple-choice sin ánimos de bochar a nadie; los profes son copados y no tienen problema en responder dudas
A55: 6036 | B55: MARTYNIUK-DANAS | C55: MA-VI | D55: VIRTUAL | E55: 20:00-21:30 | G55: ESCRITO | H55: SI | J55: Son dos profes. Respetan mucho el cronograma y cargan todo el material de la cursada en un drive. Toman dos parciales escritos de dos preguntas para desarrollar en una carilla cada uno. Es una càtedra exigente pero ordenada, si se està al dìa con el material se aprueba con buena nota. Se promociona con 4.
A56: 6035 | B56: MARTYNIUK-ELJATIB AXEL | C56: MA-VI | D56: PRESENCIAL | E56: 20:00-21:30 | F56: MEDIO | G56: ESCRITO | H56: SI | I56: NO | J56: Toman ambos parciales escritos en los que es importante haber ido a las clases porque los temas suelen estar bien explicados en ellas. Es importante la asistencia para mantener la regularidad.
A57: 6078 | B57: RABBI B.-MAINO | C57: MA-VI | D57: PRESENCIAL | E57: 20:00-21:30 | F57: MEDIO | G57: ESCRITO | H57: SI | I57: NO | J57: Toman dos parciales a desarrollar. Respetan mucho el cronograma, y explican los temas más de una vez. Es una cátedra con enfoque ius naturalista. No hay mucho para leer pero es importante estar al día con el material. | K57: TECNICA
A58: 6045 | B58: RABBI B.-MULLER | C58: MA-VI | D58: PRESENCIAL | E58: 20:00-21:30 | F58: MEDIO | G58: ESCRITO | H58: NO | I58: NO | J58: Buenos profes, sin ánimos de bochar a nadie. Los parciales son escritos pero los recuperatorios son orales, es promocionable, se toma lo dado en clase. El manual es el de Rabbi Baldi, y los profes en general explican bien cada tema, recomiendo tomar apuntes.
A59: 6044 | B59: RABBI B.-PACHECO | C59: LU-JU | D59: PRESENCIAL | E59: 20:00-21:30 | F59: MEDIO | G59: ESCRITO | H59: NO | I59: NO | J59: Toma 2 parciales a desarrollar con preguntas teóricas y prácticas. Las clases se dictan con poca interacción con lxs estudiantes. Hay opiniones encontradas acerca de responder dudas
A60: 6065 | B60: MARTYNIUK-MAS ANALIA | C60: LU-JU | D60: VIRTUAL | E60: 21:30-23:00 | F60: BAJO | G60: MULTIPLECHOICE | H60: SI | I60: NO | J60: Cursada remota. Las clases son oganizadas y hay profes copados, suben todo el material al campus. Los parciales son multiple choice, al igual que los recuperatorios. Super promocionable. | K60: TECNICA
A61: 6046 | B61: RABBI B.-PACHECO | C61: LU-JU | D61: PRESENCIAL | E61: 21:30-23:00 | F61: MEDIO | G61: ESCRITO | H61: NO | I61: NO | J61: Los parciales son domiciliarios durante 4hs, no son complicados. Las clases se dictan con poca interacción con lxs estudiantes. Hay opiniones encontradas acerca de responder dudas
A62: 6070 | B62: ALONSO-DIEZ IGLESIAS | C62: MA-VI | D62: PRESENCIAL | E62: 7:00-08:30 | F62: MEDIO | G62: MULTIPLECHOICE | H62: SI | I62: NO | J62: Las clases son organizadas. Se envian guias de preguntas, de las cuales algunas pueden aparecer en los parciales. Cambian muy seguido el adjunto y hace que varie la catedra de cuatri a cuatri.
A63: 6001 | B63: ALEGRE-SEMINARIO LAURA | C63: LU-JU | D63: PRESENCIAL | E63: 7:00-8:30
A64: 6074 | B64: ALONSO-DIEZ IGLESIAS | C64: MA-VI | D64: PRESENCIAL | E64: 8:30-10:00
A65: 6054 | B65: ROSENKRANTZ-PEREL P. | C65: MI-SA | D65: VIRTUAL | E65: Mie 20:00 a 21:30 - Sab 11:30 a 13:00 | F65: MEDIO | G65: ESCRITO | H65: SI | J65: Càtedra promocionable, evalùan con tps que consisten en armar ensayos sobre los temas trabajados en la cursada.

Sheet TDE
A1: 📚 TEORÍA DEL ESTADO - 2º CUATRI 2026 - LA CÁMPORA 📚
A2: N° | B2: COMISIÓN | C2: DÍAS | D2: MODALIDAD | E2: HORARIO | F2: NIVEL | G2: EXAMEN | H2: TOMA LISTA | I2: TOMA TPS | J2: COMENTARIO | K2: POSTURA
A3: 6218 | B3: BERCHOLC - BERCHOLC | C3: LU-JU | D3: PRESENCIAL | E3: 18:30 - 20:00HS | F3: MEDIO | G3: MIXTO | H3: SI | I3: SI | J3: Comisión sin ánimos de bochar. Tienen buena llegada con los estudiantes, no tienen problema en poner notas altas y si te falta nota podés rendir un TP para promocionar la materia.
A4: 6236 | B4: D AURIA-HEFFES AGOS O.D. | C4: MA-VI | D4: PRESENCIAL | E4: 07:00-08:30 | F4: MEDIO | G4: ESCRITO | H4: SI | I4: NO | J4: El profesor Omar Heffes es super recomendado por sus alumnos, da explicaciones con cada texto de la fecha, lleva el cronograma de clases al dia. Todo el material esta en el campus (bibliografia aportada por la catedra. | K4: APERTURA
A5: 6210 | B5: BERCHOLC-BARILE | C5: LU-JU | D5: VIRTUAL | E5: 08:30-10:00 | F5: MEDIO | G5: MIXTO | H5: SI | I5: NO | J5: Hay opiniones encontradas sobre esta comisión acerca de los tiempos para rendir los parciales. El primero fue escrito con solo 20 minutos para contestar
A6: 6211 | B6: BERCHOLC-BARRAZA | C6: MA-VI | D6: VIRTUAL | E6: 07:00-8:30 | F6: BAJO | G6: MIXTO | H6: NO | I6: SI | J6: ATENCIÓN: Cambió el adjunto. Última recomendación: los parciales son choice y a desarrollar. Envia textos para estudiar // No recomendada, los profesores son desorganizados, llegan tarde a los parciales y hacen TPs sobre conferencias a las que te hacen asistir que promedian con los parciales. | K6: APERTURA
A7: 6240 | B7: DE LUCA-CAMPIONE | C7: LU-JU | D7: PRESENCIAL | E7: 08:30-10:00 | F7: MEDIO | G7: ESCRITO | H7: NO | I7: SI | J7: Toma 3 o 4 preguntas a desarrollar. Manda videos explicativos. Pro alumno. | K7: APERTURA
A8: 6261 | B8: FEDERICI-GUMA CHRISTIAN | C8: MA-VI | D8: PRESENCIAL | E8: 08:30-10:00 | F8: MEDIO | G8: ESCRITO | H8: NO | I8: NO | J8: ATENCIÓN: Cambió el adjunto. Última recomendación: Se toma lo visto en clase, la mayoría promociona.
A9: 6260 | B9: FEDERICI-FLORIO | C9: LU-JU | D9: PRESENCIAL | E9: 08:30-10:00 | F9: MEDIO | G9: MIXTO | H9: NO | I9: NO | J9: La cursada puede ser desorganizada, toman multiple-choice relativamente fáciles y después orales los propios compañeros tenemos que poner nota,
A10: 6270 | B10: SCHERLIS-GABRIEL S. | C10: LU-JU | D10: PRESENCIAL | E10: 08:30-10:00 | F10: BAJO | G10: MULTIPLECHOICE | H10: SI | I10: NO | J10: Son 4 parciales, buen trato y sin ánimos de bochar.
A11: 6271 | B11: SCHERLIS-WADDELL J. | C11: MA-VI | D11: PRESENCIAL | E11: 08:30-10:00 | F11: BAJO | G11: ESCRITO | H11: NO | I11: NO | J11: solo da clase 1 docente, es cordial con los estudiantes, quiere que participan en clase. Tiene las clases diagramadas en el cronograma da 1 autor por clase (la clase no suele extenderse toda la hora de cursada) toma 2 parciales escritos y hay 1 recuperarorio por parcial que también es escrito, toma 3 preguntas por parcial y da varios temas. El segundo parcial es más complicado porque hay que desarrollar un autor que te da al azar | K11: TECNICA
A12: 6212 | B12: BERCHOLC-FAMA ADRIAN | C12: MI | D12: PRESENCIAL | E12: 08:30-11:30 | F12: BAJO | G12: MIXTO | H12: NO | I12: SI | J12: ATENCIÓN: Cambió el adjunto. Última recomendación: los parciales son choice y a desarrollar. Envia textos para estudiar // No recomendada, los profesores son desorganizados, llegan tarde a los parciales y hacen TPs sobre conferencias a las que te hacen asistir que promedian con los parciales. | K12: APERTURA
A13: 6221 | B13: CAO C.-ZAPPA MARÍA SOLEDAD | C13: MI | D13: PRESENCIAL | E13: 08:30-11:30 | H13: SI
A14: 6242 | B14: DE LUCA-CAMPIONE | C14: MI | D14: PRESENCIAL | E14: 08:30-11:30 | F14: MEDIO | G14: ESCRITO | H14: NO | I14: SI | J14: Toma 3 o 4 preguntas a desarrollar. Manda videos explicativos. Pro alumno. | K14: APERTURA
A15: 6219 | B15: CAO C-PIERPAULI RICARDO | C15: LU-JU | D15: PRESENCIAL | E15: 10:00-11:30 | F15: BAJO | G15: ESCRITO | H15: SI | I15: NO | J15: No tienen problemas en poner notas altas a la hora de corregir, mandan una guía de preguntas dos semanas antes de las que sacan después las consignas del parcial así que es súper promocionable. A considerar que te hacen comprar dos libros de profesor en su editorial y que son abiertamente conservadores y religiosos | K15: CONSERVADORA
A16: 6228 | B16: CAO-PIERPAULLI RICARDO | C16: LU-JU | D16: PRESENCIAL | E16: 10:00-11:30 | F16: BAJO | G16: ESCRITO | H16: SI | I16: NO | J16: No tienen problemas en poner notas altas a la hora de corregir, mandan una guía de preguntas dos semanas antes de las que sacan después las consignas del parcial así que es súper promocionable. A considerar que te hacen comprar dos libros de profesor en su editorial y que son abiertamente conservadores y religiosos | K16: CONSERVADORA
A17: 6230 | B17: D AURIA-VITA LETICIA | C17: MA-VI | D17: PRESENCIAL | E17: 10:00-11:30 | F17: ALTO | G17: MIXTO | H17: NO | I17: NO | J17: Amenas. Mandan bastante para leer pero no es condición necesaria para aprobar. Los temas centrales se ven en la clase y los textos sirven para reforzar si queres 10. Los profes explican bien y dan mucho lugar a que participen. La profe está en el conicet sabe mucho de divulgación.
A18: 6243 | B18: DE LUCA-BURSZTYN DEBORA | C18: MA-VI | D18: PRESENCIAL | E18: 10:00-11:30 | F18: MEDIO | G18: MULTIPLECHOICE | H18: SI | I18: NO | J18: Explican muy bien. Los parciales son 60 multiple choice y te dan 1 hora y media para completarlo. Toman lo visto en clase, el material lo suben al campus en un drive. | K18: TECNICA
A19: 6252 | B19: DE LUCA-VIDELA MONTILLA | C19: LU-JU | D19: VIRTUAL | E19: 10:00-11:30 | F19: MEDIO | G19: MULTIPLECHOICE | H19: SI | I19: NO | J19: Los profesores te dan el material para estudiar y las clases son llevaderas.
A20: 6262 | B20: FEDERICI-HALAMAN | C20: MA-VI | D20: PRESENCIAL | E20: 10:00-11:30 | F20: ALTO | G20: MIXTO | H20: SI | I20: SI | J20: Comisión exigente con el material, hay que llevarla muy al día para promocionarla. Toman dos parciales que suelen varias cuatrimestre tras cuatrimestre aunque saben tomar multiple-choice a justificar o TPs grupales como método de evaluación
A21: 6213 | B21: BERCHOLC-BARRAZA | C21: MI | D21: PRESENCIAL | E21: 10:00-13:00 | F21: MEDIO | G21: ESCRITO | H21: SI | I21: SI | J21: Es una cátedra organizada, siguen el cronograma y evaluan con parciales escritos (3 preguntas). Realiza excursiones. | K21: -
A22: 6272 | B22: SCHERLIS-AGUIRRE G. | C22: SA | D22: PRESENCIAL | E22: 10:00-13:00 | F22: MEDIO | G22: ESCRITO | H22: NO | I22: SI | J22: El profesor es organizado, los parciales son domiciliarios de una semana a la otra y se entregan resúmenes que el profesor puede ir eligiendo al azar. No tiene ánimos de bochar, es exigente en la corrección mas pone notas altas
A23: 6281 | B23: SCHERLIS-PERICOLA | C23: MI | D23: PRESENCIAL | E23: 10:00-13:00 | F23: MEDIO | G23: ESCRITO | H23: SI | I23: NO | J23: Toman dos parciales escritos con 3 preguntas a desarrollar. Comisión muy completa con buena llegada con los estudiantes; siguen al pie de la letra el cronograma de clases que mandan al comienzo de la cursada
A24: 6200 | B24: A DESIG.-DI GIOIA | C24: MA-VI | D24: PRESENCIAL | E24: 11:30-13:00
A25: 6231 | B25: D AURIA-VITA LETICIA | C25: MA-VI | D25: PRESENCIAL | E25: 11:30-13:00 | F25: MEDIO | G25: MIXTO | H25: NO | I25: NO | J25: Siguen el cronograma, son ordenados. Dan modelos de parciales para practicar. No toman TPs, los parciales son multiplechoice y a desarrollar.
A26: 6241 | B26: DE LUCA-BURSZTYN DEBORA | C26: MA-VI | D26: PRESENCIAL | E26: 11:30-13:00 | F26: MEDIO | G26: MULTIPLECHOICE | H26: SI | I26: NO | J26: Explican muy bien. Los parciales son 60 multiple choice y te dan 1 hora y media para completarlo. Toman lo visto en clase, el material lo suben al campus en un drive. | K26: TECNICA
A27: 6244 | B27: DE LUCA-FINOCCHIARO | C27: MA-VI | D27: PRESENCIAL | E27: 11:30-13:00 | F27: ALTO | G27: MIXTO | H27: SI | I27: NO | J27: Los parciales son escritos con recuperatorio y final orales. Contenido pesado, mucho para leer. Clases aburridas. | K27: CONSERVADORA
A28: 6263 | B28: FEDERICI-FLORIO | C28: MA-VI | D28: PRESENCIAL | E28: 11:30-13:00 | F28: BAJO | G28: MIXTO | H28: SI | I28: NO | J28: Dos parciales, el primero escrito y el segundo oral. Para los dos te da las preguntas de antemano. El parcial escrito son 4 preguntas y una a elección personal. Es muy difícil comunicarse con los docentes, tardan en contestar. Se usa el manual de Justo López que puede ser de difícil lectura por falta de acompañamiento didáctico en las clases
A29: 6273 | B29: SCHERLIS-GABRIEL S. | C29: LU-JU | D29: PRESENCIAL | E29: 11:30-13:00 | F29: BAJO | G29: MULTIPLECHOICE | H29: SI | I29: NO | J29: Son 4 parciales, buen trato y sin ánimos de bochar.
A30: 6274 | B30: SCHERLIS-LESCANO G. | C30: LU-JU | D30: PRESENCIAL | E30: 11:30-13:00 | F30: MEDIO | G30: ESCRITO | H30: NO | I30: SI | J30: Muy recomendada. Toman dos parciales escritos de 2 o 3 preguntas de temas vistos en clase sin ninguna sorpresa y un TP de regularidad. El profesor tiene buena llegada pero la ayudante es la mejor haciendo que las clases sean súper llevaderas; responden todas las dudas y no tienen ningún ánimo de bochar | K30: APERTURA
A31: 6275 | B31: SCHERLIS-LESCANO G. | C31: MA-VI | D31: PRESENCIAL | E31: 11:30-13:00 | F31: MEDIO | G31: ORAL | H31: SI | I31: NO | J31: Recomendada. Cátedra inclusiva y con perspectiva feminista, toman 2 orales de 5 minutos sin ánimos de bochar ni en los parciales ni en el recuperatorio. Recomendada | K31: APERTURA
A32: 6235 | B32: D AURIA-IBARRA | C32: MA-VI | D32: PRESENCIAL | E32: 14:00-15:30 | F32: MEDIO | G32: ESCRITO | H32: NO | I32: NO | J32: Muy recomendada. Los profesores tienen buen trato con los estudiantes con gran disposición para responder dudas y explicar siguiendo el cronograma. Cada clase se ve un texto diferente y la segunda mitad es con perspectiva nacional. Los parciales son dos con dos preguntas a desarrollar que ambas deben contestarse mínimamente bien (recuperatorio igual) y el final es oral. Se disfruta mucho, si bien no toman lista se recomienda ir por las clases. | K32: APERTURA
A33: 6245 | B33: DE LUCA-SCARRAMBERG JUAN MARTIN | C33: LU-JU | D33: PRESENCIAL | E33: 07:00 a 8:30 | F33: MEDIO | G33: ESCRITO | H33: NO | I33: NO | J33: No toma lista pero se recomienda ir a las clases ya que estudiando de los apuntes se puede promocionar. No tienen problema en poner notas altas y no tienen ningún ánimo de bochar. | K33: TECNICA
A34: 6282 | B34: SCHERLIS-WINER | C34: MI | D34: PRESENCIAL | E34: 14:00-17:00 | F34: MEDIO | G34: ORAL | H34: SI | I34: SI | J34: Toman un TP por semana conceptual para llevar la regularidad, pasan lista y toman dos exámenes. Al final de la cursada podés exponer un trabajo en clase de manera optativa
A35: 6234 | B35: D AURIA-BALERDI | C35: MA-VI | D35: PRESENCIAL | E35: 15:30-17:00 | F35: MEDIO | G35: ESCRITO | H35: SI | I35: NO | J35: El primer parcial escrito, dos preguntas a desarrollar. El segundo es domiciliario para entregarlo en una semana, te dan tres preguntas y elegís dos.
A36: 6232 | B36: D AURIA-DOTI A. | C36: LU-JU | D36: PRESENCIAL | E36: 15:30-17:00 | F36: MEDIO | G36: MIXTO | H36: SI | I36: NO | J36: Los profesores son muy buena onda, las clases son entretenidas y el material muy interesante. El primer parcial son preguntas a desarrollar y el segundo una monografía sobre una película. Notas altas, la mayoría promociona. Lo malo es que son muy desorganizados con el material y no siguen estrictamente el cronograma. También llegan tarde. | K36: TECNICA
A37: 6233 | B37: D AURIA-IBARRA | C37: MA-VI | D37: PRESENCIAL | E37: 15:30-17:00 | F37: MEDIO | G37: ESCRITO | H37: NO | I37: NO | J37: Muy recomendada. Los profesores tienen buen trato con los estudiantes con gran disposición para responder dudas y explicar siguiendo el cronograma. Cada clase se ve un texto diferente y la segunda mitad es con perspectiva nacional. Los parciales son dos con dos preguntas a desarrollar que ambas deben contestarse mínimamente bien (recuperatorio igual) y el final es oral. Se disfruta mucho, si bien no toman lista se recomienda ir por las clases. | K37: APERTURA
A38: 6264 | B38: FEDERICI-GALLARDO | C38: MA-VI | D38: PRESENCIAL | E38: 15:30-17:00 | F38: MEDIO | G38: MIXTO | H38: NO | I38: NO | J38: La modalidad de parciales se decide por votación, pueden ser orales o escritos. Preguntas a desarrollar, una sobre un fallo y otra la da el profesor la clase antes del parcial. En los parciales solamente se evalúan los textos , pero no se explican en clase. No se le da importancia a lo dado en clase la hora de evaluar. Es muy desorganizada. No se recomienda. | K38: CONSERVADORA
A39: 6276 | B39: SCHERLIS-PERICOLA M. | C39: LU-JU | D39: PRESENCIAL | E39: 15:30-17:00 | F39: ALTO | G39: MIXTO | H39: SI | I39: SI | J39: Las clases pueden ser aburridas y en los parciales, demorandose mucho para corregir, ponen notas bajas sin justificar por qué. Hay poco espacio para justificar ya que la modalidad es multiple-choice a justificar. | K39: TECNICA
A40: 6223 | B40: D AURIA-CABRERA M. | C40: MI | D40: PRESENCIAL | E40: 15:30-18:30 | F40: ALTO | G40: ESCRITO | H40: SI | I40: SI | J40: muy cerrado. mala dirección hacia los alumnos. si llegas tarde o algo, se enoja. | K40: CONSERVADORA
A41: 6214 | B41: BERCHOLC-BARILE | C41: LU-JU | D41: PRESENCIAL | E41: 17:00-18:30 | F41: MEDIO | G41: MIXTO | H41: SI | I41: NO | J41: Siguen el cronograma. Los profes son excelentes y las clases muy amenas. Toman dos parciales multiple choice y a desarrollar, super promocionable. | K41: APERTURA
A42: 6217 | B42: BERCHOLC-BARRAZA | C42: MA-VI | D42: PRESENCIAL | E42: 17:00-18:30 | H42: SI
A43: 6224 | B43: CAO C.-GARGARELLA | C43: LU-JU | D43: PRESENCIAL | E43: 17:00-18:30 | F43: ALTO | G43: ESCRITO | H43: SI | I43: NO | J43: Comisión para estudiar y aprovechar los materiales de estudio. No es exigente, se recomienda seguirla al día en las clases para promocionar sin problemas (estudiando de las clases y las guías). Toman dos parciales escritos a desarrollar. Lo único es que tal vez pueden ser desorganizados con los tiempos y así complicarse los recuperatorios
A44: 6246 | B44: DE LUCA-NEGRO S. | C44: MA-VI | D44: VIRTUAL | E44: 17:00-18:30 | F44: MEDIO | G44: ESCRITO | H44: NO | I44: SI | J44: La profesora es super amable y no tiene problemas en contestar dudas. Son dos parciales y TPS para mantener la regularidad. Es recomendable ir, no se toma asistencia | K44: TECNICA
A45: 6225 | B45: CAO C.-FUENTES | C45: MI | D45: PRESENCIAL | E45: 17:00-20:00 | F45: MEDIO | G45: MIXTO | H45: NO | I45: SI | J45: Los tps no son obligatorios,los examenes son lo que se ve en clase, se sigue el cronograma. Pro alumno, sin ánimos de bochar
A46: 6226 | B46: CAO C.-ALBERTUS | C46: LU-JU | D46: PRESENCIAL | E46: 18:30-20:00 | F46: ALTO | G46: MIXTO | H46: SI | I46: NO | J46: Los profesores no se ponen de acuerdo entre si con la modalidad de la cursada al punto que el mismo dia del examen te enteras si va a ser escrito u oral. Toman parciales bastantes exigentes y en clase no se ve todo lo que toman.
A47: 6227 | B47: CAO C.-BULACIO | C47: LU-JU | D47: PRESENCIAL | E47: 17:00 a 18:30 | F47: BAJO | G47: ESCRITO | H47: SI | I47: SI | J47: Las clases se basan en la teoria antigua del Estado basado en la iglesia catolica. Toman trabajos practicos. Es virtual. Se evalua mediante parciales domiciliarios en base a una pelicula. | K47: CONSERVADORA
A48: 6247 | B48: DE LUCA-NEGRO S. | C48: MA-VI | D48: PRESENCIAL | E48: 18:30-20:00 | F48: MEDIO | G48: ESCRITO | H48: NO | I48: SI | J48: La profesora es super amable y no tiene problemas en contestar dudas. Son dos parciales y TPS para mantener la regularidad. Es recomendable ir, no se toma asistencia | K48: TECNICA
A49: 6284 | B49: FEDERICI-ALI | C49: MA-VI | D49: PRESENCIAL | E49: 18:30-20:00 | F49: MEDIO | G49: ESCRITO | H49: NO | I49: NO | J49: Toman dos parciales escritos de tres preguntas a desarrollar; las clases son particulares, dan lo que está en los manuales al pie de la letra. IMPORTANTE: En el primer cuatrimestre esta comisión no fue abierta por no llegar al mínimo de inscriptos que exige la Facultad.
A50: 6278 | B50: SCHERLIS-AGUIRRE G. | C50: MA-VI | D50: PRESENCIAL | E50: 18:30-20:00 | F50: ALTO | G50: MIXTO | H50: SI | I50: NO | J50: Buen trato con los estudiantes y sin ánimos de bochar. Son exigentes en los parciales así que es importante llevar al día las clases y estudiar para cada una de ellas para seguirle el ritmo al profesor
A51: 6280 | B51: SCHERLIS-WINER | C51: LU-JU | D51: PRESENCIAL | E51: 18:30-20:00 | F51: MEDIO | G51: ORAL | H51: SI | I51: SI | J51: Si bien pueden ser un poco desorganizados (no tienen cronograma) es una comisión súper amena en la que los profesores se preocupan y no tienen problema en contestar dudas e inquietudes. Al ser una materia pesada se puede tornar aburrida o tediosa pero si seguís día a día la cursada llegas bien a aprobar leyendo las guías. Importante ir a cursar porque las clases son una buena síntesis y a los profesores le interesa la participación. Toman TPS | K51: APERTURA
A52: 6279 | B52: SCHERLIS-WADDELL J. | C52: MI | D52: PRESENCIAL | E52: 18:30-21:30 | F52: BAJO | G52: ESCRITO | H52: NO | I52: NO | J52: Solo da clase un docente, es coordial con los estudiantes, quiere que participan en clase. Tiene las clases diagramadas en el cronograma da 1 autor por clase (no suele extenderse toda la hora de cursada). Toma 2 parciales escritos y hay 1 recuperarorio por parcial que también es escrito, toma 3 preguntas por parcial y da varios temas. Le interesa particularmente que se relacionen las fuentes | K52: TECNICA
A53: 6215 | B53: BERCHOLC-BARRAZA | C53: LU-JU | D53: PRESENCIAL | E53: 20:00-21:30 | F53: MEDIO | G53: ESCRITO | H53: SI | I53: NO | J53: Los profesores faltan sin avisar y a veces llegan tarde inclusive en los parciales, dejando poco tiempo para resolverlos ya que son extensos y se pierde bastante esperando su llegada
A54: 6216 | B54: BERCHOLC-BARRAZA | C54: MA-VI | D54: PRESENCIAL | E54: 18:30 - 20:00 | F54: MEDIO | G54: ESCRITO | H54: SI | I54: NO | J54: Son varios profesores, se lee mucho. Las clases suelen terminar antes aunque no abarcan todos los textos. Los parciales son V o F a justificar y algunos a desarrollar | K54: CONSERVADORA
A55: 6201 | B55: CAO C.-BENENTE | C55: LU-JU | D55: PRESENCIAL | E55: 20:00-21:30 | F55: ALTO | G55: MIXTO | H55: NO | I55: NO | K55: TECNICA
A56: 6248 | B56: DE LUCA-KRIVOCAPICH | C56: MA-VI | D56: PRESENCIAL | E56: 20:00-21:30 | F56: MEDIO | G56: MIXTO | H56: SI | I56: SI | J56: Toman un TP en base a una película en el que hay que relacionar conceptos y un oral con 3 preguntas súper entendibles, no tienen ánimos de bochar. Dan buenas explicaciones en las clases con las que alcanza para promocionar estudiando de ellas.
A57: 6254 | B57: DE LUCA-KRIVOCAPICH | C57: MA-VI | D57: PRESENCIAL | E57: 20:00-21:30 | F57: MEDIO | G57: MIXTO | H57: SI | I57: SI | J57: Toman un TP en base a una película en el que hay que relacionar conceptos y un oral con 3 preguntas súper entendibles, no tienen ánimos de bochar. Dan buenas explicaciones en las clases con las que alcanza para promocionar estudiando de ellas.
A58: 6269 | B58: FEDERICI-GALLARDO | C58: MA-VI | D58: PRESENCIAL | E58: 20:00-21:30 | F58: MEDIO | G58: ORAL | H58: NO | I58: NO | J58: Toman lo dado en clase apoyado en la bibliografía. Es mucho contenido pero sin ánimos de bochar. Dos parciales orales. La primera parte es filosofía política desde Antigua Grecia hasta la posmodernidad y también historia argentina. La segunda parte evalúan el análisis del mundo actual con el libro del adjunto. | K58: APERTURA
A59: 6268 | B59: FEDERICI-HALLAMAN | C59: MA-VI | D59: PRESENCIAL | E59: 20:00-21:30 | F59: ALTO | G59: MIXTO | H59: SI | I59: SI | J59: Comisión exigente con el material, hay que llevarla muy al día para promocionarla. Toman dos parciales que suelen varias cuatrimestre tras cuatrimestre aunque saben tomar multiple-choice a justificar o TPs grupales como método de evaluación
A60: 6250 | B60: DE LUCA-VIDELA MONTILLA | C60: MI | D60: PRESENCIAL | E60: 20:00-23:00 | F60: MEDIO | G60: MIXTO | H60: SI | I60: NO | J60: Su forma de evaluación es una incógnita porque cambia durante el cuatrimestre, mala llegada con los estudiantes sobre dudas y parciales. No ponen notas altas.// Hay opiniones encontradas acerca del trato de los docentes

Sheet CIVIL
A1: 📚 ELEMENTOS DEL DERECHO CIVIL - 2º CUATRI 2026 - LA CÁMPORA 📚
A2: N° | B2: COMISIÓN | C2: DÍAS | D2: MODALIDAD | E2: HORARIO | F2: NIVEL | G2: EXAMEN | H2: TOMA LISTA | I2: TOMA TPS | J2: COMENTARIO | K2: POSTURA
A3: 6840 | B3: LAFERRIERE-MUÑIZ | C3: LU-JU | D3: PRESENCIAL | E3: 07:00-08:30 | F3: ALTO | G3: MIXTO | H3: SI | J3: Los profes explican bien y son bastante organizados. Evaluan con dos parciales que tienen una parte choice y otra desarrollar, son bastante específicos pero se aprueba.
A4: 6800 | B4: PERALTA MARISCAL-LOVECE G. | C4: MA-VI | D4: VIRTUAL | E4: 07:00-08:30 | F4: ALTO | G4: ESCRITO | H4: SI | I4: SI | J4: Recomiendo, catedra muy organizada y cumple con el cronograma. Las profes son lo más, explican bien, se aprende mucho. Los parciales son a desarrollar, nada rebuscados, pero son exigentes con las condiciones de evaluación | K4: TECNICA
A5: 6813 | B5: PERALTA MARISCAL-REY M. | C5: LU-JU | D5: PRESENCIAL | E5: 07:00-08:30 | F5: MEDIO | G5: ESCRITO | H5: SI | J5: Las profesras explican muybien. Nancy los días lunes (lleva Powerpoints buenísimos para estudiar)y Mariana (los jueves) y suelen dar muchos ejemplos de casos.Toman asistencia. Son 2 parciales escritos con casos a desarrollar (fundamentando con n el CCyCN y el manual de Rivera)
A6: 6872 | B6: CROVI-FISSORE | C6: MA-VI | D6: PRESENCIAL | E6: 08:30-10:00 | F6: BAJO | G6: MIXTO | H6: NO | I6: NO | J6: Recomendada. Toma solo lo dado en clase con parciales escritos a desarrollar -en algunos casos oral-. No toma asistencia ni trabajos prácticos. | K6: TECNICA
A7: 6871 | B7: CROVI-GRAFEUILLE | C7: LU-JU | D7: VIRTUAL | E7: 08:30-10:00 | F7: BAJO | G7: MULTIPLECHOICE | H7: NO | I7: NO | J7: Se sigue un cronograma durante la cursada y se ven fallos para ejemplificar los conceptos. Parciales hay uno solo con 25 preguntas MC que se promociona con 4. En caso de ir a recuperar, también promociona con 4. La mayoría aprueba y con buenas notas. | K7: TECNICA
A8: 6880 | B8: DE LORENZO-LAVALLE G. | C8: MA-VI | D8: PRESENCIAL | E8: 08:30-10:00 | F8: MEDIO | G8: MIXTO | H8: NO | J8: El profesor Lavalle explica de una manera dinámica y se le entiende muchísimo. No pasa lo mismo con otros docentes de la catedra, nunca explica el tema que le toca, se va por las ramas y termina hablando de otra cosa que no sirve. No toman asistencia nunca. Lo malo es que tardan muchísimo en pasar las notas de los parciales, para el primer parcial estuvieron 1 mes sin decirnos nuestra nota, también siempre llegan al menos 15 minutos tarde a la clase. El parcial se divide en 2 partes, la primera es multiple choice y si lo aprobas, pasas a la parte escrita, donde te suelen dejar usar el código civil.
A9: 6822 | B9: GARRIDO C.-BALMACEDA M. | C9: MA-VI | D9: PRESENCIAL | E9: 08:30-10:00 | F9: MEDIO | G9: MIXTO | H9: SI | I9: SI | J9: Las clases son entretenidas y dinámicas. Cada clase intercala entre dos profes para dictar la clase. No toman lista, ni mandan trabajos prácticos pero piden alguna que otra tarea en la primer parte de la materia. En los exámenes se toma teoría y práctica, son para redactar y multiple choice. El recuperatorio y el final son orales. | K9: TECNICA
A10: 6841 | B10: LAFERRIERE-ARCOS | C10: LU-JU | D10: PRESENCIAL | E10: 08:30-10:00 | F10: MEDIO | G10: ESCRITO | H10: NO | I10: SI | J10: La recomiendo, los lunes hace clases de consultas y los jueves se dan casos prácticos. Tiene todas las clases subidas a YouTube y el material es a elección se super entienden las clases, es promocionable y pro alumno. Los parciales son dos y escritos. | K10: TECNICA
A11: 6842 | B11: LAFERRIERE-MUÑIZ | C11: LU-JU | D11: PRESENCIAL | E11: 08:30-10:00 | F11: ALTO | G11: MIXTO | H11: SI | J11: Los profes explican bien y son bastante organizados. Evaluan con dos parciales que tienen una parte choice y otra desarrollar, son bastante específicos pero se aprueba.
A12: 6850 | B12: SANTARELLI-FORNARI M. | C12: MA-VI | D12: PRESENCIAL | E12: 08:30-10:00 | J12: Buenas opiniones entre estudiantes. Tomaban un tp por semana con cada tema visto, sirve mucho hacerlos para ir al día, no son pesados.
A13: 6801 | B13: BORDA-ZOTTO | C13: LU-JU | D13: PRESENCIAL | E13: 10:00-11:30 | F13: MEDIO | G13: ESCRITO | H13: NO | I13: NO | J13: Se aprende mucho de las clases, en las que se explican los casos que luego se toman en los parciales. A la hora de rendir, se hace con los apuntes y se eligen para contestar 2 de 5 preguntas. Se recomienda asistir a las clases. | K13: TECNICA
A14: 6802 | B14: BORDA-ZOTTO | C14: LU-JU | D14: PRESENCIAL | E14: 10:00-11:30 | F14: MEDIO | G14: ESCRITO | H14: NO | I14: NO | J14: Se aprende mucho de las clases, en las que se explican los casos que luego se toman en los parciales. A la hora de rendir, se hace con los apuntes y se eligen para contestar 2 de 5 preguntas. Se recomienda asistir a las clases. | K14: TECNICA
A15: 6860 | B15: BORDA-CAPRA | C15: LU-JU | D15: PRESENCIAL | E15: 10:00-11:30 | F15: MEDIO | G15: MIXTO | H15: SI | J15: Muy buena la recomiendo mucho. La profesora una genia, super dinámica la clase, fácil de seguir y divertida. Los parciales son exactamente lo que ella da en clase y deja a votación si hacer 2 o 3 para que sea más liviano y las fechas lo mismo, ella da opciones y se vota cual queda.
A16: 6881 | B16: DE LORENZO-LAVALLE G. | C16: MA-VI | D16: PRESENCIAL | E16: 10:00-11:30 | F16: MEDIO | G16: MIXTO | H16: NO | J16: El profesor Lavalle explica de una manera dinámica y se le entiende muchísimo. No pasa lo mismo con otros docentes de la catedra, nunca explica el tema que le toca, se va por las ramas y termina hablando de otra cosa que no sirve. No toman asistencia nunca. Lo malo es que tardan muchísimo en pasar las notas de los parciales, para el primer parcial estuvieron 1 mes sin decirnos nuestra nota, también siempre llegan al menos 15 minutos tarde a la clase. El parcial se divide en 2 partes, la primera es multiple choice y si lo aprobas, pasas a la parte escrita, donde te suelen dejar usar el código civil.
A17: 6823 | B17: GARRIDO C.-BALMACEDA M. | C17: MA-VI | D17: PRESENCIAL | E17: 10:00-11:30 | F17: MEDIO | G17: MIXTO | H17: SI | I17: SI | J17: Las clases son entretenidas y dinámicas. Cada clase intercala entre dos profes para dictar la clase. No toman lista, ni mandan trabajos prácticos pero piden alguna que otra tarea en la primer parte de la materia. En los exámenes se toma teoría y práctica, son para redactar y multiple choice. El recuperatorio y el final son orales. | K17: TECNICA
A18: 6828 | B18: GARRIDO C.-CARTA ADRIAN | C18: LU-JU | D18: PRESENCIAL | E18: 10:00-11:30 | F18: MEDIO | G18: ESCRITO | H18: NO | I18: NO | J18: Cátedra súper recomendable. El material de estudio es el mismo Código. El profesor es excelente explicando y da muchos ejemplos, muy predispuesto. Las preguntas de los parciales son específicas así que se contestan con precisión, y son muy fáciles si estudias. La gran mayoria aprueba y casi nadie fue a final.
A19: 6824 | B19: GARRIDO C.-CARTA ADRIAN | C19: MA-VI | D19: PRESENCIAL | E19: 10:00-11:30 | F19: MEDIO | G19: ESCRITO | H19: NO | I19: NO | J19: Cátedra súper recomendable. El material de estudio es el mismo Código. El profesor es excelente explicando y da muchos ejemplos, muy predispuesto. Las preguntas de los parciales son específicas así que se contestan con precisión, y son muy fáciles si estudias. La gran mayoria aprueba y casi nadie fue a final.
A20: 6845 | B20: LAFERRIERE-MAYOR L. | C20: LU-JU | D20: PRESENCIAL | E20: 10:00-11:30 | F20: ALTO | G20: MIXTO | H20: SI | J20: Explica las veces que sean necesarias sin problema y se manejan acorde a un cronograma para organiarse. Es necesario estudiar y se recomienda mantenerse al día con el material de estudio para facilitar la cursada. Los parciales son 5 preguntas choice y dos a desarrollar.
A21: 6846 | B21: LAFERRIERE-CRICI | C21: LU-JU | D21: PRESENCIAL | E21: 11:30-13:00 | F21: ALTO | G21: MIXTO | H21: SI | J21: Son bastante exigentes pero se aprende, buenos profes, mandan apuntes de las clases que sirven para estudiar. Los parciales son puntos choice a justificar y puntos a desarrollar y podes rendir un recuperatorio en caso de que te falte poquito para promocionar.
A22: 6803 | B22: PERALTA MARISCAL-LOVECE G. | C22: MA-VI | D22: VIRTUAL | E22: 10:00-11:30 | F22: ALTO | G22: ESCRITO | H22: NO | I22: NO | J22: Buena cátedra. Es remota, los parciales los toma de manera presencial, la única manera que verifican la regularidad es asistiendo a clases puntuales dictadas por el titular de cátedra | K22: TECNICA
A23: 6851 | B23: SANTARELLI-JAGOU | C23: MA-VI | D23: VIRTUAL | E23: 10:00-11:30
A24: 6804 | B24: PERALTA MARISCAL-SOBRINO A. | C24: MI | D24: PRESENCIAL | E24: 10:00-13:00 | F24: MEDIO | G24: MIXTO | H24: NO | I24: NO | J24: Los parciales son escritos y orales. No toman lista ni TPs. Usan manuales virtuales que suben al campus
A25: 6882 | B25: DE LORENZO-BERBERE D.J. | C25: LU-JU | D25: PRESENCIAL | E25: 11:30-13:00 | F25: MEDIO | G25: ESCRITO | H25: SI | I25: NO | J25: El docente explica bien pero es acelerado, tiene 2 ayudantes que dan 1 tema cada uno. El final es oral con el titular de cátedra. No tiene intensión de desaprobar estudiantes si quiere que aprendan y participen en clase, también hace que lxs Estudiantes expliquen 1 tema por grupo. | K25: APERTURA
A26: 6825 | B26: GARRIDO C.-RODRIGUEZ | C26: LU-JU | D26: PRESENCIAL | E26: 11:30-13:00 | F26: MEDIO | G26: ESCRITO | H26: SI | J26: Muy buena cátedra, los profesores se turnan para dar las clases, generalmente entre el Dr. Rodríguez y el Dr. Roberts, aunque hay dos ayudantes también, son muy apasionados en dar la materia y esto hace que entiendas, siempre están dispuestos a atender las dudas hasta que comprendas. Se manejan con el CCyC y un manual de dcho. civil que a mi me ayudó bastante para preparar la materia. Son re llevaderas las clases, y la anterior al examen es de repaso. Toman dos parciales con tres preguntas, las respuestas tienen que ser concisas, no es necesario desarrollar mucho. Si estudiaste lo aprobás seguro, la mayoría promocionó.
A27: 6826 | B27: GARRIDO C.-RODRIGUEZ | C27: LU-JU | D27: PRESENCIAL | E27: 11:30-13:00 | F27: MEDIO | G27: ESCRITO | H27: SI | J27: Muy buena cátedra, los profesores se turnan para dar las clases, generalmente entre el Dr. Rodríguez y el Dr. Roberts, aunque hay dos ayudantes también, son muy apasionados en dar la materia y esto hace que entiendas, siempre están dispuestos a atender las dudas hasta que comprendas. Se manejan con el CCyC y un manual de dcho. civil que a mi me ayudó bastante para preparar la materia. Son re llevaderas las clases, y la anterior al examen es de repaso. Toman dos parciales con tres preguntas, las respuestas tienen que ser concisas, no es necesario desarrollar mucho. Si estudiaste lo aprobás seguro, la mayoría promocionó.
A28: 6805 | B28: PERALTA MARISCAL-MORENO | C28: LU-JU | D28: PRESENCIAL | E28: 11:30-13:00 | F28: MEDIO | G28: ESCRITO | H28: SI | J28: No son exigentes, usan el manual de Lovece y evaluan con dos parciales escritos a desarrollar.
A29: 6873 | B29: CROVI-REVIRIEGO N. | C29: LU-JU | D29: PRESENCIAL | E29: 14:00-15:30 | F29: ALTO | G29: MIXTO | H29: SI | I29: NO | J29: 1er Parcial y el 2do escrito, MUY BUEN TRATO DOCENTE, ES ACCESIBLE ES MUY ATENTO AL GRUPO DE WPP Y TIENE VIDEOS DE YOUTUBE
A30: 6883 | B30: DE LORENZO-FELDMAN | C30: MA-VI | D30: PRESENCIAL | E30: 14:00-15:30 | F30: ALTO | I30: SI | J30: Muy exigente, malos comentarios del equipo docente. Mandan muchos tps e investigaciones.
A31: 6827 | B31: GARRIDO C.-MONTALTO A. | C31: LU-JU | D31: PRESENCIAL | E31: 14:00-15:30 | F31: MEDIO | H31: SI | J31: Totalmente recomendable, excelente cátedra, los ayudantes siempre bien dispuestos a responder todas las dudas que surjan, hay que llevarla al día con los artículos del CCyCN que se ven, es una materia "técnica", te toman sólo lo visto en clase, pero hay que conocer muy bien el contenido de los artículos vistos, no es rebuscada.
A32: 6843 | B32: LAFERRIERE-BENAVENTE | C32: LU-JU | D32: VIRTUAL | E32: 14:00-15:30 | F32: MEDIO | G32: ESCRITO | H32: NO | I32: SI | J32: Recomendada. Manual a elección y suben material a un drive. Además el titular tiene un canal de youtube que se pueden utilizar para estudiar. Buena predisposición docente. | K32: TECNICA
A33: 6829 | B33: GARRIDO C.-BRINSEK R. | C33: MI | D33: PRESENCIAL | E33: 14:00-17:00 | F33: ALTO | G33: MIXTO | H33: SI | J33: Es medio exigente pero son clases y contenidos super completos. Trabajamos todo en clase. Rosario es buenísima explicando. Igual, Guillermo (jtp) dio casi todas las clases, es bueno pero no como Rosario. 1er parcial oral (corrección exigente e injusta para algunos, otros con 9 e incompletos), 2° parcial oral bastante tranqui. Son pro alumnx. Rosario es lo más y nota si sabes o no. Clases con powerpoint. | K33: CONSERVADORA
A34: 6861 | B34: BORDA-CAPRA | C34: MA-VI | D34: PRESENCIAL | E34: 15:30-17:00 | F34: MEDIO | G34: MIXTO | H34: SI | J34: Muy buena la recomiendo mucho. La profesora una genia, super dinámica la clase, fácil de seguir y divertida. Los parciales son exactamente lo que ella da en clase y deja a votación si hacer 2 o 3 para que sea más liviano y las fechas lo mismo, ella da opciones y se vota cual queda.
A35: 6878 | B35: CROVI-FISSORE | C35: LU-JU | D35: PRESENCIAL | E35: 15:30-17:00 | F35: ALTO | G35: ESCRITO | H35: SI | I35: NO | J35: Es una comisión bastante exigente, para aprobar es necesario estar al día con las lecturas de la cursada y sobre todo con el manual. Evaluan tomando dos parciales, el primero es a desarollar y el segundo es oral. IMPORTANTE: En el primer cuatrimestre esta comisión no fue abierta por no llegar al mínimo de inscriptos que exige la Facultad.
A36: 6877 | B36: CROVI-GRAFEUILLE | C36: LU-JU | D36: PRESENCIAL | E36: 15:30-17:00 | F36: ALTO | G36: MIXTO | H36: SI | I36: NO | J36: Usan el manual de Rivera. Primer parcial escrito, tres preguntas, dos a desarrollar una especifica (definir un concepto) Segundo parcial oral, tres preguntas a desarrollar. Final oral. Importante seguir la lectura. Los profesores explican muy bien. | K36: TECNICA
A37: 6874 | B37: CROVI-PEREIRA V. | C37: LU-JU | D37: PRESENCIAL | E37: 15:30-17:00 | F37: ALTO | G37: ESCRITO | H37: SI | J37: Desde el primer día suben el cronograma de las clases, pero muchas veces no se respeta. También se carga a un classroom propio de la comisión material adicional como powerpoints y textos extras que ayudan bastante al momento de estudiar para los parciales. Los profes son super buena onda y clarísimos en la explicación, especialmente Nico y Mati que son quienes suelen dictar la materia. Para evaluar toman dos parciales escritos y cada uno cuenta con su recuperatorio. La cátedra es Pro-alumno pero no regalan nota. Es necesario leer y demostrar que adquiriste conocimiento. La cátedra la recomiendo, pero tampoco me pareció excelente. A pesar de que son super claros y que se encuentran a disposición de los alumnos, la organización, en cuanto al dictado de clases y el subir el material al aula virtual, no fue para nada buena. Si no te incomoda eso, la cátedra es buena, pero si pretendes mantener la lectura organizada por fechas y poder tener el material cargado todo de una quizá hayan mejores opciones
A38: 6875 | B38: CROVI-REVIRIEGO N. | C38: LU-JU | D38: PRESENCIAL | E38: 15:30-17:00 | F38: MEDIO | G38: ORAL | H38: SI | I38: NO | J38: Nivel de exigencia medio, "normal". Destacaron buena predisposición. // Son súper desorganizados, pasan la bibliografía por el grupo de wpp y tomaron el parcial un día que no se cursaba, terminaron súper tarde
A39: 6807 | B39: GARRIDO C.-AIZENBERG | C39: MA-VI | D39: PRESENCIAL | E39: 15:30-17:00 | F39: MEDIO | G39: ESCRITO | H39: SI | J39: El profesor Colla es un gran docente que explica de forma muy clara y quiere que aprendas. Te da una gran base de civil para el resto de las materias de esa rama. Dos parciales escritos con casos practicos, si seguis las clases y llevas la materia al dia es promocionable. Ponen notas altas. Muy bien organizadas y esquematizadas las clases, todo con cronograma. Recomiendo!!
A40: 6844 | B40: LAFERRIERE-BENAVENTE | C40: MA-VI | D40: VIRTUAL | E40: 15:30-17:00 | F40: MEDIO | J40: Recomendada. Manual a elección y suben material a un drive. Además el titular tiene un canal de youtube que se pueden utilizar para estudiar. Buena predisposición docente.
A41: 6806 | B41: PERALTA MARISCAL-WEINGARTEN | C41: MA-VI | D41: PRESENCIAL | E41: 15:30-17:00 | H41: SI | J41: Comisión nueva. IMPORTANTE: En el primer cuatrimestre esta comisión no fue abierta por no llegar al mínimo de inscriptos que exige la Facultad.
A42: 6889 | B42: PICASSO-CICCHINO PAULA | C42: MA-VI | D42: PRESENCIAL | E42: 15:30-17:00 | F42: ALTO | H42: SI | J42: La Dra Cicchino es de las docente de derecho privado más claras de la facultad, clave cursar con ella | K42: APERTURA
A43: 6830 | B43: GARRIDO C.-GIAVARINO M. | C43: MI | D43: PRESENCIAL | E43: 15:30-18:30 | F43: ALTO | G43: MIXTO | H43: SI | J43: En mi caso, la recomiendo. Se toma lo dado en clase, y estas son útiles. Son exigentes, pero no es dificil promocionar. De todas formas, no comparto el criterio de evaluación y no recomiendo irse al recuperatorio del 2do parcial ya que es oral, lo mismo en caso de irse a final | K43: TECNICA
A44: 6831 | B44: GARRIDO C.-GIAVARINO M. | C44: MI | D44: PRESENCIAL | E44: 15:30-18:30 | F44: ALTO | G44: MIXTO | H44: SI | J44: En mi caso, la recomiendo. Se toma lo dado en clase, y estas son útiles. Son exigentes, pero no es dificil promocionar. De todas formas, no comparto el criterio de evaluación y no recomiendo irse al recuperatorio del 2do parcial ya que es oral, lo mismo en caso de irse a final. IMPORTANTE: En el primer cuatrimestre esta comisión no fue abierta por no llegar al mínimo de inscriptos que exige la Facultad. | K44: TECNICA
A45: 6876 | B45: CROVI-PEREIRA V. | C45: LU-JU | D45: PRESENCIAL | E45: 17:00-18:30 | F45: ALTO | H45: SI | J45: Desde el primer día suben el cronograma de las clases, pero muchas veces no se respeta. También se carga a un classroom propio de la comisión material adicional como powerpoints y textos extras que ayudan bastante al momento de estudiar para los parciales. Los profes son super buena onda y clarísimos en la explicación, especialmente Nico y Mati que son quienes suelen dictar la materia. Para evaluar toman dos parciales escritos y cada uno cuenta con su recuperatorio. La cátedra es Pro-alumno pero no regalan nota. Es necesario leer y demostrar que adquiriste conocimiento. La cátedra la recomiendo, pero tampoco me pareció excelente. A pesar de que son super claros y que se encuentran a disposición de los alumnos, la organización, en cuanto al dictado de clases y el subir el material al aula virtual, no fue para nada buena. Si no te incomoda eso, la cátedra es buena, pero si pretendes mantener la lectura organizada por fechas y poder tener el material cargado todo de una quizá hayan mejores opciones
A46: 6810 | B46: GARRIDO C.-AIZENBERG | C46: MA-VI | D46: PRESENCIAL | E46: 17:00-18:30 | F46: MEDIO | G46: ESCRITO | H46: SI | J46: El profesor Colla encargado de la clase, tiene beuna llegada los alumnos. Son dos parciales escritos, a desarrollar, con casos practicos. Siguen el cronograma y ponen notas altas.
A47: 6820 | B47: GARRIDO C.-LEIVA R. | C47: MA-VI | D47: VIRTUAL | E47: 17:00-18:30 | F47: MEDIO | G47: ORAL | J47: Las clases estan buenas y toman parcial oral por meet. Los profesores explican bien y conectan bien con los estudiantes. Hay solo un profe que es medio pesado para explicar pero es el que menos está. No te matan en el oral y son comprensivos con los que están haciendo sus primeras materias.
A48: 6821 | B48: GARRIDO C.-LEIVA R. | C48: MA-VI | D48: VIRTUAL | E48: 17:00-18:30 | F48: MEDIO | J48: Las clases estan buenas y toman parcial oral por meet. Los profesores explican bien y conectan bien con los estudiantes. Hay solo un profe que es medio pesado para explicar pero es el que menos está. No te matan en el oral y son comprensivos con los que están haciendo sus primeras materias.
A49: 6832 | B49: GARRIDO C.-SALMASO | C49: LU-JU | D49: PRESENCIAL | E49: 17:00-18:30
A50: 6808 | B50: PERALTA MARISCAL-CUIÑAS R. | C50: LU-JU | D50: PRESENCIAL | E50: 17:00-18:30 | F50: MEDIO | G50: MULTIPLECHOICE | H50: SI | I50: SI | J50: Recomendable, a veces da tps en grupo a resolver en clase, en los parciales toma casi lo mismo. Los dos primeros parciales fue choice y el tercero fueron dos choice y tres a desarrolar. | K50: TECNICA
A51: 6812 | B51: PERALTA MARISCAL-CUIÑAS R. | C51: LU-JU | D51: PRESENCIAL | E51: 17:00-18:30 | F51: MEDIO | G51: MULTIPLECHOICE | H51: SI | I51: SI | J51: Recomendable, a veces da tps en grupo a resolver en clase, en los parciales toma casi lo mismo. Los dos primeros parciales fue choice y el tercero fueron dos choice y tres a desarrolar. | K51: TECNICA
A52: 6809 | B52: PERALTA MARISCAL-SOBRINO A. | C52: MA-VI | D52: PRESENCIAL | E52: 17:00-18:30
A53: 6887 | B53: PICASSO-SAENZ LUIS | C53: LU-JU | D53: PRESENCIAL | E53: 17:00-18:30 | F53: MEDIO | G53: ESCRITO | H53: SI | J53: Cátedra recomendable, dos parciales, oral u escrito, es a elección del profesor, Luis explica bien, la ayudante a veces es medio difícil de seguirla, pero dan lo mismo que el libro. los preguntas de los parciales suelen ser muy puntuales
A54: 6833 | B54: GARRIDO C.-BRINSEK R. | C54: MI | D54: PRESENCIAL | E54: 17:00-20:00 | F54: ALTO | G54: MIXTO | H54: NO | I54: SI | J54: Los profes explican bien, la cursada es bastante ordenada, se usa el manual de Rivera, hay exposición oral en grupo para preparar un fallo. Segundo parcial oral. | K54: CONSERVADORA
A55: 6835 | B55: GARRIDO C.-ROMANO ELISA | C55: MI | D55: PRESENCIAL | E55: 17:00-20:00 | F55: BAJO | G55: ORAL | H55: SI | I55: NO | J55: Cátedra pro alumno, fácil y llevadera. Si prestas atención aprendes, pero si solo querés aprobar te sirve también. Todo lo dado en clase lo envían en PowerPoints y esa es la extensión de lo que te van a tomar. La cantidad/dificultad de las preguntas en el parcial dependen de quién te tome pero ninguno te tira para abajo. | K55: TECNICA
A56: 6884 | B56: DE LORENZO-FELDMAN | C56: LU-JU | D56: PRESENCIAL | E56: 18:30-20:00 | F56: MEDIO | G56: MIXTO | H56: SI | I56: SI | J56: La cursada es llevadera y se explican bien los temas de cursada.
A57: 6885 | B57: DE LORENZO-SANTI | C57: MA-VI | D57: PRESENCIAL | E57: 18:30-20:00 | F57: ALTO | H57: SI | I57: SI | J57: 2 parciales y se toma lo que se da en clase, si o si, no hay sorpresas. Si hay tp es a modo que se refuercen los contenidos.Catedra muy exigente y parciales dificiles. No ponen notas altas. Hay que estudiar mucho
A58: 6886 | B58: DE LORENZO-SANTI | C58: MA-VI | D58: PRESENCIAL | E58: 18:30-20:00 | F58: ALTO | H58: SI | I58: SI | J58: 2 parciales y se toma lo que se da en clase, si o si, no hay sorpresas. Si hay tp es a modo que se refuercen los contenidos.Catedra muy exigente y parciales dificiles. No ponen notas altas. Hay que estudiar mucho
A59: 6888 | B59: PICASSO-RONDINA | C59: MA-VI | D59: PRESENCIAL | E59: 18:30-20:00
A60: 6834 | B60: GARRIDO C.-DELLACQUA M. | C60: MI | D60: PRESENCIAL | E60: 18:30-21:30 | F60: MEDIO | G60: ESCRITO | H60: SI | J60: Excelente cátedra. 2 parciales con sus respectivos recuperatorios (4 oportunidades), y un final por si no llegas a promocionar, pero verdaderamente es muy promocionable. Se adaptaron bien a las clases virtuales, 1 vez por semana 3 hrs se hace un poco pesado pero son muy buenas las explicaciones. Mabel la titular es un amor y Dra Romano da ejemplos muy buenos.
A61: 6838 | B61: GARRIDO C.-DELLACQUA M. | C61: MI | D61: PRESENCIAL | E61: 18:30-21:30 | F61: MEDIO | G61: ESCRITO | H61: SI | J61: Excelente cátedra. 2 parciales con sus respectivos recuperatorios (4 oportunidades), y un final por si no llegas a promocionar, pero verdaderamente es muy promocionable. Se adaptaron bien a las clases virtuales, 1 vez por semana 3 hrs se hace un poco pesado pero son muy buenas las explicaciones. Mabel la titular es un amor y Dra Romano da ejemplos muy buenos.
A62: 6862 | B62: BORDA-ALONSO L. | C62: MA-VI | D62: PRESENCIAL | E62: 20:00-21:30 | F62: MEDIO | G62: ESCRITO | H62: SI | I62: SI | J62: Recomendable, los profes son muy claros y no tienen animos de bochar a nadie, hay bastantes instancias para aprobar, toman un tp que tienen en cuenta si te falta nota. Evaluan con dos parciales a desarrollar con casos prácticos y dejan usar el código. // Hay posiciones encontradas acerca de las correcciones, hubieron muchos bochados (más de la mitad) y no dejan ver las correcciones de los parciales
A63: 6863 | B63: BORDA-GRIMALDI | C63: MA-VI | D63: PRESENCIAL | E63: 20:00-21:30
A64: 6852 | B64: SANTARELLI-MARINO M. | C64: MA-VI | D64: PRESENCIAL | E64: 20:00-21:30
A65: 6853 | B65: SANTARELLI-MARINO M. | C65: MA-VI | D65: PRESENCIAL | E65: 20:00-21:30 | F65: MEDIO | G65: ESCRITO | H65: SI | I65: NO | J65: Toman parciales a desarrollar en los que pueden aparecer algunos V o F. Suben material al campus y responden dudas sin problemas.
A66: 6811 | B66: A DESIG-MARTELLO S. | C66: MA-VI | D66: PRESENCIAL | E66: 21:30-23:00 | F66: MEDIO | G66: ORAL | H66: SI | J66: Buena cátedra, el profe explica bien y tiene buena disposición con los alumnos. Evalúan con 2 parciales orales.
A67: 6836 | B67: GARRIDO C.-L.CASTIÑEIRA | C67: LU-JU | D67: VIRTUAL | E67: 21:30-23:00 | F67: MEDIO | G67: ORAL | H67: SI | I67: NO | J67: Muy recomendada, gran equipo docente, todos se explican muy bien aprendes mucho. | K67: TECNICA
A68: 6837 | B68: GARRIDO C.-L.CASTIÑEIRA | C68: LU-JU | D68: VIRTUAL | E68: 21:30-23:00 | F68: MEDIO | G68: ORAL | H68: SI | I68: NO | J68: Muy recomendada, gran equipo docente, todos se explican muy bien aprendes mucho. | K68: TECNICA
A69: 6870 | B69: PERALTA MARISCAL-REY M. | C69: LU-JU | D69: VIRTUAL | E69: 21:30-23:00 | F69: MEDIO | G69: ESCRITO | H69: SI | I69: NO | J69: Comisión pro alumno, toman dos parciales a desarrollar bastante sencillos (no toman tps).

Sheet DDHH
A1: 📚 DERECHOS HUMANOS Y GARANTÍAS - 2º CUATRI 2026 - LA CÁMPORA 📚
A2: N° | B2: COMISIÓN | C2: DÍAS | D2: MODALIDAD | E2: HORARIO | F2: NIVEL | G2: PARCIAL | H2: TOMA LISTA | I2: TOMA TPS | J2: COMENTARIO | K2: POSTURA
A3: 6425 | B3: PIZZOLO-PAPA ANABEL | C3: LU-JU | D3: PRESENCIAL | E3: 07:00-08:30 | G3: ESCRITO | H3: SI | J3: Muy buena catedra, los dos profesores explican muy bien, primer parcial escrito y el segundo domiciliario. Toman todo lo visto en clase, no es necesario leer toda la bibliografia, sino las partes esenciales q ellos dicen. No toman asistencia en todas las clases pero si tenes q tener 2 o 3 para rendir cada parcial. Muy pro alumno, corrigen super rapido, la recomiendo mucho
A4: 6420 | B4: PIZZOLO-PAPA ANABEL | C4: LU-JU | D4: PRESENCIAL | E4: 07:00-08:30 | G4: ESCRITO | H4: SI | J4: Muy buena catedra, los dos profesores explican muy bien, primer parcial escrito y el segundo domiciliario. Toman todo lo visto en clase, no es necesario leer toda la bibliografia, sino las partes esenciales q ellos dicen. No toman asistencia en todas las clases pero si tenes q tener 2 o 3 para rendir cada parcial. Muy pro alumno, corrigen super rapido, la recomiendo mucho
A5: 6430 | B5: SABA-AIMAR | C5: LU-JU | D5: VIRTUAL | E5: 07:00-08:30 | F5: BAJO | G5: MIXTO | J5: Modalidad Evaluación: Cada alumno desarrolla un trabajo práctico escrito individual tipo monografía (pautas designadas al inicio) y un trabajo grupal que debe exponer en un coloquio. Bibliografía y Programa: Todo el material se envía en formato digital al inicio y durnte el curso su desarrollo
A6: 6450 | B6: TRAVIESO-LOGIOVINE YAMILA | C6: MA-VI | D6: PRESENCIAL | E6: 07:00-08:30 | F6: MEDIO | G6: MIXTO | H6: SI | I6: SI | J6: Los martes hay una profesora y los viernes otra, son super organizados y los ayudantes de cátedra ayudan mucho. Se trabaja con un manual de DDHH a elección, pero lo mejor es usar el de la cátedra. Ellos lo suben al campus y suman bibliografía que suma bastante. Hay pp que ayudan un montón a estudiar porque te dicen que no te puede faltar para estudiar. El primer parcial escrito, a desarrollar y un caso práctico bastante simple. Hay un punto que si o si tiene que estar bien hecho para aprobar el parcial. Si vas a clase seguro aprobas, hay que leer pero es clave tomar apuntes y prestar atención en las clases. El segundo parcial es oral. Elegís vos con qué tema empezar y después si te ven bien te hacen 1/2 preguntas de otros temas y nada más. Tiene 3 tps opcionales que no se promedian pero sirven para estudiar. Hay 1 tp obligatorio para resumir 2 fallos que se entrega por campus.
A7: 6451 | B7: TRAVIESO-LOGIOVINE YAMILA | C7: MA-VI | D7: PRESENCIAL | E7: 07:00-08:30 | F7: MEDIO | G7: MIXTO | H7: SI | I7: SI | J7: Los martes hay una profesora y los viernes otra, son super organizados y los ayudantes de cátedra ayudan mucho. Se trabaja con un manual de DDHH a elección, pero lo mejor es usar el de la cátedra. Ellos lo suben al campus y suman bibliografía que suma bastante. Hay pp que ayudan un montón a estudiar porque te dicen que no te puede faltar para estudiar. El primer parcial escrito, a desarrollar y un caso práctico bastante simple. Hay un punto que si o si tiene que estar bien hecho para aprobar el parcial. Si vas a clase seguro aprobas, hay que leer pero es clave tomar apuntes y prestar atención en las clases. El segundo parcial es oral. Elegís vos con qué tema empezar y después si te ven bien te hacen 1/2 preguntas de otros temas y nada más. Tiene 3 tps opcionales que no se promedian pero sirven para estudiar. Hay 1 tp obligatorio para resumir 2 fallos que se entrega por campus.
A8: 6470 | B8: ABRAMOVICH-VITOLO A. | C8: MA-VI | D8: PRESENCIAL | E8: 08:30-10:00 | F8: MEDIO | G8: ESCRITO | H8: NO | I8: SI | J8: NO TOMA PARCIAL - TRABAJO FINAL INTEGRADOR | K8: CONSERVADORA
A9: 6410 | B9: PINTO-FELGUERAS S. | C9: MA-VI | D9: PRESENCIAL | E9: 08:30-10:00 | H9: NO | J9: 2 parciales con 4/5 preguntas a desarrollar, te dejan usar bibliografia y apuntes( nada electronico) son casos practicos a resolver
A10: 6429 | B10: PIZZOLO-ROHR ALDANA | C10: LU-JU | D10: PRESENCIAL | E10: 08:30-10:00 | F10: MEDIO | G10: MIXTO | H10: NO | I10: SI | J10: La docente adjunta explica muy bien y tiene muchísimos ayudantes que explican los temas de la cursada, usa el manual de gonzales napolitano. el 1er parcial es de 4 preguntas escrito, y el 2do es domiciliario donde hay que explicar un derecho que se dio en clase y contestar preguntas además hay que adjuntar la legislación que contempla el derecho elegido | K10: APERTURA
A11: 6433 | B11: SABA- | C11: MA-VI | D11: PRESENCIAL | E11: 08:30-10:00 | F11: MEDIO | G11: ESCRITO | H11: SI | J11: Catedra recomendable. Te hacen pensar pero no es dificil. Aprendes.
A12: 6452 | B12: TRAVIESO-BALBI MELISA | C12: LU-JU | D12: PRESENCIAL | E12: 08:30-10:00 | F12: MEDIO | G12: ESCRITO | H12: SI | I12: SI | J12: Los profes son copados y hacen que las clases tengan buenas dinámicas. Los parciales son dos con preguntas a desarrollar, toman TPs que no son obligatorios. Mandan fallos, no usan manual. No son exigentes pero se aprende bastante
A13: 6416 | B13: PIZZOLO-ROHR ALDANA | C13: MI | D13: PRESENCIAL | E13: 08:30-11:30 | F13: MEDIO | G13: MIXTO | H13: NO | I13: SI | J13: La docente adjunta explica muy bien y tiene muchísimos ayudantes que explican los temas de la cursada, usa el manual de gonzales napolitano. el 1er parcial es de 4 preguntas escrito, y el 2do es domiciliario donde hay que explicar un derecho que se dio en clase y contestar preguntas además hay que adjuntar la legislación que contempla el derecho elegido | K13: APERTURA
A14: 6434 | B14: SABA-GIOSA L. | C14: MI | D14: PRESENCIAL | E14: 08:30-11:30 | F14: ALTO | G14: MIXTO | H14: NO | I14: NO | J14: un parcial escrito + domiciliario, manda controles de lectura todas las semanas. | K14: APERTURA
A15: 6453 | B15: TRAVIESO-GARCIA M. | C15: SA | D15: PRESENCIAL | E15: 08:30-11:30 | F15: BAJO | G15: MIXTO | H15: NO | I15: NO | J15: BIBLIO EN DRIVE Y MANUAL
A16: 6454 | B16: TRAVIESO-GARCIA M. | C16: SA | D16: PRESENCIAL | E16: 08:30-11:30 | F16: BAJO | G16: MIXTO | H16: NO | I16: NO | J16: BIBLIO EN DRIVE Y MANUAL
A17: 6476 | B17: ABRAMOVICH-GOMEZ LUCIA | C17: LU-JU | D17: PRESENCIAL | E17: 10:00-11:30 | F17: BAJO | G17: MIXTO | H17: NO | I17: NO | J17: Dos parciales de temas victos en clases, la profesora adjunta tiene buena llegada a los alumnos
A18: 6417 | B18: ABRAMOVICH-MORALES D. | C18: LU-JU | D18: PRESENCIAL | E18: 08:30-10:00 | J18: Comisión nueva
A19: 6411 | B19: ABRAMOVICH-MORALES D. | C19: LU-JU | D19: PRESENCIAL | E19: 10:00-11:30 | F19: ALTO | G19: MIXTO | H19: SI | I19: SI | J19: Toman parcial escrito y otro oral. buena llegada con los estudiantes. Cátedra para enriquecerse en materia de DDHH y Garantías. | K19: TECNICA
A20: 6436 | B20: SABA-ZALDUMBIDE | C20: MA-VI | D20: PRESENCIAL | E20: 10:00-11:30 | F20: MEDIO | G20: MIXTO | H20: SI | I20: SI | J20: Toman un examen inicial para orientar, seguido de un TP grupal y un final oral con posibilidad de recuperatorio. Su material esta en un MicrosoftTeam y con clases de apoyo.
A21: 6455 | B21: TRAVIESO-CURIEL | C21: LU-JU | D21: PRESENCIAL | E21: 14:00-15:30 | F21: MEDIO | G21: ESCRITO | H21: NO | I21: NO | J21: Recomendada por quienes la cursaron. Toma lo que da en clase, cursada amena. Pro alumno, no tienen problema en volver a explicar un tema y ponen notas altas. El examen puede incluir V/F, preguntas teóricas y casos prácticos. Profundiza cómo acceder al Sistema internacional de DDHH, se ve toda la parte procesal, y luego se profundiza en derechos específicos. Destacan su contenido de actualidad. | K21: TECNICA
A22: 6456 | B22: TRAVIESO-SANCHEZ MANCINI | C22: LU-JU | D22: PRESENCIAL | E22: 10:00-11:30 | F22: MEDIO | G22: ESCRITO | H22: SI | I22: SI | J22: Cátedra ordenada, siguen el cronograma, los profes son copados y explican bien, se sube la bibliografía al campus. No tienen ánimos de bochar a nadie, con los apuntes de clase y complementando un poco con la bibliografía se aprueba.
A23: 6471 | B23: ABRAMOVICH-G.NAPOLITANO | C23: LU-JU | D23: VIRTUAL | E23: 11:30-13:00 | F23: MEDIO | G23: MULTIPLECHOICE | H23: NO | I23: SI | J23: Gran comisión para los que queremos seguir derecho internacional público. Las profesoras explican bien y no tienen problema en contestar preguntas, hay un grupo de Whatsapp con los ayudantes para la dudas. Los parciales son por Forms mediante multiplechoice, durante la cursada mandaron TPs para la regularidad
A24: 6412 | B24: PINTO-SALGADO A. | C24: LU-JU | D24: PRESENCIAL | E24: 11:30-13:00 | G24: MULTIPLECHOICE | H24: SI | I24: SI, NO | J24: 2 Parciales verdadero y falso sin justificar, la bibliografia la suben a facebook los docentes
A25: 6458 | B25: TRAVIESO-CURIEL | C25: LU-JU | D25: PRESENCIAL | E25: 15:30-17:00 | F25: MEDIO | G25: ESCRITO | H25: NO | I25: NO | J25: Recomendada por quienes la cursaron. Toma lo que da en clase, cursada amena. Pro alumno, no tienen problema en volver a explicar un tema y ponen notas altas. El examen puede incluir V/F, preguntas teóricas y casos prácticos. Profundiza cómo acceder al Sistema internacional de DDHH, se ve toda la parte procesal, y luego se profundiza en derechos específicos. Destacan su contenido de actualidad. | K25: TECNICA
A26: 6457 | B26: TRAVIESO-MEIS M. | C26: LU-JU | D26: PRESENCIAL | E26: 11:30-13:00 | F26: BAJO | G26: MIXTO | H26: NO | I26: SI | J26: Explican bien y no tiene problema en poner notas altas. El primer parcial es domiciliario y el segundo oral en el que sirve mucho el concepto que tengan de vos por la participación en clase. // Son desorganizados, a veces faltan a las clases sin avisar. No tienen buena llegada con los estudiantes, no recomendada.
A27: 6403 | B27: PIZZOLO-RIERA | C27: MA-VI | D27: PRESENCIAL | E27: 11:30-13:30 | F27: MEDIO | G27: MIXTO | H27: SI | I27: SI | J27: Toman el primer parcial de forma escrita y el segundo oral. Toman TPs para la regularidad y nota. Son responsables con el cronograma
A28: 6472 | B28: ABRAMOVICH-G.NAPOLITANO | C28: LU-JU | D28: VIRTUAL | E28: 13:00:14:30 | F28: MEDIO | G28: MULTIPLECHOICE | H28: NO | I28: SI | J28: Gran comisión para los que queremos seguir derecho internacional público. Las profesoras explican bien y no tienen problema en contestar preguntas, hay un grupo de Whatsapp con los ayudantes para la dudas. Los parciales son por Forms mediante multiplechoice, durante la cursada mandaron TPs para la regularidad
A29: 6437 | B29: SABA-PEREZ ANDREA | C29: LU-JU | D29: PRESENCIAL | E29: 14:00-15:30 | F29: MEDIO | G29: MIXTO | H29: SI | I29: SI | J29: Los parciales varian entre multiple choice y preguntas a desarrollar, corrige de forma global.Toma asistencia, se promociona con 6
A30: 6438 | B30: SABA-LOIANNO ADELINA | C30: MI | D30: PRESENCIAL | E30: 14:00-17:00 | F30: ALTO | G30: ESCRITO | H30: SI | I30: SI | J30: Dos parciales escrito, llegada al alumno. tp como regularidad, no siempre toma asistencia | K30: TECNICA
A31: 6473 | B31: A DESIGNAR - AGUIRRE L. | C31: LU-JU | D31: PRESENCIAL | E31: 15:30-17:00 | F31: BAJO | G31: ESCRITO | H31: NO | I31: SI | J31: La profesora Aguirre tiene buena llegada con los alumnos, toma dos parciales como TPs a entregar con tiempo y un final integrador
A32: 6421 | B32: PIZZOLO-PAVIONI NATALÍ | C32: MA-VI | D32: PRESENCIAL | E32: 15:30-17:00 | F32: MEDIO | G32: ESCRITO | H32: NO | I32: NO | J32: Parciales escritos(preguntas a desarrollar, verdaderos y falsos a justificar). El recuperatorio y el final son orales. Contenido del primer parcial , la mayoría pudo haber sido visto en el cbc. En el segundo parcial, se complementan todos los temas con fallos. Los profesores explican muy bien. RECOMENDADA. | K32: APERTURA
A33: 6422 | B33: PIZZOLO-RIERA | C33: MA-VI | D33: PRESENCIAL | E33: 15:30-17:00 | F33: MEDIO | G33: MIXTO | H33: SI | I33: SI | J33: Muy buen equipo docente, recomiendo. Primer parcial escrito, segundo simulacro de juicio. Se aprende mucho.
A34: 6459 | B34: TRAVIESO-G.STIER | C34: MA-VI | D34: PRESENCIAL | E34: 15:30-17:00 | F34: MEDIO | G34: MIXTO | H34: SI | I34: NO | J34: Muy recomendada. Cátedra proalumno y con ánimos de que aprendas participando e involucrándose. Tienen muy buen trato lo que hace muy amena la cursada, muy recomendada si estás arrancando en la Facultad. Toman parciales domiciliarios, escritos y orales que se pueden responder con las guías y lo dado en clase. 3 instancias de evaluación, la primera es un tp domiciliario, la segunda es un escrito presencial, y la tercera es un oral. También se arman clases de debate que suman | K34: APERTURA
A35: 6413 | B35: PINTO-FILIPPINI | C35: MI | D35: PRESENCIAL | E35: 15:30-18:30 | F35: ALTO | G35: MIXTO | H35: NO | I35: SI | J35: Se recomienda quienes les guste la materia y se quieran especializar en la materia. Se aprende mucho pero hay que estudiar y muy importante seguirle el ritmo.
A36: 6415 | B36: PINTO-SIGAL | C36: MI | D36: PRESENCIAL | E36: 15:30-18:30
A37: 6474 | B37: ABRAMOVICH-REVIRIEGO | C37: LU-JU | D37: PRESENCIAL | E37: 17:00-18:30 | F37: ALTO | G37: MIXTO | H37: SI | I37: NO | J37: Varían entre parciales multiplechoice y a desarrollar. Si bien siguen el cronograma pueden ser desorganizados con las clases
A38: 6423 | B38: PIZZOLO-PAVIONI NATALÍ | C38: MA-VI | D38: PRESENCIAL | E38: 17:00-18:30 | F38: MEDIO | G38: ESCRITO | H38: NO | I38: NO | J38: Parciales escritos(preguntas a desarrollar, verdaderos y falsos a justificar). El recuperatorio y el final son orales. Contenido del primer parcial , la mayoría pudo haber sido visto en el cbc. En el segundo parcial, se complementan todos los temas con fallos. Los profesores explican muy bien. RECOMENDADA. | K38: APERTURA
A39: 6424 | B39: PIZZOLO-ZIMERMAN S | C39: MA-VI | D39: PRESENCIAL | E39: 17:00-18:30 | F39: ALTO | G39: MIXTO | H39: SI | I39: SI | J39: tres parciales; dos escritos y uno oral. Cátedra super recomendable, comunmente visita a la EX-ESMA; hacen simulacro de la Corte IDH. | K39: APERTURA
A40: 6440 | B40: SABA-FERREIRA | C40: MA-VI | D40: PRESENCIAL | E40: 17:00-18:30 | F40: BAJO | G40: ESCRITO | H40: SI | J40: Buenas clases en las tematicas de genero, dos parciales sobre la identificacion de problematicas vistas en clases, a travez de casos.
A41: 6461 | B41: TRAVIESO-G.STIER | C41: MA-VI | D41: PRESENCIAL | E41: 17:00-18:30 | F41: MEDIO | G41: MIXTO | H41: SI | I41: NO | J41: Muy recomendada. Cátedra proalumno y con ánimos de que aprendas participando e involucrándose. Tienen muy buen trato lo que hace muy amena la cursada, muy recomendada si estás arrancando en la Facultad. Toman parciales domiciliarios, escritos y orales que se pueden responder con las guías y lo dado en clase. 3 instancias de evaluación, la primera es un tp domiciliario, la segunda es un escrito presencial, y la tercera es un oral. También se arman clases de debate que suman | K41: APERTURA
A42: 6460 | B42: TRAVIESO-IELLIMO M. | C42: LU-JU | D42: PRESENCIAL | E42: 17:00-18:30 | F42: MEDIO | G42: ESCRITO | H42: SI | I42: SI | J42: Cátedra organizada, dan un cronograma y lo siguen al pie de la letra sin sorpresas. Se toma lo dado en clase, no tienen ánimos de bochar a nadie y tienen buen trato con los estudiantes. Es importante tener alguna idea de la organización de la CN y tener una con los tratados de DDHH porque te permiten usarla en el parcial. Son principalmente 2 profes, ambos muy copados pero una toma lista normal y el otro lo hace por TPs (fáciles). | K42: APERTURA
A43: 6404 | B43: PIZZOLLO-FLAX | C43: MI | D43: PRESENCIAL | E43: 17:00-20:00 | F43: MEDIO | G43: ESCRITO | H43: SI | I43: NO | J43: A veces toma asistencia uno d elos profesores. Los parciales son 4 preguntas escritas.
A44: 6475 | B44: ABRAMOVICH-PULVIRENTI O | C44: MA-VI | D44: PRESENCIAL | E44: 18:30-20:00 | F44: BAJO | G44: MULTIPLECHOICE | H44: NO | I44: NO | J44: Toman dos parciales multiplechoice bastante faciles que con ir a las clases podés aprobar sin estudiar. Se aprende poco para se una materia de las primeras y tan interesante como DDHH. Hay comentarios negativos acerca de la redacción de los exámenes
A45: 6414 | B45: PINTO-CONY GUILLERMO | C45: MA-VI | D45: PRESENCIAL | E45: 18:30-20:00 | G45: ESCRITO | H45: SI | J45: Examenes a desarrollar largos con preguntas concretas, toma lo visto en clase
A46: 6426 | B46: PIZZOLO-LUCHETI | C46: LU-JU | D46: PRESENCIAL | E46: 18:30-20:00 | F46: MEDIO | G46: ESCRITO | H46: SI | I46: SI | J46: Los profesores son copados pero pueden ser desorganizados con el material y se van por las ramas. Toman dos parciales domiciliarios, pueden tener comentarios conservadores en la cursada. | K46: CONSERVADORA
A47: 6427 | B47: PIZZOLO-ZIMERMAN S | C47: MA-VI | D47: PRESENCIAL | E47: 18:30-20:00 | F47: ALTO | G47: MIXTO | H47: SI | I47: SI | J47: 1er examen escrito - oral - ecrito. 3 parciales. muy pro alumno, super abierto. comunmente hacen una visita a la Ex-ESMA. | K47: APERTURA
A48: 6441 | B48: SABA-AIMAR K. | C48: MA-VI | D48: PRESENCIAL | E48: 18:30-20:00 | F48: MEDIO | G48: MIXTO | H48: NO | I48: SI | J48: Evalúan con un oral y un TP. Los profes son copados con los estudiantes, no toman lista y no tienen ánimos de bochar. Recomendada
A49: 6462 | B49: TRAVIESO-IELLIMO M. | C49: LU-JU | D49: PRESENCIAL | E49: 18:30-20:00 | F49: MEDIO | G49: ESCRITO | H49: SI | I49: SI | J49: Cátedra organizada, dan un cronograma y lo siguen al pie de la letra sin sorpresas. Se toma lo dado en clase, no tienen ánimos de bochar a nadie y tienen buen trato con los estudiantes. Es importante tener alguna idea de la organización de la CN y tener una con los tratados de DDHH porque te permiten usarla en el parcial. Son principalmente 2 profes, ambos muy copados pero una toma lista normal y el otro lo hace por TPs (fáciles). | K49: APERTURA
A50: 6478 | B50: PINTO CAVANA | C50: MI | D50: PRESENCIAL | E50: 18:30-21:30 | J50: Comisión nueva
A51: 6401 | B51: A DESIG.-LUBERTINO | C51: MI | D51: PRESENCIAL | E51: 18:30-21:30 | F51: ALTO | H51: SI | I51: SI | J51: Versiones mixtas, algunos destacan que tiene buen nivel académico y vocación docente (explican bien, repiten el tema si hace falta), otros que hay mucha exigencia (tps todas las semanas, por ejemplo, aunque esto puede variar según el cuatrimestre).
A52: 6442 | B52: SABA-TAMBUSSI C. | C52: MI | D52: PRESENCIAL | E52: 18:30-21:30 | F52: ALTO | G52: ESCRITO | H52: SI | I52: NO | J52: Muy exigente. Hay comentarios negativos acerca de la cantidad de aprobados por comisión
A53: 6477 | B53: ABRAMOVICH-PULVIRENTI O | C53: MA-VI | D53: PRESENCIAL | E53: 20:00-21:30 | F53: BAJO | G53: MULTIPLECHOICE | H53: NO | I53: NO | J53: Toman dos parciales multiplechoice, se aprueba con lo visto en clase y no hay tanta carga de contenido en la materia. Hay comentarios negativos acerca de la redacción de los exámenes
A54: 6428 | B54: PIZZOLO-TABOADA FEDERICO GERMÁN | C54: LU-JU | D54: VIRTUAL | E54: 20:00-21:30
A55: 6463 | B55: TRAVIESO-CARZOGLIO | C55: MA-VI | D55: PRESENCIAL | E55: 20:00-21:30 | F55: MEDIO | G55: MIXTO | H55: SI | I55: NO | J55: Recomendable. Son dos examenes, el primero escrito y segundo es un video (oral), al material lo suben al campus y respetan el cronograma. Las clases son dinámicas, organizadas y se prestan al debate. Tardan en entregar las notas, pero tanto los profesores como los ayudantes explican super claro, no tienen animos de bochar a nadie. | K55: APERTURA
A56: 6443 | B56: SABA-FERREIRA | C56: MI | D56: PRESENCIAL | E56: 20:00-23:00 | F56: BAJO | G56: ESCRITO | H56: SI | I56: NO | J56: Los profes son súper atentos y no tienen ánimos de que te vaya mal, las clases son entretenidas. Suben guías de estudio para estudiar con preguntas que luego son similares a las de los parciales. Podés sumar puntos rindiendo un TP optativo o participando en clase
A57: 6466 | B57: TRAVIESO-CARZOGLIO | C57: MA-VI | D57: PRESENCIAL | E57: 21:30-23:00 | F57: MEDIO | G57: MIXTO | H57: SI | I57: NO | J57: Recomendable. Son dos examenes, el primero escrito y segundo es un video (oral), al material lo suben al campus y respetan el cronograma. Las clases son dinámicas, organizadas y se prestan al debate. Tardan en entregar las notas, pero tanto los profesores como los ayudantes explican super claro, no tienen animos de bochar a nadie. | K57: APERTURA
A58: 6464 | B58: TRAVIESO-VANZILLOTA | C58: LU-JU | D58: VIRTUAL | E58: 21:30-23:00 | F58: MEDIO | G58: MIXTO | H58: SI | I58: NO | J58: Los profesores tienen buena llegada con los estudiantes, el primer parcial es multiplechoice y el segundo un ensayo que tenés que hacer en una semana. Explican bien y se toma lo dado en clase más el material que ellos mandan por Drive muy bien organizado.
A59: 6465 | B59: TRAVIESO-VANZILLOTA | C59: LU-JU | D59: VIRTUAL | E59: 21:30-23:00 | F59: MEDIO | G59: MIXTO | H59: SI | I59: NO | J59: Los profesores tienen buena llegada con los estudiantes, el primer parcial es multiplechoice y el segundo un ensayo que tenés que hacer en una semana. Explican bien y se toma lo dado en clase más el material que ellos mandan por Drive muy bien organizado.

Sheet ANÁLISIS 
A1: 📚 ANÁLISIS ECONÓMICO Y FINANCIERO - 2º CUATRI 2026 - LA CÁMPORA 📚
A2: N° | B2: COMISIÓN | C2: DÍAS | D2: MODALIDAD | E2: HORARIO | F2: NIVEL | G2: PARCIAL | H2: TOMA LISTA | I2: TOMA TPS | J2: COMENTARIO | K2: CORTE 1° CUATRI | L2: POSTURA
A3: 8659 | B3: DI PELINO-BARREÑA M. | C3: MI | D3: PRESENCIAL | E3: 10:00-13:00 | F3: MEDIO | G3: MIXTO | H3: SI | I3: SI | J3: No tienen ánimos de desaprobar, explican bien y se hacen dinámicas las clases. Toman dos parciales escritos y orales con TPs para subir nota | K3: =VLOOKUP(A3,CORTE!$A$2:$B$1045,2,0)
A4: 8620 | B4: MAZZA-HOFMANN | C4: MA-VI | D4: PRESENCIAL | E4: 07:00-08:30 | F4: BAJO | G4: ESCRITO | H4: SI | I4: NO | J4: Buenas cátedra, dos parciales escritos de verdadero o falsos justificar en una sola oración. | K4: =VLOOKUP(A4,CORTE!$A$2:$B$1045,2,0) | L4: TECNICA
A5: 8610 | B5: STORDEUR-BIDART MARINA | C5: LU-JU | D5: PRESENCIAL | E5: 07:00-08:30 | F5: MEDIO | G5: MIXTO | H5: NO | I5: NO | J5: Usan el manual de Mankiew, toman lo visto en clase que es lo mismo que leer las filminas que mandan. Los parciales son mitad multiplechoice y mitad escrito a desarrollar de casos prácticos | K5: =VLOOKUP(A5,CORTE!$A$2:$B$1045,2,0)
A6: 8611 | B6: STORDEUR-ZUNINO | C6: MA-VI | D6: PRESENCIAL | E6: 07:00-08:30 | F6: ALTO | G6: MIXTO | H6: SI | I6: NO | J6: El docente no permite que el alumnado pregunte,se cursa con el manual de la catedra, el parcial es súper rebuscado. Cambia la modalidad de los parciales. | K6: =VLOOKUP(A6,CORTE!$A$2:$B$1045,2,0)
A7: 8621 | B7: MAZZA-VALERO J. | C7: MI | D7: PRESENCIAL | E7: 07:00-10:00 | F7: MEDIO | G7: ESCRITO | H7: SI | I7: NO | J7: Dos parciales escritos a desarrollar. No hay tps. toma asistencia. Nivel alto aprobados | K7: =VLOOKUP(A7,CORTE!$A$2:$B$1045,2,0) | L7: TECNICA
A8: 8638 | B8: ARGENTO-GONZALEZ RODRIGUEZ | C8: LU-JU | D8: PRESENCIAL | E8: 08:30-10:00 | F8: MEDIO | G8: ESCRITO | H8: SI | I8: NO | J8: Las clases son dinámicas, mandan los parciales por Forms que se pueden hacer desde casa estudiando lo visto en clases. Para estudiar mandan textos cortos +lo visto | K8: =VLOOKUP(A8,CORTE!$A$2:$B$1045,2,0)
A9: 8646 | B9: DI PELINO-HERNANDEZ | C9: LU-JU | D9: VIRTUAL | E9: 08:30-10:00 | K9: =VLOOKUP(A9,CORTE!$A$2:$B$1045,2,0)
A10: 8640 | B10: DI PELINO-TESELMAN | C10: MA-VI | D10: PRESENCIAL | E10: 08:30-10:00 | F10: ALTO | G10: ESCRITO | H10: SI | I10: NO | J10: Las clases las da EUGENIO que literalmente es un genio explicando, ambos parciales escritos con 5 puntos, el primer parcial es más que nada de “ejercicios” y el segundo más teórico definiciones,etc. Ambos parciales tienen su recuperatorio. Con estudiar de los apuntes de clases llegas bien, clave prestar atención y tener BUENOS apuntes. | K10: =VLOOKUP(A10,CORTE!$A$2:$B$1045,2,0)
A11: 8622 | B11: MAZZA-HOFMANN | C11: MA-VI | D11: PRESENCIAL | E11: 08:30-10:00 | F11: BAJO | G11: ESCRITO | H11: SI | I11: NO | J11: Buena cátedra. Promocionable. Se estudia de lo dado en clase, dos parciales v o f a justificar con una oración. | K11: =VLOOKUP(A11,CORTE!$A$2:$B$1045,2,0) | L11: TECNICA
A12: 8613 | B12: PEREZ E-SINGERMAN | C12: MA-VI | D12: PRESENCIAL | E12: 08:30-10:00 | F12: MEDIO | G12: ORAL | H12: SI | I12: NO | J12: 2 parciales tipo coloquio, y un debate a mitad de cursada. Catedra recomendable, profes copados, sin ánimos de bochar y ponen buenas notas. | K12: =VLOOKUP(A12,CORTE!$A$2:$B$1045,2,0) | L12: APERTURA
A13: 8612 | B13: STORDEUR-BIDART MARINA | C13: LU-JU | D13: PRESENCIAL | E13: 08:30-10:00 | F13: MEDIO | G13: MIXTO | H13: NO | I13: NO | J13: Usan el manual de Mankiew, toman lo visto en clase que es lo mismo que leer las filminas que mandan. Los parciales son mitad multiplechoice y mitad escrito a desarrollar de casos prácticos | K13: =VLOOKUP(A13,CORTE!$A$2:$B$1045,2,0)
A14: 8641 | B14: DI PELINO-HERNANDEZ | C14: MI | D14: PRESENCIAL | E14: 08:30-11:30 | F14: MEDIO | G14: ESCRITO | H14: NO | I14: NO | J14: La profe explica muy bien. El primer parcial es domiciliario y el otro es a desarrollar. El segundo parcial es a libro abierto. Muy buena cátedra pro alumno | K14: =VLOOKUP(A14,CORTE!$A$2:$B$1045,2,0)
A15: 8623 | B15: MAZZA-MAZZA | C15: SA | D15: PRESENCIAL | E15: 08:30-11:30 | F15: MEDIO | G15: MIXTO | H15: NO | I15: NO | J15: Hace la materia súper llevadera, no tiene ánimos de bochar a nadie. Los parciales escritos se dividen en dos partes, 5 preguntas múltiples choice y 2 preguntas para desarrollar. Muy recomendada. | K15: =VLOOKUP(A15,CORTE!$A$2:$B$1045,2,0) | L15: APERTURA
A16: 8651 | B16: PEREZ E-GARCIA FORNASERO MARINA | C16: SA | D16: PRESENCIAL | E16: 09:00-12:00 | F16: BAJO | G16: ESCRITO | H16: NO | I16: NO | J16: Parciales a desarrollar. Pro alumno. los parciales son escritos a desarrollar. Se usa un manual de la catedra. No toma lista. No hay tp. | K16: =VLOOKUP(A16,CORTE!$A$2:$B$1045,2,0)
A17: 8652 | B17: DI PELINO-BARREÑA M. | C17: MA-VI | D17: PRESENCIAL | E17: 11:30-13:00 | F17: ALTO | G17: MIXTO | H17: SI | I17: SI | J17: Los parciales pueden tener muchos cálculos y gráficos así que se pueden complicar si no llevas bien las matemáticas. Así explican bien las cosas, no tiene problema en contestar preguntas ni ánimos de bochar a nadie | K17: =VLOOKUP(A17,CORTE!$A$2:$B$1045,2,0)
A18: 8626 | B18: MAZZA-MAZZA | C18: LU-JU | D18: PRESENCIAL | E18: 11:30-13:00 | F18: MEDIO | G18: ORAL | H18: NO | I18: NO | J18: Hace la materia súper llevadera, no tiene ánimos de bochar a nadie. Los parciales escritos se dividen en dos partes, 5 preguntas múltiples choice y 2 preguntas para desarrollar.Los parciales son orales se dividen en dos grupos, uno por docente, eligen un tema y desarrollan en base a ese tema que eligieron. Es un oral re tranquilo. | K18: =VLOOKUP(A18,CORTE!$A$2:$B$1045,2,0) | L18: APERTURA
A19: 8631 | B19: STORDEUR-IANELLO | C19: MA-VI | D19: VIRTUAL | E19: 11:30-13:00 | F19: BAJO | G19: ESCRITO | H19: NO | I19: NO | J19: La hace muy llevadera, las clases las da iannello, tiene varios ayudantes. Explica con gráfica pero toma cosas conceptuales. | K19: =VLOOKUP(A19,CORTE!$A$2:$B$1045,2,0) -> 7,06 | L19: TECNICA
A20: 8614 | B20: STORDEUR-ZUNINO | C20: MA-VI | D20: PRESENCIAL | E20: 11:30-13:00 | F20: ALTO | G20: MIXTO | H20: SI | I20: NO | J20: El docente no permite que el alumnado pregunte,se cursa con el manual de la catedra, el parcial es súper rebuscado. Cambia la modalidad de los parciales. | K20: =VLOOKUP(A20,CORTE!$A$2:$B$1045,2,0)
A21: 8633 | B21: ARGENTO-ARGENTO A. | C21: LU-JU | D21: PRESENCIAL | E21: 14:00-15:30 | F21: ALTO | G21: ESCRITO | H21: NO | I21: SI | J21: Buen nivel de aprobados. // Comisión desorganizada, los profesores llegan tarde incluso en los parciales. Puede ser impredecible en la forma de evaluación, se va por las ramas en las clases explicando temas que no tienen mucho que ver con el temario | K21: =VLOOKUP(A21,CORTE!$A$2:$B$1045,2,0)
A22: 8624 | B22: MAZZA-HOFMANN | C22: LU-JU | D22: PRESENCIAL | E22: 14:00-15:30 | F22: BAJO | G22: ESCRITO | H22: SI | I22: NO | J22: Manda textos vía campus (son los mismos todos los cuatris, no llega a las 20 hojas), hace un grupo de wsp para aclarar dudas o mandar mensaje cuando sube los textos. Los parciales no son complicados si lees con anticipación, una semana antes no manda textos así podemos estudiar. Pone notas de todo tipo (casi nada de desaprobados, el que desaprueba es porque no lee) los parciales son V/F con justificación. La justificación, cuánto más parecida esté al texto, mejor. | K22: =VLOOKUP(A22,CORTE!$A$2:$B$1045,2,0) | L22: TECNICA
A23: 8653 | B23: PEREZ E-DOMINGUEZ G. | C23: MA-VI | D23: PRESENCIAL | E23: 14:00-15:30 | F23: MEDIO | G23: MIXTO | H23: NO | I23: SI | J23: Súper recomendable, te dan clases sin falta en horario de cursada. La profesora es súper atenta, responde todas las dudas y repite sin problemas. Se dividen en clases teóricas que da la profe y prácticas donde trabajan la profesora con Dani que es el ayudante alumno explicando cada tema. Están atentos a cada consulta siempre sin problemas. La bibliografía la da la profesora y se manejan con un campus de Citep. La modalidad de evaluación son 2 parciales, una parte teórica y otra práctica, no preguntan nada que no se haya visto en clase. También hay 2 tps grupales que son un porcentaje de la nota de parcial, si lo haces te suma puntos pero si no lo haces no resta. Se aprende mucho. | K23: =VLOOKUP(A23,CORTE!$A$2:$B$1045,2,0)
A24: 8643 | B24: DI PELINO-MAC DONALD | C24: MA-VI | D24: PRESENCIAL | E24: 15:30-17:00 | F24: MEDIO | G24: MIXTO | I24: NO | J24: La profe Andrea es muy buena. Explica las veces que necesites, tiene su propio libro y ahí está toda la información necesaria. Si lees antes de clase lo valora porque le gusta que participen en clase. Tomo 1 parcial escrito y el segundo oral. Da guía de preguntas para cada parcial | K24: =VLOOKUP(A24,CORTE!$A$2:$B$1045,2,0)
A25: 8654 | B25: PEREZ E-BALDINO MAYER | C25: LU-JU | D25: PRESENCIAL | E25: 15:30-17:00 | F25: MEDIO | G25: MULTIPLECHOICE | H25: SI | I25: NO | J25: Las clases se podían complicar por las explicaciones enroyadas de los profesores y los exámenes (2 multiplechoice) eran demasiado exigentes ya que había más de una opción correcta pero si marcabas una que no iba restaban todo el punto | K25: =VLOOKUP(A25,CORTE!$A$2:$B$1045,2,0)
A26: 8615 | B26: STORDEUR-GARCES | C26: LU-JU | D26: VIRTUAL | E26: 15:30-17:00 | F26: MEDIO | G26: MULTIPLECHOICE | I26: SI | J26: Super recomendada, el docente es muy claro explicando, no tiene problema en responder dudas ni en debatir ciertos temas si alguien quiere hacerlo, tiene un drive donde está en pdf todo el material necesario para la cursada. Ambos parciales son virtuales, múltiple choice en formularios de google, aproximadamente 85 consignas, da bastantes horas para hacerlo (4/5) y si bien llevan tiempo, son bastante sencillos porque se basan en lo dado en clase y en el material de lectura. A veces manda trabajos prácticos no obligatorios y las preguntas que hace ahí después están en el parcial. Todos los que cursamos logramos promocionar, nos dijo que no le gustaba mandar a nadie a final, que si a alguien no le daba el promedio podíamos ver como hacíamos. | K26: =VLOOKUP(A26,CORTE!$A$2:$B$1045,2,0)
A27: 8630 | B27: ARGENTO-ARGENTO A. | C27: LU-JU | D27: PRESENCIAL | E27: 17:00-18:30 | F27: ALTO | G27: ESCRITO | H27: NO | I27: NO | J27: Buen nivel de aprobados. | K27: =VLOOKUP(A27,CORTE!$A$2:$B$1045,2,0)
A28: 8655 | B28: PEREZ E-A DESIGNAR | C28: LU-JU | D28: PRESENCIAL | E28: 17:00-18:30 | F28: BAJO | G28: MULTIPLECHOICE | H28: NO | I28: NO | J28: Solo son dos parciales a desarrollar (notas pro alumno) con bibliografia aportada por el profesor llamada "nota de clase" (manual a eleccion). Puede terminar las clases antesdehorario y antes de la fecha del cuatrimestre. | K28: =VLOOKUP(A28,CORTE!$A$2:$B$1045,2,0)
A29: 8600 | B29: A DESIGNAR-G.NIEVES | C29: MA-VI | D29: PRESENCIAL | E29: 18:30-20:00 | F29: MEDIO | G29: MULTIPLECHOICE | H29: NO | I29: NO | J29: Es presencial y toman parciales verdadero o falso. | K29: =VLOOKUP(A29,CORTE!$A$2:$B$1045,2,0)
A30: 8644 | B30: DI PELINO-DI PELINO | C30: MA-VI | D30: PRESENCIAL | E30: 17:00-18:30 | K30: =VLOOKUP(A30,CORTE!$A$2:$B$1045,2,0)
A31: 8635 | B31: STORDEUR-IANELLO | C31: MA-VI | D31: PRESENCIAL | E31: 18:30-20:00 | F31: MEDIO | G31: ESCRITO | H31: NO | I31: NO | J31: Son 2 parciales presenciales multiple choice y dos preguntas a desarrollar cortas. Se promociona con 6. Los recuperatorios son multiple choice también. El profesor explica bien y envía los libros que se usan en la cursada. | K31: =VLOOKUP(A31,CORTE!$A$2:$B$1045,2,0)
A32: 8616 | B32: STORDEUR-REY LUIS | C32: LU-JU | D32: PRESENCIAL | E32: 18:30-20:00 | J32: IMPORTANTE: En el primer cuatrimestre esta comisión no fue abierta por no llegar al mínimo de inscriptos que exige la Facultad.
A33: 8656 | B33: PEREZ E-GARCIA FORNASERO MARINA | C33: MI | D33: PRESENCIAL | E33: 18:30-21:30 | K33: =VLOOKUP(A33,CORTE!$A$2:$B$1045,2,0)
A34: 8601 | B34: A DESIGNAR-G.NIEVES | C34: MA-VI | D34: PRESENCIAL | E34: 20:00-21:30 | F34: BAJO | G34: MULTIPLECHOICE | H34: NO | I34: NO | J34: Parciales múltiple-choice. Toma dos parciales v o f. Cátedra aprobable. Nivel alto de aprobados. | K34: =VLOOKUP(A34,CORTE!$A$2:$B$1045,2,0)
A35: 8636 | B35: ARGENTO-GONZALEZ RODRIGUEZ | C35: LU-JU | D35: PRESENCIAL | E35: 08:30-10:00 | F35: MEDIO | G35: ESCRITO | H35: SI | I35: NO | J35: Las clases son dinámicas, mandan los parciales por Forms que se pueden hacer desde casa estudiando lo visto en clases. Para estudiar mandan textos cortos +lo visto | K35: =VLOOKUP(A35,CORTE!$A$2:$B$1045,2,0)
A36: 8617 | B36: STORDEUR-ZAMORANO | C36: LU-JU | D36: PRESENCIAL | E36: 18:30-2O:00 | F36: MEDIO | G36: MIXTO | H36: SI | I36: NO | J36: El profesor Cesar Villena la hace muy llevadera y es muy claro explicando conceptos. Bastante material de lectura, se toma lo que se da en clase. El primer parcial fue escrito y el segundo oral. | K36: =VLOOKUP(A36,CORTE!$A$2:$B$1045,2,0)
A37: 8640 | B37: DI PELINO-TESELMAN | C37: LU-JU | D37: PRESENCIAL | E37: 20:00-21:30 | J37: Comisión nueva.
A38: 8657 | B38: PEREZ E-BALDINO MAYER | C38: LU-JU | D38: PRESENCIAL | E38: 21:30-23:00 | F38: MEDIO | G38: MIXTO | H38: SI | I38: NO | J38: Los profes son copados y explican bien! Sin ánimos de bochar toman dos parciales uno multiplechoice y uno oral dependiendo la cantidad de estudiantes. Se aprueba estudiando lo de las clases ya que son bastante completas y toman lo visto en ellas | K38: =VLOOKUP(A38,CORTE!$A$2:$B$1045,2,0)
A39: 8637 | B39: STORDEUR-DONNA | C39: LU-JU | D39: PRESENCIAL | E39: 21:30-23:00 | K39: =VLOOKUP(A39,CORTE!$A$2:$B$1045,2,0)

Sheet CONSTITUCIONAL 
A1: 📚 CONSTITUCIONAL - 2º CUATRI 2026 - LA CÁMPORA 📚
A3: N° | B3: COMISIÓN | C3: DÍAS | D3: MODALIDAD | E3: HORARIO | F3: NIVEL | G3: PARCIAL | H3: TOMA LISTA | I3: TOMA TPS | J3: COMENTARIO | K3: CORTE 1° CUATRI | L3: POSTURA
A4: 6600 | B4: BASTERRA-CAO C. | C4: LU-JU | D4: PRESENCIAL | E4: 07:00-08:30 | F4: ALTO | G4: ESCRITO | I4: SI | J4: Cátedra exigente, para aprender. Dan muchos fallos, y la bibliografía es libre pero siguen a Bidart Campos. La profesora tiene buena predisposición y aclara todas las dudas. Se puede promocionar, pero no es de poner notas altas. Dos parciales escritos largos, con preguntas a desarrollar y un verdadero o falso a justificar. Mandan uno o dos tps antes de cada parcial que no se entregan, pero si se responden oralmente en la clase. Recuperatorios escritos y final oral. | K4: =VLOOKUP(A4,CORTE!$A$2:$B$1045,2,0)
A5: 6688 | B5: SABSAY-TABOADA F. | C5: MI | D5: PRESENCIAL | E5: 7:00-10:00 | J5: Comisión nueva
A6: 6601 | B6: BASTERRA-CAO C. | C6: MA-VI | D6: PRESENCIAL | E6: 08:30-10:00 | F6: ALTO | G6: ESCRITO | I6: NO | J6: 2 parciales escritos de 3 preguntas a desarrollar. Son escritos con varios puntos a desarrollar algunos y otros multiple choice y verdadero falso y con mencion a algunos fallos importantes vistos en clase. Es muy exigente pero se puede promocionar. Se aprende mucho | K6: =VLOOKUP(A6,CORTE!$A$2:$B$1045,2,0) -> 6,16
A7: 6611 | B7: BASTERRA-LOZADA | C7: MA-VI | D7: PRESENCIAL | E7: 08:30-10:00 | F7: ALTO | G7: MULTIPLECHOICE | J7: Muy recomendada. Es muy exigente | K7: =VLOOKUP(A7,CORTE!$A$2:$B$1045,2,0)
A8: 6630 | B8: CLERICO-GIACCONE | C8: MA-VI | D8: VIRTUAL | E8: 08:30-10:00 | J8: Cátedra muy recomendada. Comisión nueva | L8: APERTURA
A9: 6640 | B9: DALLA VIA-ARAYA L. | C9: LU-JU | D9: PRESENCIAL | E9: 08:30-10:00 | F9: ALTO | G9: MIXTO | I9: SI | J9: Los parciales son difíciles. Son MC y no dan el puntaje parcial (en todas hay más de una correcta y si no marcas todas no cuentan el punto) toman. En las preguntas a desarrollar piden doctrina y jurisprudencia que muchas veces no se ve en clase. Dan un TP de dos instancias: una donde lo haces y lo revisa; y otra para que lo corrijas para la entrega (NUNCA DIO LA NOTA DEL TP) | K9: =VLOOKUP(A9,CORTE!$A$2:$B$1045,2,0)
A10: 6670 | B10: SABSAY-GORBAK E. | C10: LU-JU | D10: VIRTUAL | E10: 08:30-10:00 | F10: MEDIO | G10: ORAL | I10: SI | J10: El profesor Adriel Schein es excelente. Toma 3 parciales todos orales y 2 tp. Los parciales son presenciales. Exelente profesor explica muy bien, sin ánimos de bochar. Usan el manual de Sabsay y mandan el material por el campus salvo algún fallo que haya que buscar. | K10: =VLOOKUP(A10,CORTE!$A$2:$B$1045,2,0)
A11: 6680 | B11: SOLA-USLENGHI | C11: LU-JU | D11: PRESENCIAL | E11: 08:30-10:00 | J11: Comisión nueva | K11: =VLOOKUP(A11,CORTE!$A$2:$B$1045,2,0)
A12: 6671 | B12: SABSAY-PEREZ ANDREA | C12: MI | D12: PRESENCIAL | E12: 08:30-11:30 | F12: ALTO | G12: MIXTO | H12: SI | I12: SI | J12: Buena cátedra, se aprende y es llevadera. Mandan tps semanales pero cortos. El primer parcial es escrito V o F y desarrollar, bastante largo el parcial para hacer en las 3 horas. El segundo parcial es escrito pero dan la posibilidad de darlo oral. Muy recomendable. Hay que leer todos los textos sí o sí. | K12: =VLOOKUP(A12,CORTE!$A$2:$B$1045,2,0)
A13: 6641 | B13: DALLA VIA-ARAYA L. | C13: LU-JU | D13: PRESENCIAL | E13: 10:00-11:30 | F13: MEDIO | G13: ESCRITO | I13: SI | J13: Recomendable. Dos parciales a desarrollar. Hay un tp en grupo. | K13: =VLOOKUP(A13,CORTE!$A$2:$B$1045,2,0)
A14: 6642 | B14: DALLA VIA-DJEDJEIAN | C14: MA-VI | D14: PRESENCIAL | E14: 10:00-11:30 | F14: ALTO | G14: ESCRITO | H14: SI | I14: NO | J14: Los docentes son muy exigentes. Suelen desaprobar a la mayoría en el primer parcial y los que quedan aprueban. Dos parciales escritos a desarrollar | K14: =VLOOKUP(A14,CORTE!$A$2:$B$1045,2,0) | L14: TECNICA
A15: 6660 | B15: GARGARELLA-BOUZAT | C15: LU-JU | D15: PRESENCIAL | E15: 10:00-11:30 | F15: ALTO | G15: MIXTO | H15: SI | I15: NO | J15: Cátedra MUY exigente, difícil de aprobar. Los profesores explican bien pero los parciales son casi imposibles y dan muchísimo material. El primer parcial es oral y el segundo escrito | K15: =VLOOKUP(A15,CORTE!$A$2:$B$1045,2,0) | L15: CONSERVADORA
A16: 6661 | B16: GARGARELLA-BOUZAT | C16: MA-VI | D16: PRESENCIAL | E16: 10:00-11:30 | F16: ALTO | G16: MIXTO | H16: SI | I16: NO | J16: Cátedra MUY exigente, difícil de aprobar. Los profesores explican bien pero los parciales son casi imposibles y dan muchísimo material. El primer parcial es oral y el segundo escrito | K16: =VLOOKUP(A16,CORTE!$A$2:$B$1045,2,0) | L16: CONSERVADORA
A17: 6615 | B17: MANILI-LAPLACETTE CARLOS | C17: MA-VI | D17: PRESENCIAL | E17: 10:00-11:30 | F17: MEDIO | G17: ESCRITO | I17: NO | J17: Los profesores y ayudantes son super claros,responden dudas.Super pro alumno, son dos parciales con preguntas sencillas. Promocionable | K17: =VLOOKUP(A17,CORTE!$A$2:$B$1045,2,0) -> 5,11
A18: 6672 | B18: SABSAY-GORBAK E. | C18: LU-JU | D18: VIRTUAL | E18: 10:00-11:30 | F18: ALTO | G18: ORAL | H18: SI | I18: SI | J18: Cátedra desorganizada. Los trabajos prácticos son fichas sobre los fallos y uno al final de la cursada. Hay que leer mucho. La profesora es muy buena, no tiene problemas en aclarar dudas pero es muy exigente. El material de estudio es la Constitución comentada, fallos y textos. Toman tres parciales orales pesados por meet. A veces toman parcial en días que no corresponden con la cursada. Aunque en el tercer parcial a veces hacen que elijan un tema y hagan una defensa oral. | K18: =VLOOKUP(A18,CORTE!$A$2:$B$1045,2,0)
A19: 6631 | B19: BASTERRA-GONZALEZ T. | C19: MI | D19: PRESENCIAL | E19: 10:00-13:00 | F19: ALTO | G19: MULTIPLECHOICE | H19: NO | I19: SI | J19: Buena cátedra. Las clases son muy buenas, y es importante asistir para poder llevarla al día. Es desorganizada y dan mucho material para leer. Son dos parciales choice (V o F) con justificación y alguna pregunta a desarrollar. Es exigente pero se aprende mucho. Generalmente en el primer parcial ponen notas bajas, pero en el segundo todos levantan y la mayoria promociona. | K19: =VLOOKUP(A19,CORTE!$A$2:$B$1045,2,0) | L19: APERTURA
A20: 6663 | B20: GARGARELLA-ELFMAN | C20: MI | D20: PRESENCIAL | E20: 10:00-13:00 | F20: ALTO | G20: ESCRITO | H20: SI | I20: NO | J20: Da clase las 3 horas y toma lista al final. 2 parciales escritos con preguntás a desarrollar y mutiple choice. Da fallos todas las clases. Es muy exigente, dan mucho material para leer y lo evalúan. | K20: =VLOOKUP(A20,CORTE!$A$2:$B$1045,2,0) | L20: APERTURA
A21: 6662 | B21: GARGARELLA-TAUBER S. | C21: MI | D21: PRESENCIAL | E21: 10:00-13:00 | F21: ALTO | H21: SI | I21: SI | J21: Hay opiniones encontradas. Es exigente pero se aprende mucho ,mandan un tp por clase para integrar el contenido de clase y para regularidad. los parciales son domiciliarios y los tps ayudan mucho a la confeccion del parcial. | K21: =VLOOKUP(A21,CORTE!$A$2:$B$1045,2,0) -> 6,21 | L21: APERTURA
A22: 6681 | B22: SOLA-FORONDA ANA | C22: MA-VI | D22: PRESENCIAL | E22: 11:30-13:00 | F22: ALTO | G22: MIXTO | H22: SI | I22: SI | J22: Evalúan con un tp en grupo y defensa oral (esas son 2 notas) y un choice por google. | K22: =VLOOKUP(A22,CORTE!$A$2:$B$1045,2,0)
A23: 6610 | B23: BASTERRA-LONIGRO | C23: LU-JU | D23: PRESENCIAL | E23: 14:00-15:30 | F23: ALTO | G23: ESCRITO | J23: Muy exigente, si bien el profesor da buenas clases no es fácil aprobar. Se toma el manual de Lonigro prácticamente de memoria | K23: =VLOOKUP(A23,CORTE!$A$2:$B$1045,2,0)
A24: 6607 | B24: MANILI-CORCUERA SANTIAGO | C24: MA-VI | D24: PRESENCIAL | E24: 14:00-15:30 | F24: ALTO | G24: ESCRITO | H24: NO | I24: NO | J24: Se sigue un cronograma super preciso que va acorde al manual del titular de la cátedra. Se incita la participación de los alumnos en las clases y no tienen problemas en reexplicar conceptos. Son 4/5 preguntas por parcial y los recuperatorios son orales. Es recomendable prestar atención a la explicación de fallos porque suma hablar de ellos en las respuestas de los parciales. | K24: =VLOOKUP(A24,CORTE!$A$2:$B$1045,2,0) | L24: TECNICA
A25: 6632 | B25: CLERICO-SCIOSCIOLI S. | C25: LU-JU | D25: VIRTUAL | E25: 15:30-17:00 | J25: Muy buena cátedra. Comisión nueva | K25: =VLOOKUP(A25,CORTE!$A$2:$B$1045,2,0) | L25: APERTURA
A26: 6602 | B26: BASTERRA-BERRA ELIZABETH | C26: LU-JU | D26: PRESENCIAL | E26: 15:30-17:00 | F26: MEDIO | G26: MIXTO | J26: Muy recomendada. Buen equipo docente. Evalúan con google forms algunas preguntas v/f con justificación y otras a desarrollar sobre los fallos vistos en clase. El recuperatorio es de la misma modalidad pero el final es oral | K26: =VLOOKUP(A26,CORTE!$A$2:$B$1045,2,0) -> 1
A27: 6603 | B27: BASTERRA-BERRA ELIZABETH | C27: LU-JU | D27: VIRTUAL | E27: 15:30-17:00 | F27: MEDIO | G27: MIXTO | J27: Muy recomendada. Buen equipo docente. Evalúan con google forms algunas preguntas v/f con justificación y otras a desarrollar sobre los fallos vistos en clase. El recuperatorio es de la misma modalidad pero el final es oral | K27: =VLOOKUP(A27,CORTE!$A$2:$B$1045,2,0) -> 7,31
A28: 6658 | B28: FERREYRA - LAUHIRAT | C28: LU-JU | D28: PRESENCIAL | E28: 15:30-17:00 | J28: Comisión nueva
A29: 6643 | B29: DALLA VIA-DJEDJEIAN | C29: MA-VI | D29: VIRTUAL | E29: 15:30-17:00 | F29: ALTO | G29: ORAL | H29: SI | I29: NO | J29: 2 parciales orales presenciales de lo visto en clase. Recomendada | K29: =VLOOKUP(A29,CORTE!$A$2:$B$1045,2,0) | L29: TECNICA
A30: 6673 | B30: SABSAY-VENTURA A. | C30: MA-VI | D30: PRESENCIAL | E30: 15:30-17:00 | F30: ALTO | G30: ESCRITO | H30: SI | J30: Muchos no la recomiendan, porque son exigentes. Para mi explican todo en base al cronograma, organizado, son muy claros. | K30: =VLOOKUP(A30,CORTE!$A$2:$B$1045,2,0)
A31: 6652 | B31: FERREYRA-BALBIN F. | C31: MI | D31: PRESENCIAL | E31: 15:30-18:30 | F31: MEDIO | G31: MULTIPLECHOICE | J31: Toma lo dado en clase. 2 parciales múltiple choice y con VoF a desarrollar. Pro alumno y muy promocionable. | K31: =VLOOKUP(A31,CORTE!$A$2:$B$1045,2,0)
A32: 6635 | B32: CLERICO-CLERICO | C32: MI | D32: PRESENCIAL | E32: 15:30-18:30 | J32: Cátedra muy recomendada. Comisión nueva | K32: =VLOOKUP(A32,CORTE!$A$2:$B$1045,2,0) | L32: APERTURA
A33: 6690 | B33: MANILI-RISSO | C33: LU-JU | D33: PRESENCIAL | E33: 15:30-17:00 | J33: Comisión nueva
A34: 6636 | B34: CLERICO-SCIOSCIOLI S. | C34: LU-JU | D34: VIRTUAL | E34: 17:00-18:30 | F34: ALTO | G34: MIXTO | H34: SI | I34: SI | J34: Cátedra muy recomendada. El profesor explica muy bien pero es exigente. Evalúan con dos parciales parte escrita y parte choice, un verdadero o falso y una parte a desarrollar. Eso en base a fallos que se trabajan en clase, toman dos trabajos prácticos en grupo para nada dificiles. | K34: =VLOOKUP(A34,CORTE!$A$2:$B$1045,2,0) | L34: APERTURA
A35: 6633 | B35: CLERICO-GONZALEZ | C35: MA-VI | D35: PRESENCIAL | E35: 17:00-18:30 | F35: MEDIO | G35: ESCRITO | J35: Muy buena catedra, aprendes un monton. Se trabaja con fallos y tienen una perspectiva amplia de la CN en conjunto con los tratados de DDHH .Pro alumno, cero animo de bochar, no toman asistencia pero suma ir a las clases. Toman 2 parciales escritos (final generalmente oral) | K35: =VLOOKUP(A35,CORTE!$A$2:$B$1045,2,0) | L35: APERTURA
A36: 6654 | B36: FERREYRA-CAMPORA M. | C36: MA-VI | D36: PRESENCIAL | E36: 17:00-18:30 | F36: MEDIO | G36: ESCRITO | H36: SI | I36: SI | J36: Muy recomendada. Buenas clases, hay que estudiar pero se puede promocionar. El profesor valora la participación en clase y lo toma en cuenta para el promedio | K36: =VLOOKUP(A36,CORTE!$A$2:$B$1045,2,0) | L36: APERTURA
A37: 6653 | B37: FERREYRA-PERICOLA A. | C37: LU-JU | D37: PRESENCIAL | E37: 17:00-18:30 | F37: MEDIO | G37: ESCRITO | H37: SI | J37: Recomendada. Los profesores son muy buenos. Los parciales son preguntas a desarrollar, toman lo que dan en clase. | K37: =VLOOKUP(A37,CORTE!$A$2:$B$1045,2,0)
A38: 6655 | B38: GARGARELLA-SAENZ JUAN | C38: LU-JU | D38: PRESENCIAL | E38: 17:00-18:30 | F38: ALTO | G38: ESCRITO | J38: Cátedra muy buena y exigente. Mandan mucho material para leer y explican los textos en las clases (importante no faltar). Los parciales son dificiles, toman preguntas a desarrollar y casos prácticos donde se busca que se razone más allá de repetir lo que dice la bibliografía. | K38: =VLOOKUP(A38,CORTE!$A$2:$B$1045,2,0)
A39: 6608 | B39: MANILI- LISZCZYNSKI M | C39: LU-JU | D39: PRESENCIAL | E39: 17:00-18:30 | F39: MEDIO | G39: ESCRITO | I39: SI | J39: No recomendable. Los profesores no tienen buena llegada con los alumnos. Evalúan con dos parciales a desarrollar y dos tps para mantener la regularidad.
A40: 6612 | B40: MANILI-MARANIELLO | C40: MA-VI | D40: PRESENCIAL | E40: 17:00-18:30 | F40: MEDIO | G40: ESCRITO | H40: SI | I40: NO | J40: La calidad de los profesores es muy buena. Toman asistencia, no hay tps. Los parciales eran escritos 3 preguntas choice y 3 preguntas a desarrollar cortas. Muy buena cátedra | K40: =VLOOKUP(A40,CORTE!$A$2:$B$1045,2,0) -> 6,36
A41: 6613 | B41: MANILI-MORA ANGELA | C41: MA-VI | D41: VIRTUAL | E41: 17:00-18:30 | F41: MEDIO | G41: MIXTO | J41: La profesora es muy buena y su objetivo es aprobar al alumno, además de que aprenda. Los exámenes son MC con una pregunta a desarrollar, pero super accesibles. | K41: =VLOOKUP(A41,CORTE!$A$2:$B$1045,2,0)
A42: 6682 | B42: SOLA-LAZZARO | C42: LU-JU | D42: VIRTUAL | E42: 17:00-18:30 | F42: ALTO | G42: ESCRITO | H42: SI | J42: Son muy exigentes. Explican todo en base al cronograma, son organizados y muy claros. | K42: =VLOOKUP(A42,CORTE!$A$2:$B$1045,2,0)
A43: 6683 | B43: SOLA-VIVO GUSTAVO | C43: LU-JU | D43: PRESENCIAL | E43: 17:00-18:30 | F43: MEDIO | G43: MIXTO | H43: NO | I43: NO | J43: Primer parcial escrito y el segundo oral. No hay TP. Mandan material para estudiar y te responden siempre consultas por chat o por mail. Muy recomendable | K43: =VLOOKUP(A43,CORTE!$A$2:$B$1045,2,0)
A44: 6634 | B44: CLERICO-LARA C. W. | C44: MIE | D44: PRESENCIAL | E44: 17:00-20:00 | J44: Muy buena cátedra. Comisión nueva | K44: =VLOOKUP(A44,CORTE!$A$2:$B$1045,2,0) | L44: APERTURA
A45: 6616 | B45: BASTERRA-LOZADA | C45: MA-VI | D45: PRESENCIAL | E45: 18:30-20:00 | F45: ALTO | G45: MULTIPLECHOICE | J45: 2 parciales MC (las malas restan). Recomendada | K45: =VLOOKUP(A45,CORTE!$A$2:$B$1045,2,0)
A46: 6689 | B46: DALLA VIA-SPOTA | C46: LU-JU | D46: PRESENCIAL | E46: 18:30-20:00 | F46: ALTO | G46: ESCRITO | I46: NO | J46: Cátedra exigente y desorganizada. Toman 2 parciales escritos. Los profesores son buenos pero la cursada es muy desorganizada. | K46: =VLOOKUP(A46,CORTE!$A$2:$B$1045,2,0)
A47: 6651 | B47: FERREYRA-MARTINEZ L. | C47: LU-JU | D47: PRESENCIAL | E47: 18:30-20:00 | F47: ALTO | G47: ESCRITO | J47: No recomendada. Son muy exigentes y las clases no son claras. 2 parciales con MC y preguntas a desarrollar. | K47: =VLOOKUP(A47,CORTE!$A$2:$B$1045,2,0)
A48: 6656 | B48: FERREYRA-SZLAJEN | C48: MA-VI | D48: PRESENCIAL | E48: 18:30-20:00 | F48: MEDIO | G48: ESCRITO | J48: La modalidad de examen es a libro abierto. El final es oral. El trato de los profesores y ayudantes es muy bueno y explican bien. | K48: =VLOOKUP(A48,CORTE!$A$2:$B$1045,2,0)
A49: 6664 | B49: GARGARELLA-JAUREGUIBERRY INES | C49: LJ | D49: PRESENCIAL | E49: 18:30-20:00 | F49: MEDIO | G49: ESCRITO | H49: SI | I49: SI | J49: Toman lista con una hoja en clase, los tps que mandan son para la regularidad y suelen ser sobre un tema de la semana siguiente a libre elección, dos parciales a libro cerrado. | K49: =VLOOKUP(A49,CORTE!$A$2:$B$1045,2,0)
A50: 6605 | B50: MANILI-BERGALLO OSCAR | C50: MA-VI | D50: PRESENCIAL | E50: 18:30-20:00 | F50: MEDIO | G50: ESCRITO | H50: SI | I50: NO | J50: Las clases son muy poco dinámicas. Toma lista mucho antes de arrancar la clase. Los parciales son 4 preguntas a desarrollar. Se usa el manual de Manili, se toma lo dado en clase. No toma fallos, solo para citar jurisprudencia en los parciales. | K50: =VLOOKUP(A50,CORTE!$A$2:$B$1045,2,0) | L50: CONSERVADORA
A51: 6606 | B51: MANILI-FERNANDEZ | C51: MA-VI | D51: PRESENCIAL | E51: 18:30-20:00 | J51: Comisión no abierta en el 1° cuatrimestre 2025. La Facultad exige un mínimo de 8 inscriptos para la apertura de la comisión y la consecuente asignación de aula.
A52: 6609 | B52: MANILI-MARANIELLO | C52: MA-VI | D52: PRESENCIAL | E52: 18:30-20:00 | F52: MEDIO | G52: MIXTO | H52: SI | I52: NO | J52: Toman lista cada tanto, no mandan trabajos prácticos. Los parciales son MC y a desarrollar; mandan power-points. No tienen ánimos de bochar, responden dudas sin problemas | K52: =VLOOKUP(A52,CORTE!$A$2:$B$1045,2,0)
A53: 6675 | B53: SABSAY-PIZZOLO | C53: MA-VI | D53: PRESENCIAL | E53: 18:30-20:00 | F53: ALTO | G53: ESCRITO | I53: NO | J53: Cátedra recomendada y exigente. Se leen muchos fallos, que hay que llevar leídos a las clases. Los profesores mandan todo el material, los docentes y ayudantes tienen buena llegada y predisposición. Evalúan con dos parciales escrito | K53: =VLOOKUP(A53,CORTE!$A$2:$B$1045,2,0)
A54: 6684 | B54: SOLA-VIVO GUSTAVO | C54: LU-JU | D54: PRESENCIAL | E54: 18:30-20:00 | F54: MEDIO | G54: MIXTO | H54: NO | I54: NO | J54: Primer parcial MC y el segundo oral. No hay TP. Mandan material para estudiar y te responden siempre consultas por chat o por mail. Muy recomendable | K54: =VLOOKUP(A54,CORTE!$A$2:$B$1045,2,0)
A55: 6614 | B55: BASTERRA-ADAGLIO | C55: MI | D55: PRESENCIAL | E55: 18:30-21:30 | F55: ALTO | G55: MIXTO | J55: Hay comentarios que no la recomiendan, las clases no son fructiferas, los parciales son desordenados y la decisiones son volatiles para evaluar | K55: =VLOOKUP(A55,CORTE!$A$2:$B$1045,2,0) | L55: TECNICA
A56: 6644 | B56: DALLA VIA-LUGONES ALBERTO | C56: LU-JU | D56: VIRTUAL | E56: 20:00-21:30 | F56: MEDIO | G56: ESCRITO | H56: SI | J56: Los parciales son escritos y se dan de forma presencial | K56: =VLOOKUP(A56,CORTE!$A$2:$B$1045,2,0) -> 7,11
A57: 6657 | B57: FERREYRA-KENNEDY | C57: MA-VI | D57: PRESENCIAL | E57: 20:00-21:30 | F57: MEDIO | G57: ESCRITO | J57: Super recomendable. Los parciales son escritos, a libro abierto (podes tener todos los apuntes, constitucion, resumenes,etc). Toma lo visto en clase. Aprobable | K57: =VLOOKUP(A57,CORTE!$A$2:$B$1045,2,0)
A58: 6685 | B58: SOLA-MACIAS | C58: LU-JU | D58: PRESENCIAL | E58: 20:00-21:30 | F58: MEDIO | G58: ESCRITO | H58: SI | I58: NO | J58: 2 parciales con preguntas a desarrollar (aproximadamente 5). Dan muchos fallos. Mandan guías de preguntas antes de los parciales para prácticar. Responden dudas, toman lista cada tanto | K58: =VLOOKUP(A58,CORTE!$A$2:$B$1045,2,0)
A59: 6686 | B59: SOLA-MACIAS | C59: LU-JU | D59: PRESENCIAL | E59: 21:30-23:00 | F59: MEDIO | G59: ESCRITO | H59: SI | I59: NO | J59: 2 parciales con preguntas a desarrollar (aproximadamente 5). Dan muchos fallos. Mandan guías de preguntas antes de los parciales para prácticar. Responden dudas, toman lista cada tanto | K59: =VLOOKUP(A59,CORTE!$A$2:$B$1045,2,0)
A60: 6687 | B60: SOLA-USLENGHI | C60: MA-VI | D60: PRESENCIAL | E60: 21:30-23:00 | J60: Comisión nueva | K60: =VLOOKUP(A60,CORTE!$A$2:$B$1045,2,0)

Sheet OBLIGACIONES 
A1: 📚 OBLIGACIONES CIVILES Y COMERCIALES - 2º CUATRI 2026 - LA CÁMPORA 📚
A2: N° | B2: COMISIÓN | C2: DÍAS | D2: MODALIDAD | E2: HORARIO | F2: NIVEL | G2: PARCIAL | H2: TOMA LISTA | I2: TOMA TPS | J2: COMENTARIO | K2: CORTE 1° CUATRI | L2: POSTURA
A3: 7070 | B3: WIERZBA-RUA | C3: MA-VI | D3: PRESENCIAL | E3: 07:00-08:30 | F3: MEDIO | G3: MIXTO | H3: SI | I3: SI | J3: Muy recomedada, las clases las da Isabel Rúa y los ayudantes. Son dos parciales el primero escrito mitad múltiple choice y dos casos prácticos; el segundo es oral son tres o cuatro preguntas. Son pro alumno, cero ánimos de bochar. | K3: =VLOOKUP(A3,CORTE!$A$2:$B$1045,2,0) | L3: APERTURA
A4: 7040 | B4: VERGARA-KOTT CARLA | C4: MI | D4: PRESENCIAL | E4: 07:00-10:00 | F4: BAJO | G4: MIXTO | H4: SI | I4: NO | J4: Los profes no siguen el programa y puede tornarse desorganizada la cursada, faltando varios temas de obligaciones que en otras comisiones sí se ven y mejor. Toman 3 parciales (2 escritos y 1 oral): para llegar al tercero tenés que haber promocionado los otros dos, si no tenés un final en lugar del parcial de los últimos temas. Son desorganizados y según el cuatrimestre toman recuperatorios o no | K4: =VLOOKUP(A4,CORTE!$A$2:$B$1045,2,0)
A5: 7041 | B5: VERGARA-KOTT CARLA | C5: MI | D5: PRESENCIAL | E5: 07:00-10:00 | F5: BAJO | G5: MIXTO | H5: SI | I5: NO | J5: Los profes no siguen el programa y puede tornarse desorganizada la cursada, faltando varios temas de obligaciones que en otras comisiones sí se ven y mejor. Toman 3 parciales (2 escritos y 1 oral): para llegar al tercero tenés que haber promocionado los otros dos, si no tenés un final en lugar del parcial de los últimos temas. Son desorganizados y según el cuatrimestre toman recuperatorios o no | K5: =VLOOKUP(A5,CORTE!$A$2:$B$1045,2,0)
A6: 7000 | B6: CALVO COSTA-KITAINIK | C6: LU-JU | D6: PRESENCIAL | E6: 08:30-10:00 | F6: MEDIO | G6: MULTIPLECHOICE | I6: NO | J6: Cátedra muy exigente a la hora de corregir, no es fácil promocionar. Tomaron 2 parciales con cuatro preguntas; depende qué profe te toque puede ser divertida la cursada un embole | K6: =VLOOKUP(A6,CORTE!$A$2:$B$1045,2,0) | L6: TECNICA
A7: 7030 | B7: MARINO-MARINO A. | C7: LU-JU | D7: VIRTUAL | E7: 08:30-10:00 | F7: MEDIO | G7: ESCRITO | H7: NO | I7: NO | J7: Los profes responden dudas en clase, por mail o Whatsapp. Son bastante organizados y hacen que la materia que es pesada sea más llevadera. Llevando al día las clases y estudiando de allí podés promocionar tranquilamente (todos los inscriptos promocionaron), mandan guías de preguntas previas al parcial que sirven para practicar y estar al día; ayudan una banda. Ponen notas altas | K7: =VLOOKUP(A7,CORTE!$A$2:$B$1045,2,0) -> 6,06
A8: 7031 | B8: MARINO-MARINO A. | C8: LU-JU | D8: PRESENCIAL | E8: 08:30-10:00 | F8: MEDIO | G8: ESCRITO | H8: NO | I8: NO | J8: Los profes responden dudas en clase, por mail o Whatsapp. Son bastante organizados y hacen que la materia que es pesada sea más llevadera. Llevando al día las clases y estudiando de allí podés promocionar tranquilamente (todos los inscriptos promocionaron), mandan guías de preguntas previas al parcial que sirven para practicar y estar al día; ayudan una banda. Ponen notas altas | K8: =VLOOKUP(A8,CORTE!$A$2:$B$1045,2,0)
A9: 7042 | B9: VERGARA-BUSTELO | C9: MA-VI | D9: PRESENCIAL | E9: 08:30-10:00 | F9: MEDIO | G9: ESCRITO | H9: SI | I9: SI | J9: A las profes les interesa que aprendas bien los temas, no tienen ánimos de bochar y es promocionable llevando al día las clases. Toman 3 parciales y un TP grupal que hay que defender oralmente en clases. Lo malo es que si no promocionaste alguno de los dos primeros parciales te mandan a final. Usan el manual de Alterini, el código comentado de Ameal y el CCyC | K9: =VLOOKUP(A9,CORTE!$A$2:$B$1045,2,0)
A10: 7071 | B10: WIERZBA-RUA | C10: MA-VI | D10: PRESENCIAL | E10: 08:30-10:00 | F10: MEDIO | G10: MIXTO | H10: SI | I10: SI | J10: Muy recomedada, las clases las da Isabel Rúa y los ayudantes. Son dos parciales el primero escrito mitad múltiple choice y dos casos prácticos; el segundo es oral son tres o cuatro preguntas. Son pro alumno, cero ánimos de bochar. | K10: =VLOOKUP(A10,CORTE!$A$2:$B$1045,2,0) | L10: APERTURA
A11: 7043 | B11: VERGARA-BAGNATO | C11: MI | D11: PRESENCIAL | E11: 08:30-11:30 | F11: MEDIO | G11: ESCRITO | H11: SI | I11: NO | J11: Toman asistencia 2 veces, 2 parciales escritos si llegas a 6 vas a final pero solo expones la última parte sino llegas al 6 expones toda la materia. Aprendes muchísimo. Los parciales escritos no son complicados. Es más bien general podes explayarte | K11: =VLOOKUP(A11,CORTE!$A$2:$B$1045,2,0)
A12: 7044 | B12: VERGARA-BAGNATO | C12: MI | D12: PRESENCIAL | E12: 08:30-11:30 | F12: MEDIO | G12: ESCRITO | H12: SI | I12: NO | J12: Toman asistencia 2 veces, 2 parciales escritos si llegas a 6 vas a final pero solo expones la última parte sino llegas al 6 expones toda la materia. Aprendes muchísimo. Los parciales escritos no son complicados. Es más bien general podes explayarte | K12: =VLOOKUP(A12,CORTE!$A$2:$B$1045,2,0)
A13: 7001 | B13: CALVO COSTA-KITAINIK | C13: LU-JU | D13: PRESENCIAL | E13: 10:00-11:30 | F13: ALTO | G13: ESCRITO | J13: Para cada clase dan un PPT como resumen de lo que se ve. Sin ánimos de bochar. Los parciales se dividen en una parte con v o f + un práctico a resolver (te dan casos prácticos antes para que puedas resolverlos y se resuelven en clase). | K13: =VLOOKUP(A13,CORTE!$A$2:$B$1045,2,0) | L13: TECNICA
A14: 7011 | B14: GOSENDE-CAPUA JUAN M | C14: LU-JU | D14: PRESENCIAL | E14: 10:00-11:30 | F14: MEDIO | G14: ESCRITO | H14: SI | I14: SI | J14: Las clases son de consulta sobre el material de lectura (usan el manual de Wizerba) así que esta cátedra te conviene si te gusta estudiar por tu cuenta. Toman TPs de entrega obligatoria pero sin nota y los parciales son escritos con consignas similares a los TPs. No tienen ánimos de bochar y a fin de curso hacen una actividad para levantar nota a los que le falten | K14: =VLOOKUP(A14,CORTE!$A$2:$B$1045,2,0) -> 6,61
A15: 7032 | B15: MARINO-BURGOS | C15: LU-JU | D15: PRESENCIAL | E15: 10:00-11:30 | F15: MEDIO | G15: ESCRITO | H15: SI | I15: SI | J15: Los profes explican bien y no tienen problema en responder todas las dudas; te dan TPs prácticos y de teoría que no son difíciles de hacer y te ayudan a llevar al día la materia; son 2 o 3 (según el cuatrimestre) parciales cortos para aplicar teoría y lo visto en clase, sin ánimos de bochar | K15: =VLOOKUP(A15,CORTE!$A$2:$B$1045,2,0)
A16: 7045 | B16: VERGARA-BUSTELO | C16: MA-VI | D16: PRESENCIAL | E16: 10:00-11:30 | F16: MEDIO | G16: ESCRITO | H16: SI | I16: SI | J16: A las profes les interesa que aprendas bien los temas, no tienen ánimos de bochar y es promocionable llevando al día las clases. Toman 3 parciales y un TP grupal que hay que defender oralmente en clases. Lo malo es que si no promocionaste alguno de los dos primeros parciales te mandan a final. Usan el manual de Alterini, el código comentado de Ameal y el CCyC | K16: =VLOOKUP(A16,CORTE!$A$2:$B$1045,2,0)
A17: 7046 | B17: VERGARA-DELL OSA S. | C17: MA-VI | D17: PRESENCIAL | E17: 10:00-11:30 | F17: MEDIO | G17: MIXTO | H17: NO | I17: NO | J17: Es súper pedagógica y los profesores explican muy bien. No toman lista, tampoco dan tps. Mandan por el grupo de wp los materiales que son necesarios para que sea más llevadera la cursada y los parciales son tres; 2 mutilple choice por google forms y el tercero oral. En el oral no tiran a matar y ayudan mucho. | K17: =VLOOKUP(A17,CORTE!$A$2:$B$1045,2,0)
A18: 7047 | B18: VERGARA-DELL OSA S. | C18: MA-VI | D18: PRESENCIAL | E18: 10:00-11:30 | F18: MEDIO | G18: MIXTO | H18: NO | I18: NO | J18: Es súper pedagógica y los profesores explican muy bien. No toman lista, tampoco dan tps. Mandan por el grupo de wp los materiales que son necesarios para que sea más llevadera la cursada y los parciales son tres; 2 mutilple choice por google forms y el tercero oral. En el oral no tiran a matar y ayudan mucho. | K18: =VLOOKUP(A18,CORTE!$A$2:$B$1045,2,0)
A19: 7072 | B19: WIERZBA-PANIAGUA | C19: LU-JU | D19: PRESENCIAL | E19: 10:00-11:30 | F19: ALTO | G19: ESCRITO | H19: SI | I19: NO | J19: Hay opiniones encontradas sobre la forma de dar clase: pocos ejemplos y muy teóricas. Al ser una materia con gran contenido es importante llevarla al día por tu cuenta, puede hacerse pesada en esta comisión. Al no enviar el programa para guiarte puede complicarte; los parciales eran escritos y el recuperatorio oral. Usaban el manual de Wierzba | K19: =VLOOKUP(A19,CORTE!$A$2:$B$1045,2,0)
A20: 7002 | B20: CALVO COSTA-GONZALEZ | C20: MA-VI | D20: VIRTUAL | E20: 11:30-13:00 | F20: MEDIO | G20: ESCRITO | H20: NO | I20: NO | J20: Las profes son capas, no tienen ánimos de bochar y explican los temas respondiendo preguntas. Los parciales fueron escritos con pocas preguntas a desarrollar y los recuperatorios orales, te ayudaban si te trababas. No ponían notas altas pero promocionamos todos. Recomendada | K20: =VLOOKUP(A20,CORTE!$A$2:$B$1045,2,0) | L20: TECNICA
A21: 7010 | B21: GOSENDE-CAPUA JUAN M | C21: LU-JU | D21: PRESENCIAL | E21: 11:30-13:00 | F21: MEDIO | G21: ESCRITO | H21: SI | I21: SI | J21: Las clases son de consulta sobre el material de lectura (usan el manual de Wizerba) así que esta cátedra te conviene si te gusta estudiar por tu cuenta. Toman TPs de entrega obligatoria pero sin nota y los parciales son escritos con consignas similares a los TPs. No tienen ánimos de bochar y a fin de curso hacen una actividad para levantar nota a los que le falten | K21: =VLOOKUP(A21,CORTE!$A$2:$B$1045,2,0)
A22: 7073 | B22: WIERZBA-PANIAGUA | C22: LU-JU | D22: PRESENCIAL | E22: 11:30-13:00 | F22: ALTO | G22: ESCRITO | H22: SI | I22: NO | J22: Hay opiniones encontradas sobre la forma de dar clase: pocos ejemplos y muy teóricas. Al ser una materia con gran contenido es importante llevarla al día por tu cuenta, puede hacerse pesada en esta comisión. Al no enviar el programa para guiarte puede complicarte; los parciales eran escritos y el recuperatorio oral. Usaban el manual de Wierzba | K22: =VLOOKUP(A22,CORTE!$A$2:$B$1045,2,0)
A23: 7012 | B23: GOSENDE-BENAVENTE M. | C23: LU-JU | D23: PRESENCIAL | E23: 14:00-15:30 | F23: MEDIO | G23: ESCRITO | H23: NO | I23: SI | J23: Dos parciales escritos, 4 preguntas concretas. Un tp/simulacro antes del segundo parcial. No toma lista. Clases muy buenas. Trato muy ameno y atento especialmente de la Dra. Benavente. Se puede utilizar manual de Calvo Costa o Wierzba indistintamente | K23: =VLOOKUP(A23,CORTE!$A$2:$B$1045,2,0) | L23: TECNICA
A24: 7020 | B24: PICASSO-BESALU P. | C24: MA-VI | D24: VIRTUAL | E24: 14:00-15:30 | K24: =VLOOKUP(A24,CORTE!$A$2:$B$1045,2,0)
A25: 7048 | B25: VERGARA-RIBAS SOMAR | C25: LU-JU | D25: PRESENCIAL | E25: 14:00-15:30 | F25: MEDIO | G25: ESCRITO | H25: NO | I25: NO | J25: Toman dos parciales escritos a desarrollar súper promocionables, ponen notas altas. Cada tanto mandan algún TP nada difícil para mantener la regularidad | K25: =VLOOKUP(A25,CORTE!$A$2:$B$1045,2,0)
A26: 7074 | B26: WIERZBA-BORAGINA J. | C26: MA-VI | D26: PRESENCIAL | E26: 14:00-15:30 | F26: MEDIO | G26: ESCRITO | H26: SI | I26: SI | J26: Cátedra pro alumno. dos parciales de casos prácticos a resolver. se trabajan casos prácticos durante la cursada. Hay que hacer una monografía de regularidad sobre un supuesto de responsabilidad civil especial (se elige de una lista que dan desde la cátedra) | K26: =VLOOKUP(A26,CORTE!$A$2:$B$1045,2,0) | L26: TECNICA
A27: 7078 | B27: WIERZBA-ITURBIDE G. | C27: LU-JU | D27: PRESENCIAL | E27: 14:00-15:30 | F27: MEDIO | G27: MULTIPLECHOICE | H27: SI | I27: NO | J27: Pro alumno, es una cátedra donde se aprende, se usa el manual de Wierzba. Siguen el cronograma y no tienen problemas en poner notas altas, siguiendo al día la materia con las clases estás para promocionar. | K27: =VLOOKUP(A27,CORTE!$A$2:$B$1045,2,0) | L27: TECNICA
A28: 7013 | B28: GOSENDE-BENAVENTE M. | C28: LU-JU | D28: PRESENCIAL | E28: 15:30-17:00 | F28: MEDIO | G28: ESCRITO | H28: NO | I28: SI | J28: Dos parciales escritos, 4 preguntas concretas. Un tp/simulacro antes del segundo parcial. No toma lista. Clases muy buenas. Trato muy ameno y atento especialmente de la Dra. Benavente. Se puede utilizar manual de Calvo Costa o Wierzba indistintamente | K28: =VLOOKUP(A28,CORTE!$A$2:$B$1045,2,0) | L28: TECNICA
A29: 7049 | B29: VERGARA-DIAZ PABLO | C29: LU-JU | D29: PRESENCIAL | E29: 15:30-17:00 | F29: MEDIO | G29: ESCRITO | H29: SI | I29: NO | J29: No toman TPs, toman dos parciales a desarrollar con 5 preguntas. Algunos profes dan buenas clases, otros pueden ser más aburridos o monótonos. No toman fallos; la bibliografía es libre, a elección de los estudiantes. No tienen problemas en poner buenas notas, sin ánimos de bochar. | K29: =VLOOKUP(A29,CORTE!$A$2:$B$1045,2,0)
A30: 7075 | B30: WIERZBA-BORAGINA J. | C30: MA-VI | D30: PRESENCIAL | E30: 15:30-17:00 | F30: MEDIO | G30: ESCRITO | H30: SI | I30: SI | J30: Cátedra pro alumno. dos parciales de casos prácticos a resolver. se trabajan casos prácticos durante la cursada. Hay que hacer una monografía de regularidad sobre un supuesto de responsabilidad civil especial (se elige de una lista que dan desde la cátedra) | K30: =VLOOKUP(A30,CORTE!$A$2:$B$1045,2,0) | L30: TECNICA
A31: 7079 | B31: WIERZBA-ITURBIDE G. | C31: LU-JU | D31: PRESENCIAL | E31: 15:30-17:00 | F31: MEDIO | G31: MULTIPLECHOICE | H31: SI | I31: NO | J31: Pro alumno, es una cátedra donde se aprende, se usa el manual de Wierzba. Siguen el cronograma y no tienen problemas en poner notas altas, siguiendo al día la materia con las clases estás para promocionar. | K31: =VLOOKUP(A31,CORTE!$A$2:$B$1045,2,0) | L31: TECNICA
A32: 7005 | B32: CALVO COSTA-LOMBARDI | C32: MA-VI | D32: VIRTUAL | E32: 17:00-18:30 | F32: ALTO | G32: ESCRITO | H32: SI | I32: SI | J32: Pueden ser demasiado exigentes a la hora de corregir y poner notas. Las clases son teóricas con el CCyC y en los parciales piden que se contesten casos prácticos. Toman TPs que hacen una nota conceptual que se promedia con la de los parciales. Mala predisposición para responder dudas. | K32: =VLOOKUP(A32,CORTE!$A$2:$B$1045,2,0)
A33: 7004 | B33: CALVO COSTA-SAGARNA | C33: LU-JU | D33: PRESENCIAL | E33: 17:00-18:30 | F33: MEDIO | G33: ESCRITO | H33: SI | I33: SI | J33: 2 parciales escritos a desarrollar y 2 tps escritos grupales. Siguen el manual de calvo costa y suben powerpoints de todos los temas y guias de estudio al campus. | K33: =VLOOKUP(A33,CORTE!$A$2:$B$1045,2,0) | L33: TECNICA
A34: 7024 | B34: PICASSO-CICCHINO P. | C34: MA-VI | D34: PRESENCIAL | E34: 17:00-18:30 | F34: MEDIO | G34: MIXTO | H34: SI | I34: NO | J34: Los profes responden dudas en clase y por Whatsapp, no tienen ánimos de bochar y son súper calidos.los parciales son multiple-choice , si bien son exigentes con las notas te ayudan si te trabas y explican todo muchas veces . Recomendada. luis maria y paula son los profesores mas claros de derecho privado que tuve. los ayudantes son muy capos. | K34: =VLOOKUP(A34,CORTE!$A$2:$B$1045,2,0)
A35: 7025 | B35: PICASSO-MENDEZ ACOSTA | C35: LU-JU | D35: VIRTUAL | E35: 17:00-18:30 | K35: =VLOOKUP(A35,CORTE!$A$2:$B$1045,2,0)
A36: 7022 | B36: PICASSO-SANTARELLI F | C36: MA-VI | D36: PRESENCIAL | E36: 17:00-18:30 | F36: ALTO | G36: MIXTO | H36: SI | I36: NO | J36: Las clases son súper dinámicas, mucho contenido y exigente pero se aprende mucho y tienen buena predisposición. Toman dos parciales uno escrito y uno oral | K36: =VLOOKUP(A36,CORTE!$A$2:$B$1045,2,0)
A37: 7033 | B37: MARINO-MAGLIO | C37: MA-VI | D37: PRESENCIAL | E37: 08:00-10:00 | F37: MEDIO | G37: ESCRITO | H37: SI | I37: NO | J37: Cátedra promocionable, las clases son monólogos de las profesoras, mandan una guía de 80 preguntas antes de cada parcial y las preguntas del mismo salen de ahí o son muy similares. Alcanza con llevarla al día y hacer las guías de preguntas | K37: =VLOOKUP(A37,CORTE!$A$2:$B$1045,2,0)
A38: 7051 | B38: VERGARA-ALVAREZ M. | C38: LU-JU | D38: VIRTUAL | E38: 17:00-18:30 | F38: MEDIO | G38: ESCRITO | H38: SI | I38: NO | J38: Toma dos parciales escritos y un tercero oral que si respondes bien y te da la nota para promocionar ya estás, si te falta nota te pregunta acerca del parcial que peor nota tengas para que puedas llegar. Las clases eran bastante llevaderas. Es importante llevarlas al día porque el libro que usan no acompaña la cursada | K38: =VLOOKUP(A38,CORTE!$A$2:$B$1045,2,0)
A39: 7053 | B39: VERGARA-ALVAREZ M. | C39: MA-VI | D39: VIRTUAL | E39: 17:00-18:30 | K39: =VLOOKUP(A39,CORTE!$A$2:$B$1045,2,0)
A40: 7050 | B40: VERGARA-HIGHTON C | C40: LU-JU | D40: PRESENCIAL | E40: 17:00-18:30 | F40: MEDIO | G40: ESCRITO | H40: NO | I40: NO | J40: Muy buenas clases, tienen muy buena predisposición a responder dudas. Evalua con parcial a desarrollar y con algunas preguntas choice. Recomendada | K40: =VLOOKUP(A40,CORTE!$A$2:$B$1045,2,0) | L40: TECNICA
A41: 7052 | B41: VERGARA-ROMANO | C41: LU-JU | D41: PRESENCIAL | E41: 17:00-18:30 | F41: BAJO | G41: ORAL | H41: NO | I41: NO | J41: Mandan PPT (se puede estudiar de ahí tranquilamente). Te recomiendan el manual de Ameal aunque puede estudiarse de apuntes y los PPT. | K41: =VLOOKUP(A41,CORTE!$A$2:$B$1045,2,0) | L41: TECNICA
A42: 7063 | B42: VERGARA-ROMANO | C42: LU-JU | D42: PRESENCIAL | E42: 17:00-18:30 | F42: BAJO | G42: ORAL | H42: NO | I42: NO | J42: Mandan PPT (se puede estudiar de ahí tranquilamente). Te recomiendan el manual de Ameal aunque puede estudiarse de apuntes y los PPT. | K42: =VLOOKUP(A42,CORTE!$A$2:$B$1045,2,0) | L42: TECNICA
A43: 7021 | B43: PICASSO-SAENZ LUIS | C43: MI | D43: VIRTUAL | E43: 17:00-20:00 | F43: MEDIO | G43: ESCRITO | H43: SI | I43: SI | J43: Hay opiniones encontradas sobre el trato en los parciales: muy poco tiempo para responder poco más de 50 preguntas muy extensas sobre casos prácticos; virtualmente era con cámara prendida y no podías tener la mano en la boca interrumpiendo todo el tiempo del parcial. Usan el manual de Calvo Costa | K43: =VLOOKUP(A43,CORTE!$A$2:$B$1045,2,0) | L43: TECNICA
A44: 7054 | B44: VERGARA-DAMIÁN VENTURA | C44: MI | D44: PRESENCIAL | E44: 17:00-20:00 | K44: =VLOOKUP(A44,CORTE!$A$2:$B$1045,2,0)
A45: 7006 | B45: CALVO COSTA-ROSSELLO | C45: LU-JU | D45: PRESENCIAL | E45: 18:30-20:00 | F45: BAJO | G45: MIXTO | H45: SI | J45: La profesora Gabriela tiene buena llegada en alumnos, usando pp por clase. Primer parcial choice y uno segundo con preguntas a desarrollar faciles. Permite subir nota para promocionar, con un ultimo trabajo practico. | K45: =VLOOKUP(A45,CORTE!$A$2:$B$1045,2,0)
A46: 7007 | B46: CALVO COSTA-SAGARNA | C46: LU-JU | D46: PRESENCIAL | E46: 18:30-20:00 | F46: MEDIO | G46: ESCRITO | H46: SI | I46: SI | J46: Toman lista hasta el primer parcial La recomiendo. Por cada tema envían un power point para estudiar después. Toman preguntas y un caso práctico, no suelen poner notas altas. Hay un tp antes de cada parcial. | K46: =VLOOKUP(A46,CORTE!$A$2:$B$1045,2,0) | L46: TECNICA
A47: 7035 | B47: MARINO-BURGOS | C47: MA-VI | D47: PRESENCIAL | E47: 18:30-20:00 | K47: =VLOOKUP(A47,CORTE!$A$2:$B$1045,2,0)
A48: 7034 | B48: MARINO-MAGLIO | C48: MA-VI | D48: PRESENCIAL | E48: 10:00-11:30 | F48: MEDIO | G48: ESCRITO | H48: SI | I48: NO | J48: Cátedra promocionable, las clases son monólogos de las profesoras, mandan una guía de 80 preguntas antes de cada parcial y las preguntas del mismo salen de ahí o son muy similares. Alcanza con llevarla al día y hacer las guías de preguntas | K48: =VLOOKUP(A48,CORTE!$A$2:$B$1045,2,0)
A49: 7055 | B49: VERGARA-AGUIRRE P. | C49: LU-JU | D49: PRESENCIAL | E49: 18:30-20:00 | F49: MEDIO | G49: MIXTO | H49: NO | I49: NO | J49: Usan el manual de Ameal y Alterini con guías muy completas de los puntos importantes. Toman 2 parciales multiple-choice y con algún caso a resolver. Tiene final obligatorio pero promocionado con los dos parciales te toman solo el final de la materia | K49: =VLOOKUP(A49,CORTE!$A$2:$B$1045,2,0)
A50: 7076 | B50: WIERZBA-FERRARI G. | C50: MA-VI | D50: VIRTUAL | E50: 18:30-20:00 | F50: BAJO | G50: MIXTO | H50: NO | I50: SI | J50: El material de estudio es el manual de la titular de la cátedra que se sigue bastante al pie de la letra. Dependiendo del profesor que dé la clase toma o no lista (no suele influir). El primer parcial es escrito (V o F, o pregunta respuesta de no más de 2 renglones) y el recuperatorio es oral. El segundo parcial es un trabajo en grupo que se presenta oral. No hay recuperatorio del segundo parcial sino que se usa la instancia del final para tomar lo del segundo parcial si te fue mal. No tiene ánimos de bochar. Se toman TPs si es que se pierde alguna clase. MUY PRO ALUMNO Y PROMOCIONABLE. | K50: =VLOOKUP(A50,CORTE!$A$2:$B$1045,2,0) | L50: TECNICA
A51: 7014 | B51: GOSENDE-CRACOGNA F. | C51: MA-VI | D51: PRESENCIAL | E51: 20:00-21:30 | F51: MEDIO | G51: ESCRITO | H51: NO | I51: SI | J51: Toman dos parciales a desarrollar y dos trabajos practicos. Explican bien con fallos y casos actuales. | K51: =VLOOKUP(A51,CORTE!$A$2:$B$1045,2,0)
A52: 7023 | B52: PICASSO-POZZI | C52: MA-VI | D52: PRESENCIAL | E52: 20:00-21:30 | F52: MEDIO | G52: MULTIPLECHOICE | H52: NO | I52: NO | J52: Toman dos parciales multiple-choice, sin ánimos de bochar. Siguiendo al día las clases estás más que bien, no tienen problemas en responder dudas y explican bien los temas. Promocionable | K52: =VLOOKUP(A52,CORTE!$A$2:$B$1045,2,0)
A53: 7056 | B53: VERGARA-AGUIRRE P. | C53: LU-JU | D53: PRESENCIAL | E53: 20:00-21:30 | F53: MEDIO | G53: MIXTO | H53: NO | I53: NO | J53: Usan el manual de Ameal y Alterini con guías muy completas de los puntos importantes. Toman 2 parciales multiple-choice y con algún caso a resolver. Tiene final obligatorio pero promocionado con los dos parciales te toman solo el final de la materia | K53: =VLOOKUP(A53,CORTE!$A$2:$B$1045,2,0)
A54: 7058 | B54: VERGARA-GIARRATANA | C54: MA-VI | D54: PRESENCIAL | E54: 20:00-21:30 | F54: MEDIO | G54: ESCRITO | H54: SI | I54: SI | J54: 2 parciales. El primero es hacer un Contrato. El segundo es hacer una demanda domiciliaria con un compañero. La profe Giarratana sube todo a un campus a un Drive ,sube fichas por temas. Hay una carpeta de trabajo que sube con tps para practicar, que se resuelven en clases. Lo bueno es que, aprendes hacer lo que recién lo hacés en el práctico. | K54: =VLOOKUP(A54,CORTE!$A$2:$B$1045,2,0) | L54: TECNICA
A55: 7059 | B55: VERGARA-GIARRATANA | C55: MA-VI | D55: PRESENCIAL | E55: 20:00-21:30 | J55: Comisión no abierta en el 1° cuatrimestre. La Facultad exige un mínimo de 8 inscriptos para la apertura de la comisión y la consecuente asignación de aula.
A56: 7057 | B56: VERGARA-NICOLI DIEGO | C56: MA-VI | D56: PRESENCIAL | E56: 20:00-21:30 | F56: ALTO | G56: MIXTO | H56: SI | I56: NO | J56: Los profes son amables y dan buenas clases, son 2 parciales escritos. El único contra es que toman final obligatorio de manera oral, aún si te dan la nota de los otros parciales para promocionar. Son exigentes pero se aprende mucho, te da una buena base | K56: =VLOOKUP(A56,CORTE!$A$2:$B$1045,2,0)
A57: 7077 | B57: WIERZBA-FERRARI G. | C57: MA-VI | D57: VIRTUAL | E57: 20:00-21:30 | F57: BAJO | G57: MIXTO | H57: NO | I57: SI | J57: El material de estudio es el manual de la titular de la cátedra que se sigue bastante al pie de la letra. Dependiendo del profesor que dé la clase toma o no lista (no suele influir). El primer parcial es escrito (V o F, o pregunta respuesta de no más de 2 renglones) y el recuperatorio es oral. El segundo parcial es un trabajo en grupo que se presenta oral. No hay recuperatorio del segundo parcial sino que se usa la instancia del final para tomar lo del segundo parcial si te fue mal. No tiene ánimos de bochar. Se toman TPs si es que se pierde alguna clase. MUY PRO ALUMNO Y PROMOCIONABLE. | K57: =VLOOKUP(A57,CORTE!$A$2:$B$1045,2,0) | L57: TECNICA
A58: 7062 | B58: VERGARA-NICOLI DIEGO | C58: LU-JU | D58: PRESENCIAL | E58: 21:30-23:00 | F58: ALTO | G58: MIXTO | H58: SI | I58: NO | J58: Los profes son amables y dan buenas clases, son 2 parciales escritos. El único contra es que toman final obligatorio de manera oral, aún si te dan la nota de los otros parciales para promocionar. Son exigentes pero se aprende mucho, te da una buena base | K58: =VLOOKUP(A58,CORTE!$A$2:$B$1045,2,0)
A59: 7060 | B59: VERGARA-O'DONNELL G. | C59: LU-JU | D59: VIRTUAL | E59: 21:30-23:00 | F59: MEDIO | G59: MIXTO | H59: SI | I59: NO | J59: Toman 3 parciales que van alternando entre oral y escrito, no tienen ánimos de bochar y responden todas las dudas. Pueden ser desorganizados con los tiempos y las clases, se puede aprobar con lo visto en clase y el material complementario | K59: =VLOOKUP(A59,CORTE!$A$2:$B$1045,2,0)
A60: 7061 | B60: VERGARA-O'DONNELL G. | C60: LU-JU | D60: VIRTUAL | E60: 21:30-23:00 | F60: MEDIO | G60: MIXTO | H60: SI | I60: NO | J60: Toman 3 parciales que van alternando entre oral y escrito, no tienen ánimos de bochar y responden todas las dudas. Pueden ser desorganizados con los tiempos y las clases, se puede aprobar con lo visto en clase y el material complementario | K60: =VLOOKUP(A60,CORTE!$A$2:$B$1045,2,0)

Sheet REALES
A1: 📚 ELEMENTOS DE DERECHOS REALES - 2º CUATRI 2026 - LA CÁMPORA 📚
A2: N° | B2: COMISIÓN | C2: DÍAS | D2: MODALIDAD | E2: HORARIO | F2: NIVEL | G2: PARCIAL | H2: TOMA LISTA | I2: TOMA TPS | J2: COMENTARIO | K2: CORTE 1° CUATRI | L2: POSTURA
A3: 7910 | B3: CARTA-DE LARA | C3: MA-VI | D3: PRESENCIAL | E3: 07:00-08:30 | F3: MEDIO | G3: ESCRITO | H3: NO | I3: NO | J3: MUY RECOMENDADA. Dos parciales con 5 o 6 preguntas a desarrollar. Hay que ser preciso con la repuestas y explicar. Muy buen trato de los docentes. | K3: =VLOOKUP(A3,CORTE!$A$2:$B$1045,2,0)
A4: 7920 | B4: KIPER-CASTRO LAURA | C4: LU-JU | D4: VIRTUAL | E4: 07:00-08:30 | F4: MEDIO | G4: ESCRITO | I4: NO | J4: Muy recomendada. Las profesoras explican muy bien y es una cátedra ordenada. Dan casos prácticos para entender la teoria. Toman lo que dan en clase. Se aprende muchísimo. Pro alumnos. Evalúan con dos parciales escritos presenciales compuestos por V y F, y preguntas a desarrollar muy cortas y concretas. Promocionable pero hay que estudiar. | K4: =VLOOKUP(A4,CORTE!$A$2:$B$1045,2,0)
A5: 7940 | B5: ABREUT-BRAIDORT ELIANA | C5: LU-JU | D5: PRESENCIAL | E5: 08:30-10:00 | F5: MEDIO | G5: MIXTO | H5: SI | J5: Clases didacticas, son tres profes. Los parciales son mitad escrito y mitad choice con recuperatorio oral. Se aprueba estudiando de las clases y de los manuales, tienen temas particulares que no dan en otras cátedras. Pro alumno y sin ánimos de bochar | K5: =VLOOKUP(A5,CORTE!$A$2:$B$1045,2,0)
A6: 7911 | B6: CARTA-DE LARA | C6: MA-VI | D6: PRESENCIAL | E6: 08:30-10:00 | F6: MEDIO | G6: ESCRITO | H6: NO | I6: NO | J6: MUY RECOMENDADA. Dos parciales con 5 o 6 preguntas a desarrollar. Hay que ser preciso con la repuestas y explicar. Muy buen trato de los docentes. | K6: =VLOOKUP(A6,CORTE!$A$2:$B$1045,2,0) -> 7,11
A7: 7921 | B7: KIPER-MALIZIA ROBERTO | C7: MA-VI | D7: PRESENCIAL | E7: 08:30-10:00 | F7: ALTO | G7: MULTIPLECHOICE | I7: NO | J7: Cátedra exigente. No dan recuperatorio del segundo parcial (lo que está en contra del reglamento), si te va mal vas a final directo. El parcial tiene V o F, MC y casos prácticos, y son largos. Los profesores explican bien pero es muy difícil de promocionar | K7: =VLOOKUP(A7,CORTE!$A$2:$B$1045,2,0)
A8: 7930 | B8: VAZQUEZ G.-FARINA M. | C8: LU-JU | D8: PRESENCIAL | E8: 08:30-10:00 | F8: ALTO | G8: ESCRITO | J8: Cátedra organizada. Mandan material por el campus y el manual es a libre elección. Primer parcial preguntas a desarrollar. Segundo parcial tres preguntas a desarrollar y un caso práctico. | K8: =VLOOKUP(A8,CORTE!$A$2:$B$1045,2,0)
A9: 7941 | B9: ABREUT-BRAIDORT ELIANA | C9: LU-JU | D9: PRESENCIAL | E9: 10:00-11:30 | F9: MEDIO | G9: MIXTO | H9: SI | J9: Clases didacticas, son tres profes. Los parciales son mitad escrito y mitad choice con recuperatorio oral. Se aprueba estudiando de las clases y de los manuales, tienen temas particualres que no dan en otras cátedras. Pro alumno y sin ánimos de bochar | K9: =VLOOKUP(A9,CORTE!$A$2:$B$1045,2,0)
A10: 7922 | B10: KIPER-CASTRO LAURA | C10: MA-VI | D10: VIRTUAL | E10: 10:00-11:30 | F10: MEDIO | G10: ORAL | J10: Los parciales son orales. El equipo docente enseñan muy bien, son muy estrictos con la cursada, pero eso ayuda a llegar bien al parcial | K10: =VLOOKUP(A10,CORTE!$A$2:$B$1045,2,0)
A11: 7952 | B11: PERALTA MARISCAL-SICILIANO D. | C11: LU-JU | D11: PRESENCIAL | E11: 10:00-11:30 | F11: MEDIO | J11: Muy recomendada. Las profesoras tienen un muy buen trato con los estudiantes. Explican con pp en las clases que después suben al campus. Las clases son entretenidas. Evalúan con dos parciales escritos a desarrollar 5 preguntas. La profe de los lunes al final de la clase da un pequeño trabajo grupal o individual pero no se entrega no se entrega ni va con nota, solo es una actividad que se hace en clase. | K11: =VLOOKUP(A11,CORTE!$A$2:$B$1045,2,0) -> 6,66
A12: 7931 | B12: VAZQUEZ G.-FARINA M. | C12: LU-JU | D12: PRESENCIAL | E12: 10:00-11:30 | F12: MEDIO | G12: ESCRITO | J12: La profesora es muy amable y muy apasionada por la materia pero no se llega a dar todos los temas y es medio desorganizado. Los parciales son a desarollar pero quieren que solo contestes apuntando a la pregunta sin irte por las ramas. Ponen notas un poco bajas y no saben decirte qué te faltó poner y por qué te bajaron la nota. | K12: =VLOOKUP(A12,CORTE!$A$2:$B$1045,2,0)
A13: 7942 | B13: ABREUT-RULLANSKY | C13: MI | D13: PRESENCIAL | E13: 10:00-13:00 | F13: MEDIO | G13: MIXTO | J13: Buena cátedra, promocionable. El primer parcial fue MC. El segundo parcial fue oral grupal. Las clases son muy buenas y sigue el manual al pie de la letra. // Clases muy buenas. Organizadas. Todo de acuerdo al cronograma. Se estudia del manual de la titular de la cátedra. Primer parcial múltiple choice, segundo oral con tema a preparar y alguna pregunta para relacionar contenidos con otro tema. Hay tp muy sencillos todas las semanas de v o f o casos prácticos simples, no son obligatorios pero ayudan en la nota. Muy promocionable. | K13: =VLOOKUP(A13,CORTE!$A$2:$B$1045,2,0)
A14: 7953 | B14: PERALTA MARISCAL-SICILIANO D. | C14: LU-JU | D14: PRESENCIAL | E14: 11:30-13:00 | F14: MEDIO | G14: ESCRITO | J14: Muy recomendada. Las profesoras tienen un muy buen trato con los estudiantes. Explican con pp en las clases que después suben al campus. Las clases son entretenidas. Evalúan con dos parciales escritos a desarrollar 5 preguntas. La profe de los lunes al final de la clase da un pequeño trabajo grupal o individual pero no se entrega no se entrega ni va con nota, solo es una actividad que se hace en clase. | K14: =VLOOKUP(A14,CORTE!$A$2:$B$1045,2,0)
A15: 7933 | B15: VAZQUEZ G.-HACHA MARQUEZ MIGUEL | C15: LU-JU | D15: PRESENCIAL | E15: 11:30-13:00 | F15: MEDIO | G15: MIXTO | I15: NO | J15: No recomendada. El profesor Hacha tiene malos tratos hacia los alumnos. Las clases son muy malas, no le llegan a ver los temas. No toma recuperatorio. El primer parcial es escrito con V o F, multiple choice y preguntas a desarrollar. El segundo parcial es oral, y a la mayoría le puso 4 sin ningún criterio para promocionarlos porque "no toma recuperatorio". No toma final.
A16: 7938 | B16: VAZQUEZ G.-BOQUE ROBERTO | C16: LU-JU | D16: PRESENCIAL | E16: 11:30-13:00 | F16: MEDIO | J16: Se aprueba, toman lo que dan en la clase. | K16: =VLOOKUP(A16,CORTE!$A$2:$B$1045,2,0)
A17: 7943 | B17: ABREUT-LOPEZ | C17: LU-JU | D17: PRESENCIAL | E17: 14:00-15:30 | F17: MEDIO | G17: ESCRITO | H17: SI | J17: El profesor Lopez del Carril es puntual y sigue bien el cronograma. No le molesta contestar consultas. Evalúan con dos parciales escritos a desarrollar. Manda dos TP no obligatorios. | K17: =VLOOKUP(A17,CORTE!$A$2:$B$1045,2,0)
A18: 7912 | B18: CARTA-ITURBIDE G. | C18: MA-VI | D18: PRESENCIAL | E18: 14:00-15:30 | F18: MEDIO | G18: ESCRITO | H18: NO | J18: Parciales virtuales por form. No toman lista, pero piden de ir a clases. | K18: =VLOOKUP(A18,CORTE!$A$2:$B$1045,2,0)
A19: 7913 | B19: CARTA-BARREIRO | C19: MI | D19: PRESENCIAL | E19: 14:00-17:00 | F19: MEDIO | G19: MULTIPLECHOICE | H19: NO | I19: SI | J19: Recomendada. Dos "mini parciales" multiple choice de repaso antes de los parciales. Dos parciales multiple choice domiciliarios. | K19: =VLOOKUP(A19,CORTE!$A$2:$B$1045,2,0)
A20: 7954 | B20: PERALTA MARISCAL-ROSENBROCK LAMBOIS | C20: MI | D20: PRESENCIAL | E20: 14:00-17:00 | F20: MEDIO | G20: MIXTO | H20: SI | I20: NO | J20: La JTP da las clases, explica muy claro todo y no tiene problema en volver a explicar. El primer parcial es escrito (5 preguntas) y el segundo oral (podes preparar un tema y después te hace preguntas sobre otros). Las preguntas las saca de las guías que da para estudiar. | K20: =VLOOKUP(A20,CORTE!$A$2:$B$1045,2,0)
A21: 7916 | B21: CARTA-ITURBIDE G. | C21: MA-VI | D21: VIRTUAL | E21: 15:30-17:00 | J21: Comisión nueva. En general recomendada ya que la profesora Verónica Otero suele hacer las clases llevaderas y con buena predisposición con los estudiantes | K21: =VLOOKUP(A21,CORTE!$A$2:$B$1045,2,0)
A22: 7923 | B22: KIPER-FAJRE JOSE | C22: LU-JU | D22: VIRTUAL | E22: 15:30-17:00 | F22: MEDIO | G22: MULTIPLECHOICE | H22: NO | I22: NO | J22: Muy recomendada. Parciales presenciales. Son dos parciales MC, las que estan mal restan, las que estan bien suman. Las clases estan buenas, son completas y con mucha participación del alumno. Dan buen material y exámenes de practica. | K22: =VLOOKUP(A22,CORTE!$A$2:$B$1045,2,0)
A23: 7927 | B23: KIPER-HUMPHREYS E. | C23: LU-JU | D23: VIRTUAL | E23: 15:30-17:00 | F23: MEDIO | G23: ESCRITO | J23: Cátedra desorganizada. Importante prestar atención en las clases, tomar apuntes y complementar con la bibliografía para rendir. El primer parcial fueron 2 películas que nos hizo ver y un caso práctico y el segundo parcial fueron 2 casos prácticos. Muy desorganizado todo el cuatrimestre pero aprobó la mayoría. Se aprueba pero no se aprende. | K23: =VLOOKUP(A23,CORTE!$A$2:$B$1045,2,0)
A24: 7934 | B24: VAZQUEZ G.-RAMOS VARDE JULIO | C24: MA-VI | D24: PRESENCIAL | E24: 15:30-17:00 | F24: MEDIO | G24: ESCRITO | J24: Excelente cuerpo docente. Trabajan con el código y el manual de la Dra Gabriela Vázquez. Dos parciales escritos a desarrollar sencillos. Comisión no abierta en el 1° cuatrimestre. La Facultad exige un mínimo de 8 inscriptos para la apertura de la comisión y la consecuente asignación de aula.
A25: 7944 | B25: ABREUT-ABREUT | C25: MI | D25: PRESENCIAL | E25: 15:30-18:30 | F25: MEDIO | G25: MIXTO | J25: Buena cátedra. Super pro alumnos. Después de cada clase los profesores envían resumen de los temas vistos. El primer parcial es escrito de 4 preguntas (que previamente envían en una guía de parcial) El segundo parcial es oral a tema libre que quieras preparar. | K25: =VLOOKUP(A25,CORTE!$A$2:$B$1045,2,0)
A26: 7945 | B26: ABREUT-KOZAK | C26: LU-JU | D26: PRESENCIAL | E26: 17:00-18:30 | F26: MEDIO | G26: ORAL | J26: Buenas clases. Los dos parciales son orales | K26: =VLOOKUP(A26,CORTE!$A$2:$B$1045,2,0)
A27: 7914 | B27: A DESIGNAR-PEPE M. | C27: MA-VI | D27: PRESENCIAL | E27: 17:00-18:30 | F27: MEDIO | G27: MIXTO | H27: NO | I27: NO | J27: Toma el primer parcial escrito y el segundo oral. Hay posiciones encontradas y comentarios negativos acerca del trato del cuerpo docente con estudiantes. No recomendada | K27: =VLOOKUP(A27,CORTE!$A$2:$B$1045,2,0)
A28: 7924 | B28: KIPER-FAJRE JOSE | C28: LU-JU | D28: VIRTUAL | E28: 17:00-18:30 | F28: MEDIO | G28: MULTIPLECHOICE | H28: NO | I28: NO | J28: Muy recomendada. Parciales presenciales. Son dos parciales MC, las que estan mal restan, las que estan bien suman. Las clases estan buenas, son completas y con mucha participación del alumno. Dan buen material y exámenes de practica. | K28: =VLOOKUP(A28,CORTE!$A$2:$B$1045,2,0)
A29: 7925 | B29: KIPER-G.SILVANO | C29: LU-JU | D29: PRESENCIAL | E29: 17:00-18:30 | F29: MEDIO | G29: ESCRITO | J29: Recomendada. Muy buenos profesores. Los parciales son escritos a desarrollar sencillos. Muy pro alumno. | K29: =VLOOKUP(A29,CORTE!$A$2:$B$1045,2,0)
A30: 7926 | B30: KIPER-RODRIGUEZ JUAN | C30: MA-VI | D30: PRESENCIAL | E30: 17:00-18:30 | F30: ALTO | G30: ORAL | I30: NO | J30: Cátedra exigente pero muy buena. Los profesores explican muy bien y se aprende | K30: =VLOOKUP(A30,CORTE!$A$2:$B$1045,2,0)
A31: 7955 | B31: PERALTA MARISCAL-ROSENBROCK LAMBOIS | C31: MI | D31: PRESENCIAL | E31: 17:00-20:00 | F31: MEDIO | G31: MIXTO | I31: NO | J31: Las clases con el doctor Javier son muy entretenidas. Evalúan con dos parciales. El primero multiple choice y preguntas a desarrollar. El segundo es un oral, muy tranquilo. Se aprende muchísimo. | K31: =VLOOKUP(A31,CORTE!$A$2:$B$1045,2,0)
A32: 7946 | B32: ABREUT-GUTIERREZ S. | C32: LU-JU | D32: PRESENCIAL | E32: 18:30-20:00 | F32: ALTO | G32: MIXTO | J32: Buena cátedra, para aprender. La profe Sandra explica muy bien. Dos parciales. El primer parcial es escrito con un caso, hay que estudiar bien. El segundo es oral. IMPORTANTE: Comisión no abierta en el 1° cuatrimestre. La Facultad exige un mínimo de 8 inscriptos para la apertura de la comisión y la consecuente asignación de aula.
A33: 7915 | B33: CARTA-CURA GRASSI | C33: LU-JU | D33: PRESENCIAL | E33: 18:30-20:00 | F33: MEDIO | G33: ESCRITO | J33: Recomendada. Buenas clases. Los dos parciales son escritos con preguntas a desarrollar | K33: =VLOOKUP(A33,CORTE!$A$2:$B$1045,2,0)
A34: 7917 | B34: A DESIGNAR-PEPE M. | C34: MA-VI | D34: PRESENCIAL | E34: 18:30-20:00 | F34: MEDIO | G34: MIXTO | H34: NO | I34: NO | J34: Toma el primer parcial escrito y el segundo oral. Hay posiciones encontradas y comentarios negativos acerca del trato del cuerpo docente con estudiantes. No recomendada | K34: =VLOOKUP(A34,CORTE!$A$2:$B$1045,2,0)
A35: 7950 | B35: PERALTA MARISCAL-REY MARIANA | C35: LU-JU | D35: VIRTUAL | E35: 18:30-20:00 | F35: ALTO | J35: Cátedra muy exigente. Las profesores explican muy bien, siguen el manual de Mariani de Vidal. Parciales presenciales. Los dos parciales son escritos y las preguntas están relacionadas a un caso. | K35: =VLOOKUP(A35,CORTE!$A$2:$B$1045,2,0)
A36: 7951 | B36: PERALTA MARISCAL-REY MARIANA | C36: MA-VI | D36: VIRTUAL | E36: 18:30-20:00 | F36: ALTO | J36: Cátedra muy exigente. Las profesores explican muy bien, siguen el manual de Mariani de Vidal. Los dos parciales son escritos y las preguntas están relacionadas a un caso. | K36: =VLOOKUP(A36,CORTE!$A$2:$B$1045,2,0)
A37: 7900 | B37: VAZQUEZ G.-MAC DONELL | C37: LU-JU | D37: PRESENCIAL | E37: 18:30-20:00 | F37: MEDIO | G37: ESCRITO | J37: Excelentes profesores, explican muy bien. Toman 2 parciales a desarrollar solo de los temas que se vieron en clase. | K37: =VLOOKUP(A37,CORTE!$A$2:$B$1045,2,0)
A38: 7947 | B38: ABREUT-GAETA | C38: LU-JU | D38: VIRTUAL | E38: 20:00-21:30 | K38: =VLOOKUP(A38,CORTE!$A$2:$B$1045,2,0)
A39: 7918 | B39: CARTA-DOCAMPO MIÑO | C39: MA-VI | D39: PRESENCIAL | E39: 20:00-21:30 | F39: MEDIO | G39: MULTIPLECHOICE | H39: SI | I39: NO | J39: Cátedra llevadera. Los martes toman lista, los viernes de vez en cuando. Son dos parciales MC (50 preguntas V o F y las incorrectas no restan). Los profes son pro-alumno. Pone notas altas. | K39: =VLOOKUP(A39,CORTE!$A$2:$B$1045,2,0)
A40: 7928 | B40: KIPER-RODRIGUEZ JUAN | C40: MA-VI | D40: PRESENCIAL | E40: 20:00-21:30 | F40: ALTO | G40: ORAL | J40: Cátedra exigente pero muy buena. Los profesores explican muy bien y se aprende | K40: =VLOOKUP(A40,CORTE!$A$2:$B$1045,2,0)
A41: 7936 | B41: VAZQUEZ G.-NACUCCHIO JUAN MANUEL | C41: MA-VI | D41: PRESENCIAL | E41: 20:00-21:30 | F41: MEDIO | G41: ORAL | H41: NO | I41: NO | J41: Muy recomendada. Si bien es una materia de bastante contenido los profes apuntan a que se entienda lo fundamental de cada tema. Los parciales son orales toman lo visto en clase. Están siempre predispuestos a responder cualquier consulta. Es importante ir a clase para seguir la materia. Son dos parciales orales. | K41: =VLOOKUP(A41,CORTE!$A$2:$B$1045,2,0)
A42: 7937 | B42: CARTA-DOCAMPO MIÑO | C42: LU-JU | D42: VIRTUAL | E42: 21:30-23:00 | F42: MEDIO | G42: MULTIPLECHOICE | J42: Los dos parciales son MC. Las clases son bastante completas. | K42: =VLOOKUP(A42,CORTE!$A$2:$B$1045,2,0)
A43: 7929 | B43: KIPER-IRIARTE ALEJANDRO | C43: MA-VI | D43: VIRTUAL | E43: 21:30-23:00 | F43: MEDIO | G43: ORAL | I43: NO | J43: Muy recomendada. El profesor Alejandro como Liliana hacen las clases muy llevaderas. Ambos explican muy bien y buscan que todos entiendan. Hay que estudiar pero se aprueba y con notas altas. Dos parciales orales. Toman lo visto en clase. Muy proalumno y muy promocionable.Ponen buenas notas. | K43: =VLOOKUP(A43,CORTE!$A$2:$B$1045,2,0)

Sheet COMERCIAL 
A1: 📚 ELEMENTOS DE DERECHO COMERCIAL - 2º CUATRI 2026 - LA CÁMPORA 📚
A2: N° | B2: COMISIÓN | C2: DÍAS | D2: MODALIDAD | E2: HORARIO | F2: NIVEL | G2: PARCIAL | H2: TOMA LISTA | I2: TOMA TPS | J2: COMENTARIO | K2: CORTE 1° CUATRI | L2: POSTURA
A3: 8770 | B3: FRICK-TAMBUSSI P. | C3: MA-MI-VI | D3: MIXTO | E3: 07:00-08:30 | F3: MEDIO | G3: ESCRITO | I3: SI | J3: Se aprende mucho. Los parciales son presenciales algunas preguntas choice y otras a desarrollar. Las dos profesoras tienen muy buen trato con los alumnos. | K3: =VLOOKUP(A3,CORTE!$A$2:$B$1045,2,0)
A4: 8745 | B4: GENOVESI-GIORGIO M.G. | C4: LU-MI-JU | D4: MIXTO | E4: 07:00-08:30 | F4: MEDIO | G4: ESCRITO | J4: Examen a desarrollar, promocionable, pro alumno | K4: =VLOOKUP(A4,CORTE!$A$2:$B$1045,2,0)
A5: 8700 | B5: CHOMER-TAVERNA | C5: LU-MI-JU | D5: VIRTUAL | E5: 08:30-10:00 | F5: MEDIO | G5: ESCRITO | H5: SI | I5: NO | J5: No la recomiendan, mal trato con los alumnos | K5: =VLOOKUP(A5,CORTE!$A$2:$B$1045,2,0) | L5: CONSERVADORA
A6: 8771 | B6: FRICK-TAMBUSSI P. | C6: MA-MI-VI | D6: VIRTUAL | E6: 08:30-10:00 | F6: MEDIO | G6: MIXTO | H6: SI | I6: SI | J6: Las clases son agradables y las profesoras también, le dan mucha importancia a la asistencia, toda las clases toman lista estrictamente. Se aprende bien el contenido, si estudias bien se promociona. Buena catedra, las docentes son muy cumplidoras en cuanto a horarios, toman lista, dos parciales, con mas o menos 4 multiple choice y 2-3 preguntas a desarrollar, los examenes son presenciales, 1 tp en grupo durante la cursada y obligatorio | K6: =VLOOKUP(A6,CORTE!$A$2:$B$1045,2,0)
A7: 8780 | B7: ALLENDE-ALLENDE | C7: LU-MI-JU | D7: MIXTO | E7: 08:30-10:00 | F7: MEDIO | G7: MULTIPLECHOICE | H7: SI | I7: NO | J7: Buena Cátedra, no hay un manual específico, se usa mucho el CCyCN y leyes especiales. Los profes no explican mal, pero no suelen contestar dudas por mail, las clases virtuales generalmente las da el titular.Toman dos parciales multiple choice y con 1/2 preguntas a desarrollar en pocos renglones, basta estudiar de lo visto en clase y se aprende. | K7: =VLOOKUP(A7,CORTE!$A$2:$B$1045,2,0) | L7: CONSERVADORA
A8: 8800 | B8: PISANI-PISANI | C8: MA-MI-VI | D8: MIXTO | E8: 08:30-10:00 | F8: BAJO | G8: ESCRITO | J8: Pomocionabnle, buen plantel docente. Escritos 50 preguntas a contestar de manera muy concreta pero no te matan, son conceptos básicos. Bastante fácil si leíste el material | K8: =VLOOKUP(A8,CORTE!$A$2:$B$1045,2,0)
A9: 8813 | B9: ROVIRA-FERNANDEZ HECTOR | C9: LU-MI-JU | D9: MIXTO | E9: 08:30-10:00 | F9: BAJO | G9: ESCRITO | I9: SI | J9: Dos parciales escritos, con preguntas a desarrollar y un caso práctico, se pueden usar leyes y el Código. Toman un tp que sube la nota de ambos parciales | K9: =VLOOKUP(A9,CORTE!$A$2:$B$1045,2,0) -> 6,5
A10: 8820 | B10: VITOLO-PELAEZ | C10: MA-MI-VI | D10: MIXTO | E10: 08:30-10:00 | F10: MEDIO | G10: ESCRITO | I10: SI | J10: Hay opiniones encontradas. En el equipo docente tenés buenos y malos profesores. Arman un classroom donde suben pdf de guía con lo dado en clases y videos también de alguna clase grabada o de Vitolo explicando algún tema. Se usa un solo libro con que el podes complementar y está todo lo del temario también Toman tps por Google forms.Dos parciales escritos con preguntas puntuales, arman un classroom con todo lo visto en clase, recomendable. | K10: =VLOOKUP(A10,CORTE!$A$2:$B$1045,2,0)
A11: 8701 | B11: CHOMER-TAVERNA | C11: LU-MI-JU | D11: VIRTUAL | E11: 10:00-11:30 | F11: MEDIO | G11: ESCRITO | H11: SI | I11: NO | J11: No la recomiendan, mal trato con los alumnos | K11: =VLOOKUP(A11,CORTE!$A$2:$B$1045,2,0) | L11: CONSERVADORA
A12: 8726 | B12: FRICK-FALASCA | C12: MA-MI-VI | D12: MIXTO | E12: 10:00-11:30 | F12: BAJO | G12: ESCRITO | J12: Desorganizado, no tienen buena predisposición en las clases. Dos parciales con preguntas a desarrollar de lo visto en clase, tranqui
A13: 8760 | B13: MIZRAJI-DIGHERO | C13: LU-MI-JU | D13: MIXTO | E13: 10:00-11:30 | F13: MEDIO | G13: ESCRITO | H13: SI | I13: SI | J13: Toma dos parciales a desarrollar, con 5 preguntas puntuales. Muy buenas referencias de la profesora Miriam Caudullo | K13: =VLOOKUP(A13,CORTE!$A$2:$B$1045,2,0)
A14: 8791 | B14: PAOLANTONIO-BRESCA | C14: MA-MI-VI | D14: MIXTO | E14: 10:00-11:30 | F14: MEDIO | G14: MIXTO | H14: NO | I14: NO | J14: Recomendable, dan clases las dos profesoras y las ayudantes, tienen buena predisposición a responder cualquier duda. Toman dos parciales con preguntas, casos y multiple choice. El cuatrimestre pasado también tomaron uno de contratos pero no se sabe si lo van a repetir. | K14: =VLOOKUP(A14,CORTE!$A$2:$B$1045,2,0) | L14: TECNICA
A15: 8801 | B15: PISANI-PISANI | C15: MA-MI-VI | D15: MIXTO | E15: 10:00-11:30 | F15: MEDIO | G15: ESCRITO | I15: SI | J15: Toma trabajos prácticos todas las semanas. Recomendable, parciales de 30-40 preguntas que se responden con un renglón, los tps van con nota concepto. Usan el manual de Pisani y hay clases grabadas en youtube | K15: =VLOOKUP(A15,CORTE!$A$2:$B$1045,2,0)
A16: 8761 | B16: MIZRAJI-DIGHERO | C16: LU-MI-JU | D16: MIXTO | E16: 10:00-11:30 | F16: MEDIO | G16: ESCRITO | H16: SI | I16: SI | J16: Toma dos parciales a desarrollar, con 5 preguntas puntuales. Muy buenas referencias de la profesora Miriam Caudullo | K16: =VLOOKUP(A16,CORTE!$A$2:$B$1045,2,0)
A17: 8821 | B17: VITOLO-BENITEZ | C17: LU-MI-JU | D17: MIXTO | E17: 10:00-11:30 | F17: MEDIO | G17: MULTIPLECHOICE | J17: Evalúan con tres parciales los tres igual modalidad (mc) no hay que conectarse al meet. Los recuperatorios son orales y son muy exigentes. Muy promocionable y son pro alumnos | K17: =VLOOKUP(A17,CORTE!$A$2:$B$1045,2,0) -> 6,36
A18: 8720 | B18: FAVIER D-ARALDI | C18: MA-MI-VI | D18: VIRTUAL | E18: 11:30-13:00 | F18: MEDIO | G18: ESCRITO | I18: NO | J18: Pro alumno. Es dinámica y promocionable pero te deja una buena base para cuando hagas sociedades y quiebras | K18: =VLOOKUP(A18,CORTE!$A$2:$B$1045,2,0) -> 5,4
A19: 8790 | B19: PAOLANTONIO-BRESCA | C19: MA-MI-VI | D19: MIXTO | E19: 11:30-13:00 | F19: MEDIO | G19: MIXTO | H19: NO | I19: SI | J19: El cuerpo docente es pro alumno y hacen las clases dinámicas porque es mucho contenido. Para regularizar la cursada te dan un tp con su respectiva defenza oral. 2 exámenes y un tp grupal | K19: =VLOOKUP(A19,CORTE!$A$2:$B$1045,2,0)
A20: 8773 | B20: FRICK-CASTROGIOVA | C20: LU-MI-JU | D20: MIXTO | E20: 14:00-15:30 | F20: MEDIO | G20: ESCRITO | H20: SI | J20: Super ordenada, pro alumno. Toman lista y dejaron gente sin rendir por las faltas. Super buena explican bien toman en los parciales lo que dicen super pro alumno ,ordenada y aprendes mucho. Los dos parciales son a desarrollar 4 preguntas puntuales y cortas. | K20: =VLOOKUP(A20,CORTE!$A$2:$B$1045,2,0)
A21: 8781 | B21: ALLENDE-CULTRARO G. | C21: LU-MI-JU | D21: MIXTO | E21: 14:00-15:30 | F21: ALTO | G21: MIXTO | J21: No recomendada. Muy exigentes, aprueban pocos, ponen notas bajas. Bibliografía abierta. Primer parcial, preguntas a desarrollar. Segundo parcial, MC. | K21: =VLOOKUP(A21,CORTE!$A$2:$B$1045,2,0)
A22: 8750 | B22: PIEDECASAS-FERNÁNDEZ MARÍA A. | C22: LU-MI-JU | D22: VIRTUAL | E22: 14:00-15:30 | F22: MEDIO | G22: ORAL | J22: No recomendada. Cátedra desorganizada, no tienen cronograma. Los docentes son muchos, cuesta seguirles el hilo y desincentivan la participación y despejar dudas por los malos tratos.En los exámenes NO ponen buenas notas. Son tres parciales orales y dependiendo del docente que te toque va a ser más facil o mucho mas difícil. Son muy arbitrarios a la hora de poner las notas | K22: =VLOOKUP(A22,CORTE!$A$2:$B$1045,2,0)
A23: 8825 | B23: FRICK-MORCECIAN | C23: MA-MI-VI | D23: MIXTO | E23: 15:30-17:00 | F23: ALTO | G23: ESCRITO | H23: NO | I23: NO | J23: Muy recomendada. El profesor Morcecian y los profesofes tienen muy buen trato con los alumnos, siempre contestan los mails, sacan las dudas en clase. Siguen bien el cronograma. Evalúan lo visto en clase y son muy pro-alumno. Los dos parciales son escritos con preguntas teóricas concretas. Los recuperatorios son escritos aunque a algunos les tomaron oral. El final es oral. // Muy buena cátedra, los profesores muy buenos y copados, hacen que te guste la materia, dos parciales uno a desarrollar y otro múltiple choice, son exigentes para corregir, no ponen notas muy altas pero tampoco te matan. no tiene trabajo prácticos y tomaban lista los primeros días nada más | K23: =VLOOKUP(A23,CORTE!$A$2:$B$1045,2,0) | L23: TECNICA
A24: 8730 | B24: GEBHARDT-GÜERRI | C24: LU-MI-JU | D24: MIXTO | E24: 15:30-17:00 | F24: MEDIO | G24: ESCRITO | J24: Los profes no siguen el cronograma, no podes perderte ninguna clase porque toman todo y sólo lo visto en clase. Pro alumno. Evalúan con dos parciales a desarrollar | K24: =VLOOKUP(A24,CORTE!$A$2:$B$1045,2,0)
A25: 8824 | B25: GEBHARDT-ROBLEDO MARIA JOSE | C25: LU-MI-JU | D25: MIXTO | E25: 15:30-17:00 | F25: MEDIO | G25: MIXTO | J25: La profesora María José da buenas clases y tiene muy buen trato con los alumnos. Los parciales son escritos a desarrollar y MC. Hay que estudiar pero es aprobable | K25: =VLOOKUP(A25,CORTE!$A$2:$B$1045,2,0)
A26: 8740 | B26: GENOVESI-SANCHEZ C | C26: MA-MI-VI | D26: MIXTO | E26: 15:30-17:00 | F26: MEDIO | G26: ESCRITO | H26: SI | I26: NO | J26: 2 parciales escritos con preguntas a desarrollar. Suben el contenido al campus. 2 días presencial y uno virtual. Cátedra organizada tienen un pp para cada tema que dan. | K26: =VLOOKUP(A26,CORTE!$A$2:$B$1045,2,0) | L26: APERTURA
A27: 8803 | B27: PISANI-FERRO | C27: LU-MI-JU | D27: MIXTO | E27: 15:30-17:00 | F27: MEDIO | G27: MIXTO | J27: Clases completas, buena llegada a los estudiantes. El primer parcial fue a desarrollar y el segundo MC. Comisión no abierta en el 1° cuatrimestre. La Facultad exige un mínimo de 8 inscriptos para la apertura de la comisión y la consecuente asignación de aula.
A28: 8810 | B28: ROVIRA-FARINATI | C28: MA-MI-VI | D28: MIXTO | E28: 15:30-17:00 | F28: ALTO | G28: ESCRITO | H28: SI | I28: NO | J28: Parciales escritos y un recu de uno solo a final de cuatri. Las clases son pesadas | K28: =VLOOKUP(A28,CORTE!$A$2:$B$1045,2,0)
A29: 8822 | B29: VITOLO-DALESSIO | C29: LU-MI-JU | D29: MIXTO | E29: 15:30-17:00 | F29: ALTO | G29: MIXTO | H29: SI | J29: Muy recomendable. El profesor Dalessio explica muy claro. Es exigente pero promocionable. Los parciales son presenciales. El primero a desarrollar, el segundo mc y el terceros un caso y mc. El 20% de la nota es participación en clase, y lo respeta tanto para subir como bajar nota. Toma lista, pero no dejo a nadie sin rendir por eso. | K29: =VLOOKUP(A29,CORTE!$A$2:$B$1045,2,0)
A30: 8721 | B30: FAVIER D-LEFEVRE ROSANA | C30: LU-MI-JU | D30: MIXTO | E30: 17:00-18:30 | F30: MEDIO | G30: MIXTO | H30: SI | I30: SI | J30: Tomaron 2 parciales, el primero fue V o F justificando las falsas, un anagrama y una parte multiple choice. El segundo parcial fue un caso práctico corto, V o F con justificación y un cuadro comparativo sobre contratos, en este daban recuperatorio para levantar nota y promocionar. También hacen tps grupales pero es para participar en clase, principalmente en la primera parte de la materia, no evalúa con nota. Los recuperatorios siguen la modalidad de los parciales y el final es oral. Toman el presente pasando una hoja para anotarse. Dieron el material por el campus, las clases virtuales las graban y las suben, las profesoras son muy organizadas. Hacen clase de repaso y están siempre a disposición para resolver dudas. Hay que estar al día porque es una materia muy pesada. | K30: =VLOOKUP(A30,CORTE!$A$2:$B$1045,2,0)
A31: 8732 | B31: GEBHARDT-ROBLEDO MARÍA JOSÉ | C31: LU-MI-JU | D31: MIXTO | E31: 17:00-18:30 | F31: MEDIO | G31: ESCRITO | I31: SI | J31: Recomendada. Promocionable. La profesora María José es muy buena y muy amable, da los temas bien explicados, y sus ayudantes igual. Dan 3 o 4 tps (no obligatorios, pero que suben nota) y evalúan con 2 parciales escritos con preguntas a desarrollar, v o f y justificación. Se recomienda totalmente ir a las clases y preguntar cualquier duda porque son la mejor fuente de información dado que no se guía por ningún manual en particular, aunque recomiendan algunos para complementar. | K31: =VLOOKUP(A31,CORTE!$A$2:$B$1045,2,0) -> 7,16 | L31: TECNICA
A32: 8804 | B32: PISANI-COSENTINO J. | C32: MA-MI-VI | D32: MIXTO | E32: 17:00-18:30 | F32: BAJO | G32: ESCRITO | H32: SI | I32: NO | J32: Los profesores son muy buenos, y valoran la participación en clase. Aclaran todas las dudas y son didácticos. Los exámenes son presenciales. Promocionable. Dos parciales con casos y preguntas teóricas. | K32: =VLOOKUP(A32,CORTE!$A$2:$B$1045,2,0)
A33: 8712 | B33: CHOMER-ETCHEVERRY | C33: MA-MI-VI | D33: MIXTO | E33: 18:30-20:00 | F33: MEDIO | G33: ESCRITO | J33: Cátedra desorganizada. El programa es muy largo, no lo dan completo y lo toman todo igual. Los parciales son de 2 o 3 preguntas a desarrollar. | K33: =VLOOKUP(A33,CORTE!$A$2:$B$1045,2,0)
A34: 8722 | B34: FAVIER D-LUCHINSKY | C34: MA-MI-VI | D34: VIRTUAL | E34: 18:30-20:00 | F34: ALTO | G34: MULTIPLECHOICE | J34: Cátedra para aprender, exigente, buenos profesores, los parciales son MC virtuales | K34: =VLOOKUP(A34,CORTE!$A$2:$B$1045,2,0) -> 7,16
A35: 8742 | B35: GENOVESI-CRESPO PEDRO | C35: MA-MI-VI | D35: MIXTO | E35: 18:30-20:00 | F35: MEDIO | G35: ESCRITO | H35: NO | I35: NO | J35: Recomendable, los profesores explican bien y facilitan el material. Los parciales son virtuales, multiple choice y casos | K35: =VLOOKUP(A35,CORTE!$A$2:$B$1045,2,0) -> 7,11
A36: 8743 | B36: GENOVESI-D ALESANDRO | C36: MA-MI-VI | D36: MIXTO | E36: 18:30-20:00 | F36: MEDIO | G36: ESCRITO | J36: Los profesores explican bien, son tres parciales de 5/10 preguntas a desarrollar | K36: =VLOOKUP(A36,CORTE!$A$2:$B$1045,2,0)
A37: 8741 | B37: GENOVESI-GUZMAN A. | C37: LU-MI-JU | D37: MIXTO | E37: 18:30-20:00 | F37: MEDIO | G37: MIXTO | J37: Primer parcial escrito, segundo coloquio, hay que llevar al día la lectura, promocionable | K37: =VLOOKUP(A37,CORTE!$A$2:$B$1045,2,0)
A38: 8751 | B38: PIEDECASAS-FERNÁNDEZ MARÍA A. | C38: LU-MI-JU | D38: MIXTO | E38: 18:30-20:00 | F38: MEDIO | G38: ORAL | H38: NO | J38: Cátedra recomendada y promocionable. Evalúan con tres parciales orales presenciales, no usan manual, sólo el código y las leyes (defensa consumidor, concursos y quiebras). pero evalúan únicamente lo que dan en las clases así que hay que asistir. En las clases explican con casos en los que trabajaron ellos. La clases con la profesora Fernández son pesadas pero los exámenes con ella son fáciles y suele poner notas altas. Las otras profesoras preguntan más cosas y la complican un poco más. | K38: =VLOOKUP(A38,CORTE!$A$2:$B$1045,2,0)
A39: 8811 | B39: ROVIRA-FARINATI | C39: MA-MI-VI | D39: MIXTO | E39: 18:30-20:00 | J39: NO recomendada. No cumplieron con el reglamento; no permitieron recuperatorio del primer parcial, solo del segundo. Hay profesores con mala llegada a los alumnos. | K39: =VLOOKUP(A39,CORTE!$A$2:$B$1045,2,0)
A40: 8752 | B40: GEBHARDT-LLORENTE S. | C40: MA-MI-VI | D40: MIXTO | E40: 20:00-21:30 | F40: MEDIO | G40: ESCRITO | J40: No recomendada. Cátedra MUY desorganizada. No te dan cronograma, ni dieron lista de temas para preparar los parciales. Avisaban una semana antes cuando era el parcial. Ponen notas bajas. | K40: =VLOOKUP(A40,CORTE!$A$2:$B$1045,2,0)
A41: 8746 | B41: GENOVESI-ANGELOTTI DANIEL | C41: LU-MI-JU | D41: MIXTO | E41: 20:00-21:30 | F41: MEDIO | G41: ESCRITO | H41: SI | I41: SI | J41: Cátedra pro alumno. Toman lo que dan en clase y los profes tienen buen trato con los alumnos. Hay tres tps que se hacen en clase los miércoles por Google forms con el material a mano | K41: =VLOOKUP(A41,CORTE!$A$2:$B$1045,2,0)
A42: 8744 | B42: GENOVESI-HANSEN | C42: MA-MI-VI | D42: MIXTO | E42: 20:00-21:30 | F42: BAJO | G42: ESCRITO | H42: SI | J42: Los dos parciales son con preguntas a desarrollar. Son 3 o 4 muy concretas y faciles. Toman asistencia pero para control suyo, no te dan de baja. Toman lo visto únicamente en clase | K42: =VLOOKUP(A42,CORTE!$A$2:$B$1045,2,0)
A43: 8812 | B43: ROVIRA-LUCHINSKY | C43: MA-MI-VI | D43: MIXTO | E43: 20:00-21:30 | F43: BAJO | G43: ESCRITO | I43: SI | J43: Parciales virtuales. Primer parcial virtual y antes del segundo parcial dieron un tp MC que si lo aprobabas te eximia del segundo parcial y te quedaba el promedio del primer parcial y el MC. Tomas solo lo visto en clase. Dan mucho tp en la primer parte de la materia. La predisposición de los docentes con los alumnos es muy buena. Las clases son dinámicas y entretenidas. Se aprende mucho, estudiando y siguiendo la materia es MUY promocionable. No se sigue un manual y por lo general pasan muchísimo material. los recomiendo, sobre todo si hacen varias materias a la vez. es muy amena. Varios tps-2 parciales | K43: =VLOOKUP(A43,CORTE!$A$2:$B$1045,2,0) -> 6,96
A44: 8702 | B44: CHOMER-SICOLI | C44: MA-MI-VI | D44: MIXTO | E44: 21:30-23:00 | F44: MEDIO | G44: ESCRITO | J44: Las clases no son buenas, no se explican los temas que evalúan y tenés que estudiar por tu cuenta. Antes del parcial envian un cuestionario con preguntas (extenso) y toma eso. Los parciales son escritos a desarrollar | K44: =VLOOKUP(A44,CORTE!$A$2:$B$1045,2,0)
A45: 8823 | B45: VITOLO-STORDEUR | C45: LU-MI-JU | D45: MIXTO | E45: 21:30-23:00 | F45: MEDIO | G45: ESCRITO | H45: NO | I45: NO | J45: Contestan dudas en clase. No suben material al campus. Los parciales son a desarrollar y tienen buena predisposición. No toman lista ni toman TPs | K45: =VLOOKUP(A45,CORTE!$A$2:$B$1045,2,0)

Sheet PROCESAL
A1: 📚 ELEMENTOS DE DERECHO PROCESAL CIVIL Y COMERCIAL - 2º CUATRI 2026 - LA CÁMPORA 📚
A2: N° | B2: COMISIÓN | C2: DÍAS | D2: MODALIDAD | E2: HORARIO | F2: NIVEL | G2: PARCIAL | H2: TOMA LISTA | I2: TOMA TPS | J2: COMENTARIO | K2: CORTE 1° CUATRI | L2: POSTURA
A3: 7400 | B3: D.SOLIMINE-MONTALDO | C3: MA-VI | D3: VIRTUAL | E3: 07:00-08:30 | F3: ALTO | G3: ORAL | H3: SI | I3: SI | J3: Son exigentes en clases y con la presencialidad. Hacen preguntas en clases para ver si están al día los estudiantes. Toman TP obligatorios y se tienen que rehacer si están mal hechos. | K3: =VLOOKUP(A3,CORTE!$A$2:$B$1045,2,0)
A4: 7412 | B4: GOZAINI-GOBEL KARIN | C4: LU-JU | D4: PRESENCIAL | E4: 07:00-08:30 | F4: MEDIO | G4: MULTIPLECHOICE | H4: SI | I4: NO | J4: Muy estricta con las faltas. Son dos parciales choice y generalmente aprueban todos. Con el Codigo Procesal se puede aporbar. | K4: =VLOOKUP(A4,CORTE!$A$2:$B$1045,2,0) | L4: CONSERVADORA
A5: 7411 | B5: GOZAINI-PULICE S. | C5: MA-VI | D5: PRESENCIAL | E5: 07:00-08:30 | F5: MEDIO | G5: MIXTO | H5: SI | I5: SI | J5: 2 parciales escritos para desarrollar y con multiple choice (a veses toman un parcial escrito y otro oral), 2 TP grupales. Son pro alumnos, las clases son amenas y los profes responden todas las dudas. | K5: =VLOOKUP(A5,CORTE!$A$2:$B$1045,2,0) | L5: TECNICA
A6: 7401 | B6: D.SOLIMINE-MONTALDO | C6: MA-VI | D6: VIRTUAL | E6: 08:30-10:00 | F6: ALTO | G6: ORAL | H6: SI | I6: SI | J6: Son exigentes en clases y con la presencialidad. Hacen preguntas en clases para ver si están al día los estudiantes. Toman TP olbigatorios y se tienen que rehacer si están mal hechos. | K6: =VLOOKUP(A6,CORTE!$A$2:$B$1045,2,0)
A7: 7410 | B7: GOZAINI-GOBEL KARIN | C7: LU-JU | D7: PRESENCIAL | E7: 08:30-10:00 | F7: MEDIO | G7: MULTIPLECHOICE | H7: SI | I7: NO | J7: Muy estricta con las faltas. Son dos parciales choice y generalmente aprueban todos. Con el Codigo Procesal se puede aporbar. | K7: =VLOOKUP(A7,CORTE!$A$2:$B$1045,2,0) | L7: CONSERVADORA
A8: 7413 | B8: GOZAINI-PULICE S. | C8: MA-VI | D8: PRESENCIAL | E8: 08:30-10:00 | F8: MEDIO | G8: MIXTO | H8: SI | I8: SI | J8: 2 parciales escritos para desarrollar y con multiple choice (a veses toman un parcial escrito y otro oral), 2 TP grupales. Son pro alumnos, las clases son amenas y los profes responden todas las dudas. | K8: =VLOOKUP(A8,CORTE!$A$2:$B$1045,2,0) | L8: TECNICA
A9: 7420 | B9: KIELMANOVICH-SELTZER | C9: LU-JU | D9: PRESENCIAL | E9: 08:30-10:00 | F9: ALTO | G9: ESCRITO | H9: SI | I9: SI | J9: Los profesores mandan audios con las clases grabadas que hay que escuchar antes de cada clase, son exigentes con eso, les gusta la participación en clase. Toman dos parciales escritos a libro abierto (con los apuntes, fotocopias, Código, todo) y un tp en el que hay que redactar una contestación sin nota, para mantener la regularidad. | K9: =VLOOKUP(A9,CORTE!$A$2:$B$1045,2,0) -> 7,36 | L9: TECNICA
A10: 7430 | B10: LEDESMA-ACERBO | C10: LU-JU | D10: PRESENCIAL | E10: 08:30-10:00 | F10: MEDIO | G10: ESCRITO | H10: SI | I10: SI | J10: Toman dos parciales escritos para desarrollar con casos practicos. Se toman TPs individuales a lo largo de la cursada para hacer contestaciones, alegatos y demandas y al final de la cursada hay un simulacro de audiencia en grupos. | K10: =VLOOKUP(A10,CORTE!$A$2:$B$1045,2,0) | L10: CONSERVADORA
A11: 7431 | B11: LEDESMA-ACERBO | C11: MA-VI | D11: PRESENCIAL | E11: 08:30-10:00 | F11: MEDIO | G11: ESCRITO | H11: SI | I11: SI | J11: Toman dos parciales escritos para desarrollar con casos practicos. Se toman TPs individuales a lo largo de la cursada para hacer contestaciones, alegatos y demandas y al final de la cursada hay un simulacro de audiencia en grupos. | K11: =VLOOKUP(A11,CORTE!$A$2:$B$1045,2,0) | L11: CONSERVADORA
A12: 7441 | B12: ROJAS-MORENO ROMINA | C12: MA-VI | D12: PRESENCIAL | E12: 08:30-10:00 | F12: MEDIO | G12: MIXTO | H12: SI | I12: SI | J12: Dos parciales para desarrollar y con multiple choice. Ademas hay 4 TPs en grupo sobre redaccion de demandas y contestacion. Se aprende mucho y las clases son llevaderas. | K12: =VLOOKUP(A12,CORTE!$A$2:$B$1045,2,0) | L12: CONSERVADORA
A13: 7440 | B13: ROJAS-NUÑEZ ANGEL | C13: LU-JU | D13: PRESENCIAL | E13: 08:30-10:00 | F13: MEDIO | G13: ESCRITO | H13: SI | I13: SI | J13: Las clases son super entendibles aunque a veces dan mucho material, lo que no se entiende queda explicado en el manual. Hay 4 TPs para mantener la regularidad, redaccion de demanda, contestacion, pliego y finalmente una clase practica sobre una simulacion de audiencia. Los parciales son 7 preguntas a desarrollar, los finales y recus son orales. | K13: =VLOOKUP(A13,CORTE!$A$2:$B$1045,2,0)
A14: 7402 | B14: D.SOLIMINE-NANINI S. | C14: MA-VI | D14: PRESENCIAL | E14: 10:00-11:30 | F14: BAJO | G14: ESCRITO | I14: NO | J14: Catedra pro alumnos. Se toman dos parciales escritos sobre lo visto en clase. | K14: =VLOOKUP(A14,CORTE!$A$2:$B$1045,2,0) -> 7,07
A15: 7421 | B15: KIELMANOVICH-SELTZER | C15: LU-JU | D15: PRESENCIAL | E15: 10:00-11:30 | F15: ALTO | G15: ESCRITO | H15: SI | I15: SI | J15: Los profesores mandan audios con las clases grabadas que hay que escuchar antes de cada clase, son exigentes con eso, les gusta la participación en clase. Toman dos parciales escritos a libro abierto (con los apuntes, fotocopias, Código, todo) y un tp en el que hay que redactar una contestación sin nota, para mantener la regularidad. | K15: =VLOOKUP(A15,CORTE!$A$2:$B$1045,2,0) -> 6,91 | L15: TECNICA
A16: 7443 | B16: ROJAS-MORENO ROMINA | C16: MA-VI | D16: PRESENCIAL | E16: 10:00-11:30 | F16: MEDIO | G16: MIXTO | H16: SI | I16: SI | J16: Dos parciales para desarrollar y con multiple choice. Ademas hay 4 TPs en grupo sobre redaccion de demandas y contestacion. Se aprende mucho y las clases son llevaderas. // Cátedra exigente, muy buenas clases, Buenos profesores. Hay 4 tp donde se hacen demandas, se contestan y por último se corrigen. Ambos parciales escritos, no hay dificultades pero son rigurosos con la corrección. Recuperatorio es 3 puntos múltiple choice y una pregunta conceptual. Cátedra para aprender. Se estudia del manual de Rojas que es muy bueno. Son exigente con la asistencia | K16: =VLOOKUP(A16,CORTE!$A$2:$B$1045,2,0) | L16: CONSERVADORA
A17: 7442 | B17: ROJAS-NUÑEZ ANGEL | C17: LU-JU | D17: PRESENCIAL | E17: 10:00-11:30 | F17: MEDIO | G17: ESCRITO | H17: SI | I17: SI | J17: Las clases son super entendibles aunque a veces dan mucho material, lo que no se entiende queda explicado en el manual. Hay 4 TPs para mantener la regularidad, redaccion de demanda, contestacion, pliego y finalmente una clase practica sobre una simulacion de audiencia. Los parciales son 7 preguntas a desarrollar, los finales y recus son orales. | K17: =VLOOKUP(A17,CORTE!$A$2:$B$1045,2,0)
A18: 7403 | B18: D.SOLIMINE-NANINI S. | C18: MA-VI | D18: PRESENCIAL | E18: 11:30-13:00 | F18: BAJO | G18: ESCRITO | I18: NO | J18: Catedra pro alumnos. Se toman dos parciales escritos sobre lo visto en clase. | K18: =VLOOKUP(A18,CORTE!$A$2:$B$1045,2,0) -> 6,24
A19: 7414 | B19: GOZAINI-RODRIGUEZ FABIOLA | C19: MA-VI | D19: PRESENCIAL | E19: 11:30-13:00 | F19: ALTO | G19: ORAL | I19: NO | J19: Es exigente pero los profesores explican bien y terminas saliendo entendiendo la materia. La profesora es litigante. | K19: =VLOOKUP(A19,CORTE!$A$2:$B$1045,2,0) | L19: TECNICA
A20: 7422 | B20: KIELMANOVICH-QUIROZ | C20: LU-JU | D20: PRESENCIAL | E20: 11:30-13:00 | F20: MEDIO | G20: ESCRITO | I20: NO | J20: Las clases no son muy buenas, el profesor nunca termina de redondear la idea, suelen ser clases densas. Se dan algunas clases practicas y se muestra como funciona el sistema judicial. Recu oral. | K20: =VLOOKUP(A20,CORTE!$A$2:$B$1045,2,0) | L20: CONSERVADORA
A21: 7415 | B21: GOZAINI-RODRIGUEZ FABIOLA | C21: MA-VI | D21: PRESENCIAL | E21: 13:00:14:30 | F21: ALTO | G21: ORAL | I21: NO | J21: Es exigente pero los profesores explican bien y terminas saliendo entendiendo la materia. La profesora es litigante. | K21: =VLOOKUP(A21,CORTE!$A$2:$B$1045,2,0) | L21: TECNICA
A22: 7404 | B22: D.SOLIMINE-VILLAGRAN | C22: LU-JU | D22: PRESENCIAL | E22: 14:00-15:30 | F22: MEDIO | G22: ORAL | I22: NO | J22: Se toman parciales orales donde tenés que preparar un tema y hacen un par de preguntas sobre lo visto en clase. Estudiando del codigo complementado con un manual se aprueba. | K22: =VLOOKUP(A22,CORTE!$A$2:$B$1045,2,0) | L22: TECNICA
A23: 7423 | B23: KIELMANOVICH-GUAHNON | C23: LU-JU | D23: PRESENCIAL | E23: 14:00-15:30 | F23: MEDIO | G23: ESCRITO | I23: SI | J23: Toman dos parciales escritos V o F y con un caso para desarrollar. Toman dos TPs uno obligatorio el otro no. Los profesores explican muy bien y contestan todas las dudas. Es exigente pero promocionable. Dejan las clases grabadas. | K23: =VLOOKUP(A23,CORTE!$A$2:$B$1045,2,0) | L23: TECNICA
A24: 7405 | B24: D.SOLIMINE-RODRIGUEZ | C24: MI | D24: PRESENCIAL | E24: 14:00-17:00 | F24: MEDIO | G24: MIXTO | H24: SI | I24: SI | J24: Promocionable, envian TPs semanales. Primer parcial es escrito y el segundo es oral grupal. Postura política de apertura. | K24: =VLOOKUP(A24,CORTE!$A$2:$B$1045,2,0) | L24: APERTURA
A25: 7434 | B25: LEDESMA-D.LOS SANTOS | C25: MI | D25: PRESENCIAL | E25: 14:00-17:00 | F25: MEDIO | G25: ORAL | H25: SI | I25: SI | J25: Se puede cursar bien, es tranquila y si estudias se puede aprobar y promocionar. Las clases estàn bien, no son excelentes pero tampoco son malas. Los parciales no son muy complejos. Los TPs te suman para la nota final. | K25: =VLOOKUP(A25,CORTE!$A$2:$B$1045,2,0) | L25: TECNICA
A26: 7407 | B26: D.SOLIMINE-TAMBORENEA | C26: LU-JU | D26: PRESENCIAL | E26: 15:30-17:00 | F26: MEDIO | G26: MIXTO | H26: SI | I26: SI | J26: muy recomendable, son dos parciales el primero escrito con 4 preguntas a desarrollar, múltiple choice, y v o f. El segundo es oral muy fácil. Las clases las dan los ayudantes matias y melanie, muy predispuestos a responder todas las dudas | K26: =VLOOKUP(A26,CORTE!$A$2:$B$1045,2,0) -> 6,59 | L26: TECNICA
A27: 7406 | B27: D.SOLIMINE-VILLAGRAN | C27: LU-JU | D27: PRESENCIAL | E27: 15:30-17:00 | F27: MEDIO | G27: ORAL | I27: NO | J27: Se toman parciales orales donde tenés que preparar un tema y hacen un par de preguntas sobre lo visto en clase. Estudiando del codigo complementado con un manual se aprueba. | K27: =VLOOKUP(A27,CORTE!$A$2:$B$1045,2,0) | L27: TECNICA
A28: 7416 | B28: GOZAINI-CAEIRO MARIA | C28: MA-VI | D28: PRESENCIAL | E28: 15:30-17:00 | F28: ALTO | G28: MIXTO | H28: SI | I28: SI | J28: Parciales exigentes, el primero es escrito con preguntas y un caso practico, el segundo es oral. Toma un TP que consiste en armar una demanda. Los profes explican muy bien pero son exigentes. | K28: =VLOOKUP(A28,CORTE!$A$2:$B$1045,2,0) | L28: TECNICA
A29: 7424 | B29: KIELMANOVICH-GUAHNON | C29: LU-JU | D29: PRESENCIAL | E29: 15:30-17:00 | F29: MEDIO | G29: ESCRITO | I29: SI | J29: Toman dos parciales escritos V o F y con un caso para desarrollar. Toman dos TPs uno obligatorio el otro no. Los profesores explican muy bien y contestan todas las dudas. Es exigente pero promocionable. Dejan las clases grabadas. | K29: =VLOOKUP(A29,CORTE!$A$2:$B$1045,2,0) | L29: TECNICA
A30: 7432 | B30: LEDESMA-VALDEZ | C30: LU-JU | D30: PRESENCIAL | E30: 15:30-17:00 | F30: MEDIO | G30: ESCRITO | H30: SI | I30: SI | J30: 2 parciales escritos para desarrollar con recuperatorios que pueden ser escritos u orales. Toman lista a veces. Hay un TP al final de simulacion de audiencia. La profe hace preguntas todas las clases para ver que este en tema. No pone notas altas pero es promocionable. | K30: =VLOOKUP(A30,CORTE!$A$2:$B$1045,2,0)
A31: 7433 | B31: LEDESMA-VALDEZ | C31: MA-VI | D31: PRESENCIAL | E31: 15:30-17:00 | F31: MEDIO | G31: ESCRITO | H31: SI | I31: SI | J31: 2 parciales escritos para desarrollar con recuperatorios que pueden ser escritos u orales. Toman lista a veces. Hay un TP al final de simulacion de audiencia. La profe hace preguntas todas las clases para ver que este en tema. No pone notas altas pero es promocionable. | K31: =VLOOKUP(A31,CORTE!$A$2:$B$1045,2,0) -> 6,61
A32: 7444 | B32: ROJAS-PAGES | C32: LU-JU | D32: PRESENCIAL | E32: 15:30-17:00 | F32: MEDIO | J32: Material accesible y los profes explican bien. Comisión no abierta en el 1° cuatrimestre. La Facultad exige un mínimo de 8 inscriptos para la apertura de la comisión y la consecuente asignación de aula. | K32: =VLOOKUP(A32,CORTE!$A$2:$B$1045,2,0)
A33: 7417 | B33: GOZAINI-CAEIRO MARIA | C33: MA-VI | D33: PRESENCIAL | E33: 17:00-18:30 | F33: ALTO | G33: MIXTO | H33: SI | I33: SI | J33: Parciales exigentes, el primero es escrito con preguntas y un caso practico, el segundo es oral. Toma un TP que consiste en armar una demanda. Los profes explican muy bien pero son exigentes. | K33: =VLOOKUP(A33,CORTE!$A$2:$B$1045,2,0) | L33: TECNICA
A34: 7425 | B34: KIELMANOVICH-SOMER | C34: LU-JU | D34: VIRTUAL | E34: 17:00-18:30 | F34: MEDIO | G34: ORAL | H34: SI | I34: SI | J34: Los parciales son orales grupales se toman en la facultad en el horario de clases, se toma lo visto en las clases y de los PowerPoints que mandan. Se aprende bastante y los profes son muy buenas explicando. No es sencilla pero es promocionable. Durante las clases te piden que tengas la camara prendida. Hay un TP no obligatorio en el medio de la carsudad de una simulacion de audiencia | K34: =VLOOKUP(A34,CORTE!$A$2:$B$1045,2,0)
A35: 7429 | B35: KIELMANOVICH-SOMER | C35: LU-JU | D35: VIRTUAL | E35: 17:00-18:30 | F35: MEDIO | G35: ORAL | H35: SI | I35: SI | J35: Los parciales son orales grupales se toman en la facultad en el horario de clases, se toma lo visto en las clases y de los PowerPoints que mandan. Se aprende bastante y los profes son muy buenas explicando. No es sencilla pero es promocionable. Durante las clases te piden que tengas la camara prendida. Hay un TP no obligatorio en el medio de la carsudad de una simulacion de audiencia. | K35: =VLOOKUP(A35,CORTE!$A$2:$B$1045,2,0)
A36: 7435 | B36: LEDESMA-IMATZ | C36: MA-VI | D36: PRESENCIAL | E36: 17:00-18:30 | F36: MEDIO | G36: ORAL | I36: NO | J36: Explican los temas a las apuradas, es aprobable. | K36: =VLOOKUP(A36,CORTE!$A$2:$B$1045,2,0)
A37: 7445 | B37: ROJAS-PAGES | C37: LU-JU | D37: PRESENCIAL | E37: 17:00-18:30 | F37: MEDIO | J37: Material accesible y los profes explican bien | K37: =VLOOKUP(A37,CORTE!$A$2:$B$1045,2,0)
A38: 7446 | B38: ROJAS-SALGADO J. | C38: MA-VI | D38: VIRTUAL | E38: 17:00-18:30 | F38: MEDIO | G38: ESCRITO | I38: NO | J38: Dos parciales escritos con casos practicos con codigo abierto. Las clases son pesadas, se aprueba anotando todos los apuntes posibles. Los profes explican muy bien y suben todo el contenido virtualmente. | K38: =VLOOKUP(A38,CORTE!$A$2:$B$1045,2,0)
A39: 7409 | B39: D.SOLIMINE-RODRIGUEZ | C39: MI | D39: PRESENCIAL | E39: 17:00-20:00 | F39: MEDIO | G39: MIXTO | H39: SI | I39: SI | J39: Promocionable, envian TPs semanales. Primer parcial es escrito y el segundo es oral grupal. Postura política de apertura. | K39: =VLOOKUP(A39,CORTE!$A$2:$B$1045,2,0) | L39: APERTURA
A40: 7408 | B40: D.SOLIMINE-TAMBORENEA | C40: MI | D40: PRESENCIAL | E40: 17:00-20:00 | F40: MEDIO | G40: MIXTO | H40: SI | I40: SI | J40: muy recomendable, son dos parciales el primero escrito con 4 preguntas a desarrollar, múltiple choice, y v o f. El segundo es oral muy fácil. Las clases las dan los ayudantes matias y melanie, muy predispuestos a responder todas las dudas | K40: =VLOOKUP(A40,CORTE!$A$2:$B$1045,2,0) | L40: TECNICA
A41: 7436 | B41: LEDESMA-D.LOS SANTOS | C41: MI | D41: PRESENCIAL | E41: 17:00-20:00 | F41: MEDIO | G41: ORAL | H41: SI | I41: SI | J41: Se puede cursar bien, es tranquila y si estudias se puede aprobar y promocionar. Las clases estàn bien, no son excelentes pero tampoco son malas. Los parciales no son muy complejos. Los TPs te suman para la nota final. | K41: =VLOOKUP(A41,CORTE!$A$2:$B$1045,2,0) | L41: TECNICA
A42: 7426 | B42: KIELMANOVICH-VERDAGUER | C42: MA-VI | D42: PRESENCIAL | E42: 18:30-20:00 | F42: ALTO | G42: MIXTO | H42: NO | I42: SI | J42: Catedra exigente pero aprobable, se mandam muchos TPs en la cursada. Clases presenciales, parcial mitad multiple choice y mitad desarrollar. // NO SE RECOMIENDA. Tardan mucho entregar las notas al finalizar la cursada y pueden trabarte la cursada durante el cuatrimestre siguiente | K42: =VLOOKUP(A42,CORTE!$A$2:$B$1045,2,0) | L42: TECNICA
A43: 7437 | B43: LEDESMA-IMATZ | C43: MA-VI | D43: PRESENCIAL | E43: 18:30-20:00 | F43: MEDIO | G43: ORAL | I43: NO | J43: Explican los temas a las apuradas, es aprobable. | K43: =VLOOKUP(A43,CORTE!$A$2:$B$1045,2,0)
A44: 7439 | B44: LEDESMA-KANDUS | C44: LU-JU | D44: PRESENCIAL | E44: 18:30-20:00 | F44: BAJO | G44: ORAL | I44: NO | J44: Los parciales son orales, sin animo de bochar. Se toma lo visto en clase. Postura política de apertura. | K44: =VLOOKUP(A44,CORTE!$A$2:$B$1045,2,0) -> 6,86 | L44: APERTURA
A45: 7448 | B45: ROJAS-GOMEZ MARIA | C45: LU-JU | D45: PRESENCIAL | E45: 18:30-20:00 | F45: ALTO | G45: MIXTO | H45: NO | I45: SI | J45: Es exigente pero sin animos de bochar. Hay que estar al día. Los parciales tienen preguntas a desarrollar pero no son rebuscados; tambien tienen preguntas multiple choice y se puede usar el manual. Un TP sobre redaccion de demanda. Se usa el manual de Rojas. | K45: =VLOOKUP(A45,CORTE!$A$2:$B$1045,2,0) | L45: TECNICA
A46: 7447 | B46: ROJAS-SALGADO J. | C46: MA-VI | D46: PRESENCIAL | E46: 18:30-20:00 | F46: MEDIO | G46: ESCRITO | I46: NO | J46: Dos parciales escritos con casos practicos con codigo abierto. Las clases son pesadas, se aprueba anotando todos los apuntes posibles. Los profes explican muy bien y suben todo el contenido virtualmente. | K46: =VLOOKUP(A46,CORTE!$A$2:$B$1045,2,0)
A47: 7418 | B47: GOZAINI-MAESA | C47: MA-VI | D47: PRESENCIAL | E47: 20:00-21:30 | F47: ALTO | G47: ESCRITO | I47: NO | J47: Catedra exigente pero las profesoras explican muy bien. Suelen tomar lo visto en clase. | K47: =VLOOKUP(A47,CORTE!$A$2:$B$1045,2,0) | L47: TECNICA
A48: 7427 | B48: KIELMANOVICH-LUBEL | C48: LU-JU | D48: PRESENCIAL | E48: 20:00-21:30 | F48: ALTO | G48: ESCRITO | I48: SI | J48: Dos parciales escrito con preguntas. Tienen un blog donde suben todo el material. Hay 2 TPs obligatorios para hacer una demanda y una contestacion de la misma. Son exigentes pero muy bien organizados. | K48: =VLOOKUP(A48,CORTE!$A$2:$B$1045,2,0) | L48: TECNICA
